Workbook

Sheet Dashboard
A1: Agentic Stability Framework v1.0 - Initial Public Release Dashboard
A2: Portfolio summary for Agentic Force, Enterprise Gravity, Stability Margin, and governance readiness
A4: Metric | B4: Value | D4: Orbit | E4: Count | F4: Default Action
A5: Total Agents | B5: =COUNTA(Assessment!A5:A9) | D5: Stable Orbit | E5: =COUNTIF(Assessment!X2:X100,"Stable Orbit") | F5: Scale with monitoring
A6: Average AFI | B6: =AVERAGE(Assessment!U5:U9) | D6: Controlled Orbit | E6: =COUNTIF(Assessment!X2:X100,"Controlled Orbit") | F6: Proceed with controls
A7: Average EGI | B7: =AVERAGE(Assessment!V5:V9) | D7: Edge Orbit | E7: =COUNTIF(Assessment!X2:X100,"Edge Orbit") | F7: Pilot / limited production
A8: Average SMI | B8: =AVERAGE(Assessment!W5:W9) | D8: Unstable Orbit | E8: =COUNTIF(Assessment!X2:X100,"Unstable Orbit") | F8: Control uplift required
A9: Negative SMI Agents | B9: =COUNTIF(Assessment!W5:W9,"<0") | D9: Critical Orbit | E9: =COUNTIF(Assessment!X2:X100,"Critical Orbit") | F9: Do not deploy
A10: ABOM Missing | B10: =COUNTIF(Assessment!Z5:Z9,"No")
A11: Threat Model Required | B11: =COUNTIF(Assessment!AA5:AA9,"Yes")
A12: Risk Acceptance Required | B12: =COUNTIF(Assessment!AB5:AB104,"Yes")
A15: Agent Snapshot
A16: Agent | B16: Domain | C16: AFI | D16: EGI | E16: SMI | F16: Orbit | G16: Decision | H16: Next Uplift
A17: =Assessment!A5 | B17: =Assessment!B5 | C17: =Assessment!U5 | D17: =Assessment!V5 | E17: =Assessment!W5 | F17: =Assessment!X5 | G17: =Assessment!Y5 | H17: =Assessment!AE5
A18: =Assessment!A6 | B18: =Assessment!B6 | C18: =Assessment!U6 | D18: =Assessment!V6 | E18: =Assessment!W6 | F18: =Assessment!X6 | G18: =Assessment!Y6 | H18: =Assessment!AE6
A19: =Assessment!A7 | B19: =Assessment!B7 | C19: =Assessment!U7 | D19: =Assessment!V7 | E19: =Assessment!W7 | F19: =Assessment!X7 | G19: =Assessment!Y7 | H19: =Assessment!AE7
A20: =Assessment!A8 | B20: =Assessment!B8 | C20: =Assessment!U8 | D20: =Assessment!V8 | E20: =Assessment!W8 | F20: =Assessment!X8 | G20: =Assessment!Y8 | H20: =Assessment!AE8
A21: =Assessment!A9 | B21: =Assessment!B9 | C21: =Assessment!U9 | D21: =Assessment!V9 | E21: =Assessment!W9 | F21: =Assessment!X9 | G21: =Assessment!Y9 | H21: =Assessment!AE9

Sheet Assessment
A1: ASF Agentic System Instance Assessment v1.0 - Initial Public Release
A2: Enter force/gravity scores for the deployed agentic system instance. Formulas compute AFI, EGI, SMI, orbit, and action.
A4: Agent Name | B4: Domain Overlay | C4: Deployment Zone | D4: Scoring Mode | E4: Decision Autonomy | F4: Decision Velocity | G4: Operational Reach | H4: Operational Criticality | I4: Adaptability | J4: Collaboration Complexity | K4: Persistence and Memory | L4: Identity | M4: Authorization | N4: Policy Enforcement | O4: Observability | P4: Governance and Lifecycle | Q4: Recovery and Resilience | R4: Assurance and Evaluation | S4: Min Evidence Tier | T4: Evidence Warning | U4: AFI | V4: EGI | W4: SMI | X4: Orbit | Y4: Deployment Decision | Z4: ABOM Complete | AA4: Threat Model Required | AB4: Risk Acceptance Required | AC4: Weakest Gravity | AD4: Highest Force | AE4: Next Control Uplift | AF4: Review Date
A5: Documentation Assistant | B5: Knowledge / Documentation | C5: Assisted Zone | D5: Basic | E5: 1 | F5: 1 | G5: 1 | H5: 1 | I5: 1 | J5: 1 | K5: 1 | L5: 4 | M5: 4 | N5: 3 | O5: 4 | P5: 4 | Q5: 3 | R5: 3 | S5: 3 | T5: =IF(AND(MAX(L5:R5)>3,S5<3),"Warning: EGI >3 needs Tier 3+ evidence",IF(AND(C5="Autonomous Operations Zone",S5<4),"Warning: Autonomous zone needs Tier 4 evidence","OK")) | U5: =IF($A5="","",IF($D5="Basic",SUM(E5:K5)/35*100,SUMPRODUCT(E5:K5,XLOOKUP($B5,'Weighted Scoring'!$A$5:$A$13,'Weighted Scoring'!$B$5:$H$13))/SUMPRODUCT(5,XLOOKUP($B5,'Weighted Scoring'!$A$5:$A$13,'Weighted Scoring'!$B$5:$H$13))*100)) | V5: =IF($A5="","",IF($D5="Basic",SUM(L5:R5)/35*100,SUMPRODUCT(L5:R5,XLOOKUP($B5,'Weighted Scoring'!$A$5:$A$13,'Weighted Scoring'!$I$5:$O$13))/SUMPRODUCT(5,XLOOKUP($B5,'Weighted Scoring'!$A$5:$A$13,'Weighted Scoring'!$I$5:$O$13))*100)) | W5: =IF($A5="","",V5-U5) | X5: =IF($A5="","",IFS(W5>=40,"Stable Orbit",W5>=15,"Controlled Orbit",W5>=-14,"Edge Orbit",W5>=-39,"Unstable Orbit",TRUE,"Critical Orbit")) | Y5: =IF($A5="","",XLOOKUP(X5,'Deployment Gates'!$A$5:$A$9,'Deployment Gates'!$C$5:$C$9)) | Z5: Yes | AA5: =IF($A5="","",IF(OR(X5="Edge Orbit",X5="Unstable Orbit",X5="Critical Orbit",H5>=4,G5>=4,E5>=4,J5>=4),"Yes","No")) | AB5: =IF($A5="","",IF(W5<0,"Yes","No")) | AC5: =IF($A5="","",INDEX($L$4:$R$4,1,MATCH(MIN(L5:R5),L5:R5,0))) | AD5: =IF($A5="","",INDEX($E$4:$K$4,1,MATCH(MAX(E5:K5),E5:K5,0))) | AE5: =IF($A5="","",XLOOKUP(AC5,'Control Uplift Planner'!$A$5:$A$11,'Control Uplift Planner'!$B$5:$B$11)) | AF5: 2026-09-30
A6: Client-Request Automation Agent | B6: Financial Operations | C6: Governed Operations Zone | D6: Basic | E6: 3 | F6: 3 | G6: 3 | H6: 5 | I6: 3 | J6: 2 | K6: 2 | L6: 4 | M6: 4 | N6: 4 | O6: 3 | P6: 3 | Q6: 3 | R6: 2 | S6: 3 | T6: =IF(AND(MAX(L6:R6)>3,S6<3),"Warning: EGI >3 needs Tier 3+ evidence",IF(AND(C6="Autonomous Operations Zone",S6<4),"Warning: Autonomous zone needs Tier 4 evidence","OK")) | U6: =IF($A6="","",IF($D6="Basic",SUM(E6:K6)/35*100,SUMPRODUCT(E6:K6,XLOOKUP($B6,'Weighted Scoring'!$A$5:$A$13,'Weighted Scoring'!$B$5:$H$13))/SUMPRODUCT(5,XLOOKUP($B6,'Weighted Scoring'!$A$5:$A$13,'Weighted Scoring'!$B$5:$H$13))*100)) | V6: =IF($A6="","",IF($D6="Basic",SUM(L6:R6)/35*100,SUMPRODUCT(L6:R6,XLOOKUP($B6,'Weighted Scoring'!$A$5:$A$13,'Weighted Scoring'!$I$5:$O$13))/SUMPRODUCT(5,XLOOKUP($B6,'Weighted Scoring'!$A$5:$A$13,'Weighted Scoring'!$I$5:$O$13))*100)) | W6: =IF($A6="","",V6-U6) | X6: =IF($A6="","",IFS(W6>=40,"Stable Orbit",W6>=15,"Controlled Orbit",W6>=-14,"Edge Orbit",W6>=-39,"Unstable Orbit",TRUE,"Critical Orbit")) | Y6: =IF($A6="","",XLOOKUP(X6,'Deployment Gates'!$A$5:$A$9,'Deployment Gates'!$C$5:$C$9)) | Z6: Yes | AA6: =IF($A6="","",IF(OR(X6="Edge Orbit",X6="Unstable Orbit",X6="Critical Orbit",H6>=4,G6>=4,E6>=4,J6>=4),"Yes","No")) | AB6: =IF($A6="","",IF(W6<0,"Yes","No")) | AC6: =IF($A6="","",INDEX($L$4:$R$4,1,MATCH(MIN(L6:R6),L6:R6,0))) | AD6: =IF($A6="","",INDEX($E$4:$K$4,1,MATCH(MAX(E6:K6),E6:K6,0))) | AE6: =IF($A6="","",XLOOKUP(AC6,'Control Uplift Planner'!$A$5:$A$11,'Control Uplift Planner'!$B$5:$B$11)) | AF6: 2026-09-30
A7: Kubernetes Deployment Agent | B7: Software Delivery | C7: Governed Operations Zone | D7: Basic | E7: 4 | F7: 3 | G7: 4 | H7: 4 | I7: 3 | J7: 2 | K7: 3 | L7: 4 | M7: 3 | N7: 4 | O7: 3 | P7: 3 | Q7: 4 | R7: 2 | S7: 3 | T7: =IF(AND(MAX(L7:R7)>3,S7<3),"Warning: EGI >3 needs Tier 3+ evidence",IF(AND(C7="Autonomous Operations Zone",S7<4),"Warning: Autonomous zone needs Tier 4 evidence","OK")) | U7: =IF($A7="","",IF($D7="Basic",SUM(E7:K7)/35*100,SUMPRODUCT(E7:K7,XLOOKUP($B7,'Weighted Scoring'!$A$5:$A$13,'Weighted Scoring'!$B$5:$H$13))/SUMPRODUCT(5,XLOOKUP($B7,'Weighted Scoring'!$A$5:$A$13,'Weighted Scoring'!$B$5:$H$13))*100)) | V7: =IF($A7="","",IF($D7="Basic",SUM(L7:R7)/35*100,SUMPRODUCT(L7:R7,XLOOKUP($B7,'Weighted Scoring'!$A$5:$A$13,'Weighted Scoring'!$I$5:$O$13))/SUMPRODUCT(5,XLOOKUP($B7,'Weighted Scoring'!$A$5:$A$13,'Weighted Scoring'!$I$5:$O$13))*100)) | W7: =IF($A7="","",V7-U7) | X7: =IF($A7="","",IFS(W7>=40,"Stable Orbit",W7>=15,"Controlled Orbit",W7>=-14,"Edge Orbit",W7>=-39,"Unstable Orbit",TRUE,"Critical Orbit")) | Y7: =IF($A7="","",XLOOKUP(X7,'Deployment Gates'!$A$5:$A$9,'Deployment Gates'!$C$5:$C$9)) | Z7: Yes | AA7: =IF($A7="","",IF(OR(X7="Edge Orbit",X7="Unstable Orbit",X7="Critical Orbit",H7>=4,G7>=4,E7>=4,J7>=4),"Yes","No")) | AB7: =IF($A7="","",IF(W7<0,"Yes","No")) | AC7: =IF($A7="","",INDEX($L$4:$R$4,1,MATCH(MIN(L7:R7),L7:R7,0))) | AD7: =IF($A7="","",INDEX($E$4:$K$4,1,MATCH(MAX(E7:K7),E7:K7,0))) | AE7: =IF($A7="","",XLOOKUP(AC7,'Control Uplift Planner'!$A$5:$A$11,'Control Uplift Planner'!$B$5:$B$11)) | AF7: 2026-08-31
A8: Multi-Agent SDLC Workflow | B8: Multi-Agent SDLC | C8: Assisted Zone | D8: Basic | E8: 4 | F8: 3 | G8: 4 | H8: 4 | I8: 4 | J8: 4 | K8: 3 | L8: 3 | M8: 3 | N8: 3 | O8: 4 | P8: 3 | Q8: 3 | R8: 3 | S8: 3 | T8: =IF(AND(MAX(L8:R8)>3,S8<3),"Warning: EGI >3 needs Tier 3+ evidence",IF(AND(C8="Autonomous Operations Zone",S8<4),"Warning: Autonomous zone needs Tier 4 evidence","OK")) | U8: =IF($A8="","",IF($D8="Basic",SUM(E8:K8)/35*100,SUMPRODUCT(E8:K8,XLOOKUP($B8,'Weighted Scoring'!$A$5:$A$13,'Weighted Scoring'!$B$5:$H$13))/SUMPRODUCT(5,XLOOKUP($B8,'Weighted Scoring'!$A$5:$A$13,'Weighted Scoring'!$B$5:$H$13))*100)) | V8: =IF($A8="","",IF($D8="Basic",SUM(L8:R8)/35*100,SUMPRODUCT(L8:R8,XLOOKUP($B8,'Weighted Scoring'!$A$5:$A$13,'Weighted Scoring'!$I$5:$O$13))/SUMPRODUCT(5,XLOOKUP($B8,'Weighted Scoring'!$A$5:$A$13,'Weighted Scoring'!$I$5:$O$13))*100)) | W8: =IF($A8="","",V8-U8) | X8: =IF($A8="","",IFS(W8>=40,"Stable Orbit",W8>=15,"Controlled Orbit",W8>=-14,"Edge Orbit",W8>=-39,"Unstable Orbit",TRUE,"Critical Orbit")) | Y8: =IF($A8="","",XLOOKUP(X8,'Deployment Gates'!$A$5:$A$9,'Deployment Gates'!$C$5:$C$9)) | Z8: No | AA8: =IF($A8="","",IF(OR(X8="Edge Orbit",X8="Unstable Orbit",X8="Critical Orbit",H8>=4,G8>=4,E8>=4,J8>=4),"Yes","No")) | AB8: =IF($A8="","",IF(W8<0,"Yes","No")) | AC8: =IF($A8="","",INDEX($L$4:$R$4,1,MATCH(MIN(L8:R8),L8:R8,0))) | AD8: =IF($A8="","",INDEX($E$4:$K$4,1,MATCH(MAX(E8:K8),E8:K8,0))) | AE8: =IF($A8="","",XLOOKUP(AC8,'Control Uplift Planner'!$A$5:$A$11,'Control Uplift Planner'!$B$5:$B$11)) | AF8: 2026-08-31
A9: Autonomous Production Remediation Agent | B9: Cloud / Infrastructure | C9: Autonomous Operations Zone | D9: Basic | E9: 5 | F9: 4 | G9: 5 | H9: 5 | I9: 4 | J9: 3 | K9: 5 | L9: 4 | M9: 4 | N9: 4 | O9: 3 | P9: 3 | Q9: 4 | R9: 2 | S9: 3 | T9: =IF(AND(MAX(L9:R9)>3,S9<3),"Warning: EGI >3 needs Tier 3+ evidence",IF(AND(C9="Autonomous Operations Zone",S9<4),"Warning: Autonomous zone needs Tier 4 evidence","OK")) | U9: =IF($A9="","",IF($D9="Basic",SUM(E9:K9)/35*100,SUMPRODUCT(E9:K9,XLOOKUP($B9,'Weighted Scoring'!$A$5:$A$13,'Weighted Scoring'!$B$5:$H$13))/SUMPRODUCT(5,XLOOKUP($B9,'Weighted Scoring'!$A$5:$A$13,'Weighted Scoring'!$B$5:$H$13))*100)) | V9: =IF($A9="","",IF($D9="Basic",SUM(L9:R9)/35*100,SUMPRODUCT(L9:R9,XLOOKUP($B9,'Weighted Scoring'!$A$5:$A$13,'Weighted Scoring'!$I$5:$O$13))/SUMPRODUCT(5,XLOOKUP($B9,'Weighted Scoring'!$A$5:$A$13,'Weighted Scoring'!$I$5:$O$13))*100)) | W9: =IF($A9="","",V9-U9) | X9: =IF($A9="","",IFS(W9>=40,"Stable Orbit",W9>=15,"Controlled Orbit",W9>=-14,"Edge Orbit",W9>=-39,"Unstable Orbit",TRUE,"Critical Orbit")) | Y9: =IF($A9="","",XLOOKUP(X9,'Deployment Gates'!$A$5:$A$9,'Deployment Gates'!$C$5:$C$9)) | Z9: No | AA9: =IF($A9="","",IF(OR(X9="Edge Orbit",X9="Unstable Orbit",X9="Critical Orbit",H9>=4,G9>=4,E9>=4,J9>=4),"Yes","No")) | AB9: =IF($A9="","",IF(W9<0,"Yes","No")) | AC9: =IF($A9="","",INDEX($L$4:$R$4,1,MATCH(MIN(L9:R9),L9:R9,0))) | AD9: =IF($A9="","",INDEX($E$4:$K$4,1,MATCH(MAX(E9:K9),E9:K9,0))) | AE9: =IF($A9="","",XLOOKUP(AC9,'Control Uplift Planner'!$A$5:$A$11,'Control Uplift Planner'!$B$5:$B$11)) | AF9: 2026-07-31
T10: =IF(AND(MAX(L10:R10)>3,S10<3),"Warning: EGI >3 needs Tier 3+ evidence",IF(AND(C10="Autonomous Operations Zone",S10<4),"Warning: Autonomous zone needs Tier 4 evidence","OK")) | U10: =IF($A10="","",IF($D10="Basic",SUM(E10:K10)/35*100,SUMPRODUCT(E10:K10,XLOOKUP($B10,'Weighted Scoring'!$A$5:$A$13,'Weighted Scoring'!$B$5:$H$13))/SUMPRODUCT(5,XLOOKUP($B10,'Weighted Scoring'!$A$5:$A$13,'Weighted Scoring'!$B$5:$H$13))*100)) | V10: =IF($A10="","",IF($D10="Basic",SUM(L10:R10)/35*100,SUMPRODUCT(L10:R10,XLOOKUP($B10,'Weighted Scoring'!$A$5:$A$13,'Weighted Scoring'!$I$5:$O$13))/SUMPRODUCT(5,XLOOKUP($B10,'Weighted Scoring'!$A$5:$A$13,'Weighted Scoring'!$I$5:$O$13))*100)) | W10: =IF($A10="","",V10-U10) | X10: =IF($A10="","",IFS(W10>=40,"Stable Orbit",W10>=15,"Controlled Orbit",W10>=-14,"Edge Orbit",W10>=-39,"Unstable Orbit",TRUE,"Critical Orbit")) | Y10: =IF($A10="","",XLOOKUP(X10,'Deployment Gates'!$A$5:$A$9,'Deployment Gates'!$C$5:$C$9)) | AA10: =IF($A10="","",IF(OR(X10="Edge Orbit",X10="Unstable Orbit",X10="Critical Orbit",H10>=4,G10>=4,E10>=4,J10>=4),"Yes","No")) | AB10: =IF($A10="","",IF(W10<0,"Yes","No")) | AC10: =IF($A10="","",INDEX($L$4:$R$4,1,MATCH(MIN(L10:R10),L10:R10,0))) | AD10: =IF($A10="","",INDEX($E$4:$K$4,1,MATCH(MAX(E10:K10),E10:K10,0))) | AE10: =IF($A10="","",XLOOKUP(AC10,'Control Uplift Planner'!$A$5:$A$11,'Control Uplift Planner'!$B$5:$B$11))
T11: =IF(AND(MAX(L11:R11)>3,S11<3),"Warning: EGI >3 needs Tier 3+ evidence",IF(AND(C11="Autonomous Operations Zone",S11<4),"Warning: Autonomous zone needs Tier 4 evidence","OK")) | U11: =IF($A11="","",IF($D11="Basic",SUM(E11:K11)/35*100,SUMPRODUCT(E11:K11,XLOOKUP($B11,'Weighted Scoring'!$A$5:$A$13,'Weighted Scoring'!$B$5:$H$13))/SUMPRODUCT(5,XLOOKUP($B11,'Weighted Scoring'!$A$5:$A$13,'Weighted Scoring'!$B$5:$H$13))*100)) | V11: =IF($A11="","",IF($D11="Basic",SUM(L11:R11)/35*100,SUMPRODUCT(L11:R11,XLOOKUP($B11,'Weighted Scoring'!$A$5:$A$13,'Weighted Scoring'!$I$5:$O$13))/SUMPRODUCT(5,XLOOKUP($B11,'Weighted Scoring'!$A$5:$A$13,'Weighted Scoring'!$I$5:$O$13))*100)) | W11: =IF($A11="","",V11-U11) | X11: =IF($A11="","",IFS(W11>=40,"Stable Orbit",W11>=15,"Controlled Orbit",W11>=-14,"Edge Orbit",W11>=-39,"Unstable Orbit",TRUE,"Critical Orbit")) | Y11: =IF($A11="","",XLOOKUP(X11,'Deployment Gates'!$A$5:$A$9,'Deployment Gates'!$C$5:$C$9)) | AA11: =IF($A11="","",IF(OR(X11="Edge Orbit",X11="Unstable Orbit",X11="Critical Orbit",H11>=4,G11>=4,E11>=4,J11>=4),"Yes","No")) | AB11: =IF($A11="","",IF(W11<0,"Yes","No")) | AC11: =IF($A11="","",INDEX($L$4:$R$4,1,MATCH(MIN(L11:R11),L11:R11,0))) | AD11: =IF($A11="","",INDEX($E$4:$K$4,1,MATCH(MAX(E11:K11),E11:K11,0))) | AE11: =IF($A11="","",XLOOKUP(AC11,'Control Uplift Planner'!$A$5:$A$11,'Control Uplift Planner'!$B$5:$B$11))
T12: =IF(AND(MAX(L12:R12)>3,S12<3),"Warning: EGI >3 needs Tier 3+ evidence",IF(AND(C12="Autonomous Operations Zone",S12<4),"Warning: Autonomous zone needs Tier 4 evidence","OK")) | U12: =IF($A12="","",IF($D12="Basic",SUM(E12:K12)/35*100,SUMPRODUCT(E12:K12,XLOOKUP($B12,'Weighted Scoring'!$A$5:$A$13,'Weighted Scoring'!$B$5:$H$13))/SUMPRODUCT(5,XLOOKUP($B12,'Weighted Scoring'!$A$5:$A$13,'Weighted Scoring'!$B$5:$H$13))*100)) | V12: =IF($A12="","",IF($D12="Basic",SUM(L12:R12)/35*100,SUMPRODUCT(L12:R12,XLOOKUP($B12,'Weighted Scoring'!$A$5:$A$13,'Weighted Scoring'!$I$5:$O$13))/SUMPRODUCT(5,XLOOKUP($B12,'Weighted Scoring'!$A$5:$A$13,'Weighted Scoring'!$I$5:$O$13))*100)) | W12: =IF($A12="","",V12-U12) | X12: =IF($A12="","",IFS(W12>=40,"Stable Orbit",W12>=15,"Controlled Orbit",W12>=-14,"Edge Orbit",W12>=-39,"Unstable Orbit",TRUE,"Critical Orbit")) | Y12: =IF($A12="","",XLOOKUP(X12,'Deployment Gates'!$A$5:$A$9,'Deployment Gates'!$C$5:$C$9)) | AA12: =IF($A12="","",IF(OR(X12="Edge Orbit",X12="Unstable Orbit",X12="Critical Orbit",H12>=4,G12>=4,E12>=4,J12>=4),"Yes","No")) | AB12: =IF($A12="","",IF(W12<0,"Yes","No")) | AC12: =IF($A12="","",INDEX($L$4:$R$4,1,MATCH(MIN(L12:R12),L12:R12,0))) | AD12: =IF($A12="","",INDEX($E$4:$K$4,1,MATCH(MAX(E12:K12),E12:K12,0))) | AE12: =IF($A12="","",XLOOKUP(AC12,'Control Uplift Planner'!$A$5:$A$11,'Control Uplift Planner'!$B$5:$B$11))
T13: =IF(AND(MAX(L13:R13)>3,S13<3),"Warning: EGI >3 needs Tier 3+ evidence",IF(AND(C13="Autonomous Operations Zone",S13<4),"Warning: Autonomous zone needs Tier 4 evidence","OK")) | U13: =IF($A13="","",IF($D13="Basic",SUM(E13:K13)/35*100,SUMPRODUCT(E13:K13,XLOOKUP($B13,'Weighted Scoring'!$A$5:$A$13,'Weighted Scoring'!$B$5:$H$13))/SUMPRODUCT(5,XLOOKUP($B13,'Weighted Scoring'!$A$5:$A$13,'Weighted Scoring'!$B$5:$H$13))*100)) | V13: =IF($A13="","",IF($D13="Basic",SUM(L13:R13)/35*100,SUMPRODUCT(L13:R13,XLOOKUP($B13,'Weighted Scoring'!$A$5:$A$13,'Weighted Scoring'!$I$5:$O$13))/SUMPRODUCT(5,XLOOKUP($B13,'Weighted Scoring'!$A$5:$A$13,'Weighted Scoring'!$I$5:$O$13))*100)) | W13: =IF($A13="","",V13-U13) | X13: =IF($A13="","",IFS(W13>=40,"Stable Orbit",W13>=15,"Controlled Orbit",W13>=-14,"Edge Orbit",W13>=-39,"Unstable Orbit",TRUE,"Critical Orbit")) | Y13: =IF($A13="","",XLOOKUP(X13,'Deployment Gates'!$A$5:$A$9,'Deployment Gates'!$C$5:$C$9)) | AA13: =IF($A13="","",IF(OR(X13="Edge Orbit",X13="Unstable Orbit",X13="Critical Orbit",H13>=4,G13>=4,E13>=4,J13>=4),"Yes","No")) | AB13: =IF($A13="","",IF(W13<0,"Yes","No")) | AC13: =IF($A13="","",INDEX($L$4:$R$4,1,MATCH(MIN(L13:R13),L13:R13,0))) | AD13: =IF($A13="","",INDEX($E$4:$K$4,1,MATCH(MAX(E13:K13),E13:K13,0))) | AE13: =IF($A13="","",XLOOKUP(AC13,'Control Uplift Planner'!$A$5:$A$11,'Control Uplift Planner'!$B$5:$B$11))
T14: =IF(AND(MAX(L14:R14)>3,S14<3),"Warning: EGI >3 needs Tier 3+ evidence",IF(AND(C14="Autonomous Operations Zone",S14<4),"Warning: Autonomous zone needs Tier 4 evidence","OK")) | U14: =IF($A14="","",IF($D14="Basic",SUM(E14:K14)/35*100,SUMPRODUCT(E14:K14,XLOOKUP($B14,'Weighted Scoring'!$A$5:$A$13,'Weighted Scoring'!$B$5:$H$13))/SUMPRODUCT(5,XLOOKUP($B14,'Weighted Scoring'!$A$5:$A$13,'Weighted Scoring'!$B$5:$H$13))*100)) | V14: =IF($A14="","",IF($D14="Basic",SUM(L14:R14)/35*100,SUMPRODUCT(L14:R14,XLOOKUP($B14,'Weighted Scoring'!$A$5:$A$13,'Weighted Scoring'!$I$5:$O$13))/SUMPRODUCT(5,XLOOKUP($B14,'Weighted Scoring'!$A$5:$A$13,'Weighted Scoring'!$I$5:$O$13))*100)) | W14: =IF($A14="","",V14-U14) | X14: =IF($A14="","",IFS(W14>=40,"Stable Orbit",W14>=15,"Controlled Orbit",W14>=-14,"Edge Orbit",W14>=-39,"Unstable Orbit",TRUE,"Critical Orbit")) | Y14: =IF($A14="","",XLOOKUP(X14,'Deployment Gates'!$A$5:$A$9,'Deployment Gates'!$C$5:$C$9)) | AA14: =IF($A14="","",IF(OR(X14="Edge Orbit",X14="Unstable Orbit",X14="Critical Orbit",H14>=4,G14>=4,E14>=4,J14>=4),"Yes","No")) | AB14: =IF($A14="","",IF(W14<0,"Yes","No")) | AC14: =IF($A14="","",INDEX($L$4:$R$4,1,MATCH(MIN(L14:R14),L14:R14,0))) | AD14: =IF($A14="","",INDEX($E$4:$K$4,1,MATCH(MAX(E14:K14),E14:K14,0))) | AE14: =IF($A14="","",XLOOKUP(AC14,'Control Uplift Planner'!$A$5:$A$11,'Control Uplift Planner'!$B$5:$B$11))
T15: =IF(AND(MAX(L15:R15)>3,S15<3),"Warning: EGI >3 needs Tier 3+ evidence",IF(AND(C15="Autonomous Operations Zone",S15<4),"Warning: Autonomous zone needs Tier 4 evidence","OK")) | U15: =IF($A15="","",IF($D15="Basic",SUM(E15:K15)/35*100,SUMPRODUCT(E15:K15,XLOOKUP($B15,'Weighted Scoring'!$A$5:$A$13,'Weighted Scoring'!$B$5:$H$13))/SUMPRODUCT(5,XLOOKUP($B15,'Weighted Scoring'!$A$5:$A$13,'Weighted Scoring'!$B$5:$H$13))*100)) | V15: =IF($A15="","",IF($D15="Basic",SUM(L15:R15)/35*100,SUMPRODUCT(L15:R15,XLOOKUP($B15,'Weighted Scoring'!$A$5:$A$13,'Weighted Scoring'!$I$5:$O$13))/SUMPRODUCT(5,XLOOKUP($B15,'Weighted Scoring'!$A$5:$A$13,'Weighted Scoring'!$I$5:$O$13))*100)) | W15: =IF($A15="","",V15-U15) | X15: =IF($A15="","",IFS(W15>=40,"Stable Orbit",W15>=15,"Controlled Orbit",W15>=-14,"Edge Orbit",W15>=-39,"Unstable Orbit",TRUE,"Critical Orbit")) | Y15: =IF($A15="","",XLOOKUP(X15,'Deployment Gates'!$A$5:$A$9,'Deployment Gates'!$C$5:$C$9)) | AA15: =IF($A15="","",IF(OR(X15="Edge Orbit",X15="Unstable Orbit",X15="Critical Orbit",H15>=4,G15>=4,E15>=4,J15>=4),"Yes","No")) | AB15: =IF($A15="","",IF(W15<0,"Yes","No")) | AC15: =IF($A15="","",INDEX($L$4:$R$4,1,MATCH(MIN(L15:R15),L15:R15,0))) | AD15: =IF($A15="","",INDEX($E$4:$K$4,1,MATCH(MAX(E15:K15),E15:K15,0))) | AE15: =IF($A15="","",XLOOKUP(AC15,'Control Uplift Planner'!$A$5:$A$11,'Control Uplift Planner'!$B$5:$B$11))
T16: =IF(AND(MAX(L16:R16)>3,S16<3),"Warning: EGI >3 needs Tier 3+ evidence",IF(AND(C16="Autonomous Operations Zone",S16<4),"Warning: Autonomous zone needs Tier 4 evidence","OK")) | U16: =IF($A16="","",IF($D16="Basic",SUM(E16:K16)/35*100,SUMPRODUCT(E16:K16,XLOOKUP($B16,'Weighted Scoring'!$A$5:$A$13,'Weighted Scoring'!$B$5:$H$13))/SUMPRODUCT(5,XLOOKUP($B16,'Weighted Scoring'!$A$5:$A$13,'Weighted Scoring'!$B$5:$H$13))*100)) | V16: =IF($A16="","",IF($D16="Basic",SUM(L16:R16)/35*100,SUMPRODUCT(L16:R16,XLOOKUP($B16,'Weighted Scoring'!$A$5:$A$13,'Weighted Scoring'!$I$5:$O$13))/SUMPRODUCT(5,XLOOKUP($B16,'Weighted Scoring'!$A$5:$A$13,'Weighted Scoring'!$I$5:$O$13))*100)) | W16: =IF($A16="","",V16-U16) | X16: =IF($A16="","",IFS(W16>=40,"Stable Orbit",W16>=15,"Controlled Orbit",W16>=-14,"Edge Orbit",W16>=-39,"Unstable Orbit",TRUE,"Critical Orbit")) | Y16: =IF($A16="","",XLOOKUP(X16,'Deployment Gates'!$A$5:$A$9,'Deployment Gates'!$C$5:$C$9)) | AA16: =IF($A16="","",IF(OR(X16="Edge Orbit",X16="Unstable Orbit",X16="Critical Orbit",H16>=4,G16>=4,E16>=4,J16>=4),"Yes","No")) | AB16: =IF($A16="","",IF(W16<0,"Yes","No")) | AC16: =IF($A16="","",INDEX($L$4:$R$4,1,MATCH(MIN(L16:R16),L16:R16,0))) | AD16: =IF($A16="","",INDEX($E$4:$K$4,1,MATCH(MAX(E16:K16),E16:K16,0))) | AE16: =IF($A16="","",XLOOKUP(AC16,'Control Uplift Planner'!$A$5:$A$11,'Control Uplift Planner'!$B$5:$B$11))
T17: =IF(AND(MAX(L17:R17)>3,S17<3),"Warning: EGI >3 needs Tier 3+ evidence",IF(AND(C17="Autonomous Operations Zone",S17<4),"Warning: Autonomous zone needs Tier 4 evidence","OK")) | U17: =IF($A17="","",IF($D17="Basic",SUM(E17:K17)/35*100,SUMPRODUCT(E17:K17,XLOOKUP($B17,'Weighted Scoring'!$A$5:$A$13,'Weighted Scoring'!$B$5:$H$13))/SUMPRODUCT(5,XLOOKUP($B17,'Weighted Scoring'!$A$5:$A$13,'Weighted Scoring'!$B$5:$H$13))*100)) | V17: =IF($A17="","",IF($D17="Basic",SUM(L17:R17)/35*100,SUMPRODUCT(L17:R17,XLOOKUP($B17,'Weighted Scoring'!$A$5:$A$13,'Weighted Scoring'!$I$5:$O$13))/SUMPRODUCT(5,XLOOKUP($B17,'Weighted Scoring'!$A$5:$A$13,'Weighted Scoring'!$I$5:$O$13))*100)) | W17: =IF($A17="","",V17-U17) | X17: =IF($A17="","",IFS(W17>=40,"Stable Orbit",W17>=15,"Controlled Orbit",W17>=-14,"Edge Orbit",W17>=-39,"Unstable Orbit",TRUE,"Critical Orbit")) | Y17: =IF($A17="","",XLOOKUP(X17,'Deployment Gates'!$A$5:$A$9,'Deployment Gates'!$C$5:$C$9)) | AA17: =IF($A17="","",IF(OR(X17="Edge Orbit",X17="Unstable Orbit",X17="Critical Orbit",H17>=4,G17>=4,E17>=4,J17>=4),"Yes","No")) | AB17: =IF($A17="","",IF(W17<0,"Yes","No")) | AC17: =IF($A17="","",INDEX($L$4:$R$4,1,MATCH(MIN(L17:R17),L17:R17,0))) | AD17: =IF($A17="","",INDEX($E$4:$K$4,1,MATCH(MAX(E17:K17),E17:K17,0))) | AE17: =IF($A17="","",XLOOKUP(AC17,'Control Uplift Planner'!$A$5:$A$11,'Control Uplift Planner'!$B$5:$B$11))
T18: =IF(AND(MAX(L18:R18)>3,S18<3),"Warning: EGI >3 needs Tier 3+ evidence",IF(AND(C18="Autonomous Operations Zone",S18<4),"Warning: Autonomous zone needs Tier 4 evidence","OK")) | U18: =IF($A18="","",IF($D18="Basic",SUM(E18:K18)/35*100,SUMPRODUCT(E18:K18,XLOOKUP($B18,'Weighted Scoring'!$A$5:$A$13,'Weighted Scoring'!$B$5:$H$13))/SUMPRODUCT(5,XLOOKUP($B18,'Weighted Scoring'!$A$5:$A$13,'Weighted Scoring'!$B$5:$H$13))*100)) | V18: =IF($A18="","",IF($D18="Basic",SUM(L18:R18)/35*100,SUMPRODUCT(L18:R18,XLOOKUP($B18,'Weighted Scoring'!$A$5:$A$13,'Weighted Scoring'!$I$5:$O$13))/SUMPRODUCT(5,XLOOKUP($B18,'Weighted Scoring'!$A$5:$A$13,'Weighted Scoring'!$I$5:$O$13))*100)) | W18: =IF($A18="","",V18-U18) | X18: =IF($A18="","",IFS(W18>=40,"Stable Orbit",W18>=15,"Controlled Orbit",W18>=-14,"Edge Orbit",W18>=-39,"Unstable Orbit",TRUE,"Critical Orbit")) | Y18: =IF($A18="","",XLOOKUP(X18,'Deployment Gates'!$A$5:$A$9,'Deployment Gates'!$C$5:$C$9)) | AA18: =IF($A18="","",IF(OR(X18="Edge Orbit",X18="Unstable Orbit",X18="Critical Orbit",H18>=4,G18>=4,E18>=4,J18>=4),"Yes","No")) | AB18: =IF($A18="","",IF(W18<0,"Yes","No")) | AC18: =IF($A18="","",INDEX($L$4:$R$4,1,MATCH(MIN(L18:R18),L18:R18,0))) | AD18: =IF($A18="","",INDEX($E$4:$K$4,1,MATCH(MAX(E18:K18),E18:K18,0))) | AE18: =IF($A18="","",XLOOKUP(AC18,'Control Uplift Planner'!$A$5:$A$11,'Control Uplift Planner'!$B$5:$B$11))
T19: =IF(AND(MAX(L19:R19)>3,S19<3),"Warning: EGI >3 needs Tier 3+ evidence",IF(AND(C19="Autonomous Operations Zone",S19<4),"Warning: Autonomous zone needs Tier 4 evidence","OK")) | U19: =IF($A19="","",IF($D19="Basic",SUM(E19:K19)/35*100,SUMPRODUCT(E19:K19,XLOOKUP($B19,'Weighted Scoring'!$A$5:$A$13,'Weighted Scoring'!$B$5:$H$13))/SUMPRODUCT(5,XLOOKUP($B19,'Weighted Scoring'!$A$5:$A$13,'Weighted Scoring'!$B$5:$H$13))*100)) | V19: =IF($A19="","",IF($D19="Basic",SUM(L19:R19)/35*100,SUMPRODUCT(L19:R19,XLOOKUP($B19,'Weighted Scoring'!$A$5:$A$13,'Weighted Scoring'!$I$5:$O$13))/SUMPRODUCT(5,XLOOKUP($B19,'Weighted Scoring'!$A$5:$A$13,'Weighted Scoring'!$I$5:$O$13))*100)) | W19: =IF($A19="","",V19-U19) | X19: =IF($A19="","",IFS(W19>=40,"Stable Orbit",W19>=15,"Controlled Orbit",W19>=-14,"Edge Orbit",W19>=-39,"Unstable Orbit",TRUE,"Critical Orbit")) | Y19: =IF($A19="","",XLOOKUP(X19,'Deployment Gates'!$A$5:$A$9,'Deployment Gates'!$C$5:$C$9)) | AA19: =IF($A19="","",IF(OR(X19="Edge Orbit",X19="Unstable Orbit",X19="Critical Orbit",H19>=4,G19>=4,E19>=4,J19>=4),"Yes","No")) | AB19: =IF($A19="","",IF(W19<0,"Yes","No")) | AC19: =IF($A19="","",INDEX($L$4:$R$4,1,MATCH(MIN(L19:R19),L19:R19,0))) | AD19: =IF($A19="","",INDEX($E$4:$K$4,1,MATCH(MAX(E19:K19),E19:K19,0))) | AE19: =IF($A19="","",XLOOKUP(AC19,'Control Uplift Planner'!$A$5:$A$11,'Control Uplift Planner'!$B$5:$B$11))
T20: =IF(AND(MAX(L20:R20)>3,S20<3),"Warning: EGI >3 needs Tier 3+ evidence",IF(AND(C20="Autonomous Operations Zone",S20<4),"Warning: Autonomous zone needs Tier 4 evidence","OK")) | U20: =IF($A20="","",IF($D20="Basic",SUM(E20:K20)/35*100,SUMPRODUCT(E20:K20,XLOOKUP($B20,'Weighted Scoring'!$A$5:$A$13,'Weighted Scoring'!$B$5:$H$13))/SUMPRODUCT(5,XLOOKUP($B20,'Weighted Scoring'!$A$5:$A$13,'Weighted Scoring'!$B$5:$H$13))*100)) | V20: =IF($A20="","",IF($D20="Basic",SUM(L20:R20)/35*100,SUMPRODUCT(L20:R20,XLOOKUP($B20,'Weighted Scoring'!$A$5:$A$13,'Weighted Scoring'!$I$5:$O$13))/SUMPRODUCT(5,XLOOKUP($B20,'Weighted Scoring'!$A$5:$A$13,'Weighted Scoring'!$I$5:$O$13))*100)) | W20: =IF($A20="","",V20-U20) | X20: =IF($A20="","",IFS(W20>=40,"Stable Orbit",W20>=15,"Controlled Orbit",W20>=-14,"Edge Orbit",W20>=-39,"Unstable Orbit",TRUE,"Critical Orbit")) | Y20: =IF($A20="","",XLOOKUP(X20,'Deployment Gates'!$A$5:$A$9,'Deployment Gates'!$C$5:$C$9)) | AA20: =IF($A20="","",IF(OR(X20="Edge Orbit",X20="Unstable Orbit",X20="Critical Orbit",H20>=4,G20>=4,E20>=4,J20>=4),"Yes","No")) | AB20: =IF($A20="","",IF(W20<0,"Yes","No")) | AC20: =IF($A20="","",INDEX($L$4:$R$4,1,MATCH(MIN(L20:R20),L20:R20,0))) | AD20: =IF($A20="","",INDEX($E$4:$K$4,1,MATCH(MAX(E20:K20),E20:K20,0))) | AE20: =IF($A20="","",XLOOKUP(AC20,'Control Uplift Planner'!$A$5:$A$11,'Control Uplift Planner'!$B$5:$B$11))
T21: =IF(AND(MAX(L21:R21)>3,S21<3),"Warning: EGI >3 needs Tier 3+ evidence",IF(AND(C21="Autonomous Operations Zone",S21<4),"Warning: Autonomous zone needs Tier 4 evidence","OK")) | U21: =IF($A21="","",IF($D21="Basic",SUM(E21:K21)/35*100,SUMPRODUCT(E21:K21,XLOOKUP($B21,'Weighted Scoring'!$A$5:$A$13,'Weighted Scoring'!$B$5:$H$13))/SUMPRODUCT(5,XLOOKUP($B21,'Weighted Scoring'!$A$5:$A$13,'Weighted Scoring'!$B$5:$H$13))*100)) | V21: =IF($A21="","",IF($D21="Basic",SUM(L21:R21)/35*100,SUMPRODUCT(L21:R21,XLOOKUP($B21,'Weighted Scoring'!$A$5:$A$13,'Weighted Scoring'!$I$5:$O$13))/SUMPRODUCT(5,XLOOKUP($B21,'Weighted Scoring'!$A$5:$A$13,'Weighted Scoring'!$I$5:$O$13))*100)) | W21: =IF($A21="","",V21-U21) | X21: =IF($A21="","",IFS(W21>=40,"Stable Orbit",W21>=15,"Controlled Orbit",W21>=-14,"Edge Orbit",W21>=-39,"Unstable Orbit",TRUE,"Critical Orbit")) | Y21: =IF($A21="","",XLOOKUP(X21,'Deployment Gates'!$A$5:$A$9,'Deployment Gates'!$C$5:$C$9)) | AA21: =IF($A21="","",IF(OR(X21="Edge Orbit",X21="Unstable Orbit",X21="Critical Orbit",H21>=4,G21>=4,E21>=4,J21>=4),"Yes","No")) | AB21: =IF($A21="","",IF(W21<0,"Yes","No")) | AC21: =IF($A21="","",INDEX($L$4:$R$4,1,MATCH(MIN(L21:R21),L21:R21,0))) | AD21: =IF($A21="","",INDEX($E$4:$K$4,1,MATCH(MAX(E21:K21),E21:K21,0))) | AE21: =IF($A21="","",XLOOKUP(AC21,'Control Uplift Planner'!$A$5:$A$11,'Control Uplift Planner'!$B$5:$B$11))
... T104: =IF(AND(MAX(L104:R104)>3,S104<3),"Warning: EGI >3 needs Tier 3+ evidence",IF(AND(C104="Autonomous Operations Zone",S104<4),"Warning: Autonomous zone needs Tier 4 evidence","OK")) | U104: =IF($A104="","",IF($D104="Basic",SUM(E104:K104)/35*100,SUMPRODUCT(E104:K104,XLOOKUP($B104,'Weighted Scoring'!$A$5:$A$13,'Weighted Scoring'!$B$5:$H$13))/SUMPRODUCT(5,XLOOKUP($B104,'Weighted Scoring'!$A$5:$A$13,'Weighted Scoring'!$B$5:$H$13))*100)) | V104: =IF($A104="","",IF($D104="Basic",SUM(L104:R104)/35*100,SUMPRODUCT(L104:R104,XLOOKUP($B104,'Weighted Scoring'!$A$5:$A$13,'Weighted Scoring'!$I$5:$O$13))/SUMPRODUCT(5,XLOOKUP($B104,'Weighted Scoring'!$A$5:$A$13,'Weighted Scoring'!$I$5:$O$13))*100)) | W104: =IF($A104="","",V104-U104) | X104: =IF($A104="","",IFS(W104>=40,"Stable Orbit",W104>=15,"Controlled Orbit",W104>=-14,"Edge Orbit",W104>=-39,"Unstable Orbit",TRUE,"Critical Orbit")) | Y104: =IF($A104="","",XLOOKUP(X104,'Deployment Gates'!$A$5:$A$9,'Deployment Gates'!$C$5:$C$9)) | AA104: =IF($A104="","",IF(OR(X104="Edge Orbit",X104="Unstable Orbit",X104="Critical Orbit",H104>=4,G104>=4,E104>=4,J104>=4),"Yes","No")) | AB104: =IF($A104="","",IF(W104<0,"Yes","No")) | AC104: =IF($A104="","",INDEX($L$4:$R$4,1,MATCH(MIN(L104:R104),L104:R104,0))) | AD104: =IF($A104="","",INDEX($E$4:$K$4,1,MATCH(MAX(E104:K104),E104:K104,0))) | AE104: =IF($A104="","",XLOOKUP(AC104,'Control Uplift Planner'!$A$5:$A$11,'Control Uplift Planner'!$B$5:$B$11))

Sheet Weighted Scoring
A1: Advanced Mode Weights
A2: Weights are applied only when Scoring Mode = Advanced
A4: Domain Overlay | B4: Decision Autonomy | C4: Decision Velocity | D4: Operational Reach | E4: Operational Criticality | F4: Adaptability | G4: Collaboration Complexity | H4: Persistence and Memory | I4: Identity | J4: Authorization | K4: Policy Enforcement | L4: Observability | M4: Governance and Lifecycle | N4: Recovery and Resilience | O4: Assurance and Evaluation
A5: Knowledge / Documentation | B5: 1 | C5: 1 | D5: 1 | E5: 1 | F5: 1 | G5: 1 | H5: 1 | I5: 1 | J5: 1 | K5: 1 | L5: 1 | M5: 1 | N5: 1 | O5: 1
A6: API Governance | B6: 1.4 | C6: 1 | D6: 1.5 | E6: 1.4 | F6: 1.2 | G6: 1 | H6: 1 | I6: 1.2 | J6: 1.4 | K6: 1.8 | L6: 1.6 | M6: 1.6 | N6: 1.1 | O6: 1.4
A7: Software Delivery | B7: 1.6 | C7: 1.2 | D7: 1.6 | E7: 1.8 | F7: 1.4 | G7: 1.3 | H7: 1 | I7: 1.3 | J7: 1.5 | K7: 1.9 | L7: 1.8 | M7: 1.2 | N7: 1.8 | O7: 1.7
A8: Cloud / Infrastructure | B8: 1.7 | C8: 1.5 | D8: 1.8 | E8: 1.9 | F8: 1.4 | G8: 1.2 | H8: 1.2 | I8: 1.5 | J8: 1.8 | K8: 1.9 | L8: 1.8 | M8: 1.2 | N8: 2 | O8: 1.6
A9: Security Operations | B9: 1.8 | C9: 1.6 | D9: 1.4 | E9: 1.9 | F9: 1.3 | G9: 1.2 | H9: 1 | I9: 1.8 | J9: 1.6 | K9: 2 | L9: 1.8 | M9: 1.1 | N9: 2 | O9: 1.7
A10: Customer Service | B10: 1.3 | C10: 1.5 | D10: 1.8 | E10: 1.7 | F10: 1.2 | G10: 1.1 | H10: 1.6 | I10: 1.2 | J10: 1.8 | K10: 1.4 | L10: 1.9 | M10: 1.2 | N10: 1.2 | O10: 1.8
A11: Financial Operations | B11: 1.8 | C11: 1.2 | D11: 1.7 | E11: 2 | F11: 1.2 | G11: 1 | H11: 1.3 | I11: 1.5 | J11: 2 | K11: 1.6 | L11: 1.5 | M11: 1.8 | N11: 1.4 | O11: 2
A12: Regulated Data | B12: 1.4 | C12: 1.1 | D12: 1.7 | E12: 2 | F12: 1.2 | G12: 1 | H12: 1.6 | I12: 1.4 | J12: 2 | K12: 1.7 | L12: 1.9 | M12: 1.7 | N12: 1.3 | O12: 2
A13: Multi-Agent SDLC | B13: 1.6 | C13: 1.3 | D13: 1.7 | E13: 1.8 | F13: 1.7 | G13: 2 | H13: 1.3 | I13: 1.4 | J13: 1.5 | K13: 1.8 | L13: 2 | M13: 1.9 | N13: 1.6 | O13: 1.8

Sheet AFI Rubric
A1: Agentic Force Index (AFI) Rubric
A2: Score each dimension from 0 to 5
A4: Dimension | B4: 0 | C4: 1 | D4: 2 | E4: 3 | F4: 4 | G4: 5
A5: Decision Autonomy | B5: No decision capability | C5: Suggests actions only | D5: Recommends for approval | E5: Executes after human approval | F5: Executes under policy approval | G5: Executes independently within delegated authority
A6: Decision Velocity | B6: No decisions | C6: Occasional/manual | D6: Daily/batch | E6: Hourly/event-driven | F6: Near-real-time | G6: Continuous autonomous loop
A7: Operational Reach | B7: No system access | C7: Single user workspace | D7: Single app/repository | E7: Multiple apps in one domain | F7: Multiple domains/business units | G7: Enterprise-wide or external ecosystem
A8: Operational Criticality | B8: No impact | C8: Low/cosmetic | D8: Team productivity | E8: Application/workflow | F8: Production/customer/security | G8: Financial/regulatory/safety/enterprise-critical
A9: Adaptability | B9: No adaptation | C9: Static prompt/fixed workflow | D9: Chooses predefined paths | E9: Generates dynamic plans | F9: Learns from feedback/memory | G9: Discovers tools/self-optimizes
A10: Collaboration Complexity | B10: No collaboration | C10: Single-agent | D10: Human-agent | E10: Multi-agent fixed roles | F10: Dynamic handoffs | G10: Swarm-like/emergent
A11: Persistence and Memory | B11: No persistence | C11: Single-session | D11: Short-term task memory | E11: Long-lived scoped memory | F11: Cross-session memory | G11: Enterprise/self-maintained memory

Sheet EGI Rubric
A1: Enterprise Gravity Index (EGI) Rubric
A2: Score only controls that are present, well-designed, and evidenced
A4: Dimension | B4: 0 | C4: 1 | D4: 2 | E4: 3 | F4: 4 | G4: 5
A5: Identity | B5: No distinct identity | C5: Shared user/service account | D5: Dedicated service identity | E5: Workload identity with ownership | F5: Short-lived credentials + strong auth | G5: Cryptographic identity + continuous verification
A6: Authorization | B6: No boundary | C6: Broad static access | D6: Role-based access | E6: Least privilege by tool/workflow | F6: Context-aware authorization | G6: Dynamic policy-driven JIT access
A7: Policy Enforcement | B7: None | C7: Human guidelines only | D7: Static config checks | E7: CI/CD or pre-execution checks | F7: Runtime policy enforcement | G7: Adaptive risk-based policy
A8: Observability | B8: No logs | C8: Basic application logs | D8: Tool-call logs | E8: Prompt/plan/action traces | F8: End-to-end traceability | G8: Audit-grade decision provenance
A9: Governance and Lifecycle | B9: No inventory | C9: Informal ownership | D9: Agent catalog/registry | E9: Lifecycle approval workflow | F9: Version/certification/deprecation | G9: Control plane for agents/tools/models/memory/policies
A10: Recovery and Resilience | B10: No recovery | C10: Manual intervention | D10: Basic rollback | E10: Kill switch/circuit breaker | F10: Automated rollback + human takeover | G10: Blast-radius isolation + recovery drills
A11: Assurance and Evaluation | B11: No evaluation | C11: Manual pre-release testing | D11: Basic prompt/output eval | E11: Scenario eval + red team | F11: Runtime eval + drift detection | G11: Continuous assurance across policy/behavior/security/outcomes

Sheet Evidence Tiers
A1: Evidence Tiers
A2: EGI scores above 3 require Tier 3+ evidence
A4: Tier | B4: Name | C4: Meaning | D4: Examples
A5: 0 | B5: Claimed | C5: Claimed, no evidence | D5: Verbal statement, slide, unvalidated design claim
A6: 1 | B6: Documented | C6: Documented design | D6: Architecture doc, policy draft, decision record
A7: 2 | B7: Implemented | C7: Implemented control | D7: Configured identity, gateway, policy, logging, workflow
A8: 3 | B8: Tested | C8: Tested control | D8: Validation result, policy test, rollback test, drill
A9: 4 | B9: Runtime Verified | C9: Runtime-verified control | D9: Production trace, policy decision log, audit event
A10: 5 | B10: Continuous Audit | C10: Continuously monitored and audited | D10: Dashboards, recurring evidence, automated checks
A12: Rule | B12: Applies To | C12: Requirement | D12: Notes
A13: EGI > 3 | B13: Any EGI dimension | C13: Tier 3+ evidence required | D13: Design intent is not enough
A14: Production-impacting agent | B14: Policy, Observability, Recovery, Assurance | C14: Tier 4+ evidence required to move beyond Edge Orbit | D14: Runtime proof expected

Sheet ABOM
A1: ABOM - System Boundary
A2: Defines model, runtime, memory, tools/MCP, identity, permissions, policies, approvals, and operating context.
A4: Category | B4: Required Information | C4: Owner | D4: Evidence Link / Location | E4: Status
A5: Agentic System Instance | B5: Name, version, owner, purpose, business domain, assessed context
A6: Model | B6: Provider, model, deployment mode, approval status
A7: Runtime | B7: Agent framework, orchestrator, hosting environment
A8: Prompts | B8: System prompts, task prompts, prompt versioning
A9: Tools / MCP Servers | B9: APIs, MCP servers, plugins, scripts, functions, workflows; read/write capability, tool risk level, reversibility
A10: Data Sources | B10: KBs, vector stores, databases, files, SaaS systems
A11: Memory | B11: Session, short-term, long-term, enterprise memory
A12: Identity | B12: Agent identity, user delegation, service identity, on-behalf-of authority
A13: Authorization | B13: Permissions, scopes, roles, environments, JIT access, delegated authority model
A14: Policies | B14: Policy rules, enforcement points, exceptions, tool/action policies
A15: Observability | B15: Logs, traces, audit store, dashboards, prompt-plan-tool-action traces
A16: Recovery | B16: Rollback, kill switch, circuit breakers, compensating actions, reversibility limits
... A23: Operating Context | B23: Environment, users, approval model, delegated authority, business process, regulatory context

Sheet Threat Model
A1: ASF Threat Model Gate
A2: Required for Edge, Unstable, or Critical Orbit agents, and for any agent with production action authority, sensitive-data access, multi-agent handoffs, long-term memory, or external exposure.
A4: Threat Category | B4: Scenario / Question | C4: Likelihood | D4: Impact | E4: Mitigation | F4: Status
A5: Prompt injection | B5: Can user or retrieved content override agent instructions or policy boundaries?
A6: Tool misuse | B6: Can the agent invoke tools in unintended order, scope, or context?
A7: Excessive agency | B7: Does the agent have broader permissions than its task requires?
A8: Identity abuse | B8: Can agent identity or delegated user authority be misused?
A9: Memory poisoning | B9: Can malicious content persist and influence future behavior?
A10: Context poisoning | B10: Can retrieved content manipulate plan or tool choice?
A11: Data exfiltration | B11: Can retrieved or generated content leak sensitive data?
A12: Inter-agent manipulation | B12: Can one agent manipulate another through handoff, context, or memory?
A13: Policy evasion | B13: Can the agent bypass gateway, broker, or policy enforcement?
A14: Cascading failure | B14: Can one action trigger uncontrolled downstream impact?
A15: Recovery failure | B15: Can the enterprise stop, reverse, or contain action fast enough?

Sheet Domain Overlays
A1: Domain Overlays
A2: Adjust scoring emphasis, evidence expectations, threat scenarios, and uplift actions
A4: Overlay | B4: Use When | C4: Higher Force Weights | D4: Higher Gravity Weights | E4: Required Evidence
A5: Software Delivery | B5: Reviewing, coding, testing, merging, deploying software | C5: Autonomy, Criticality, Reach, Collaboration | D5: Policy, Recovery, Observability, Assurance | E5: Repo permissions, CI/CD logs, policy-as-code, rollback validation
A6: Cloud / Infrastructure | B6: Provisioning, configuring, remediating cloud/platform systems | C6: Autonomy, Reach, Criticality, Velocity | D6: Identity, Authorization, Policy, Recovery | E6: IaC policy, workload identity, namespace/account scoping, recovery drills
A7: Security Operations | B7: Triaging alerts, changing controls, incident response | C7: Autonomy, Criticality, Velocity | D7: Identity, Policy, Recovery, Observability | E7: SOC playbooks, evidence logs, credential boundaries, containment controls
A8: API Governance | B8: Reviewing specs, attaching policies, publishing APIs | C8: Reach, Criticality, Autonomy | D8: Policy, Observability, Governance, Authorization | E8: Catalog workflow, Spectral/OPA rules, gateway policy binding records
A9: Customer Service | B9: Using CRM, case data, external customer communications | C9: Reach, Criticality, Memory | D9: Authorization, Assurance, Observability | E9: PII controls, response review, escalation logs
A10: Financial Operations | B10: Payments, invoices, reconciliation, approvals | C10: Criticality, Autonomy, Reach | D10: Authorization, Assurance, Governance | E10: Segregation of duties, approval records, fraud controls
A11: Regulated Data | B11: Health, financial, legal, regulated data | C11: Criticality, Reach, Memory | D11: Authorization, Observability, Assurance | E11: Data classification, audit-grade logs, regulatory review
A12: Multi-Agent SDLC | B12: Planner, coder, tester, reviewer, release handoffs | C12: Collaboration, Adaptability, Reach | D12: Observability, Policy, Governance | E12: Handoff traces, shared memory controls, conflict resolution
A13: Knowledge / Documentation | B13: Read-only enterprise knowledge assistants | C13: Reach, Memory | D13: Identity, Authorization, Observability | E13: Approved sources, access logs, output disclaimers where needed

Sheet Risk Acceptance
A1: Risk Acceptance Workflow
A2: Required when SMI is negative and deployment continues by exception
A4: Field | B4: Requirement | C4: Value | D4: Evidence / Notes
A5: Business Owner | B5: Named accountable business owner
A6: Technology Owner | B6: Named accountable technical owner
A7: Reason | B7: Why exception is needed
A8: Compensating Controls | B8: Controls that reduce exposure
A9: Expiration Date | B9: No open-ended exceptions
A10: Reassessment Date | B10: Required follow-up date
A11: Residual Risk | B11: Accepted residual risk statement
A12: Approval Record | B12: Governance approval evidence
A13: Decision | B13: Accept / Reject / Defer

Sheet Architecture Review Packet
A1: ASF Architecture Review Packet
A2: Use this checklist in architecture review board or AI governance review
A4: Review Item | B4: Required? | C4: Status | D4: Evidence / Link
A5: Agent profile and business context | B5: Yes
A6: Agent Bill of Materials complete | B6: Yes
A7: AFI, EGI, SMI, orbit classification | B7: Yes
A8: Deployment zone and default decision | B8: Yes
A9: Architecture diagram | B9: Yes
A10: Tool/MCP inventory | B10: Required | C10: Classify tools/MCP servers by read/write capability, action impact, reversibility, auth model, and auditability. | D10: ABOM / Tool registry
A11: Data-source inventory | B11: Yes
A12: Identity model | B12: Yes
A13: Authorization model | B13: Yes
A14: Policy enforcement model | B14: Yes
A15: Observability model | B15: Yes
A16: Recovery and rollback model | B16: Yes
A17: Threat model and mitigation plan | B17: Yes
A18: Evidence tier summary | B18: Yes
A19: Open control gaps | B19: Yes
A20: Risk acceptance record if applicable | B20: Yes
A21: Reassessment date and triggers | B21: Yes

Sheet Deployment Gates
A1: Deployment Gates
A2: Default deployment decision by orbit
A4: Orbit | B4: SMI Range | C4: Default Deployment Decision | D4: Minimum Required Action
A5: Stable Orbit | B5: +40 to +100 | C5: Approved for scale with monitoring | D5: Maintain evidence and reassessment cadence
A6: Controlled Orbit | B6: +15 to +39 | C6: Approved with standard controls | D6: Proceed with standard governance controls
A7: Edge Orbit | B7: -14 to +14 | C7: Pilot, sandbox, or limited production only | D7: Architecture review and active control uplift
A8: Unstable Orbit | B8: -15 to -39 | C8: Do not expand; control uplift required | D8: Increase gravity, reduce force, or formal exception
A9: Critical Orbit | B9: -40 to -100 | C9: Do not deploy without formal exception | D9: Executive risk acceptance and major control uplift

Sheet Control Uplift Planner
A1: Control Uplift Planner
A2: Recommended actions based on weakest Enterprise Gravity dimension
A4: Weakest Gravity Dimension | B4: Recommended Control Uplift | C4: Evidence Target
A5: Identity | B5: Assign dedicated workload identity; remove shared credentials; add ownership metadata. | C5: Tier 3+ identity test or Tier 4 runtime identity logs
A6: Authorization | B6: Apply least privilege by tool, workflow, environment, and risk level; add JIT access where needed. | C6: Permission boundary evidence and access logs
A7: Policy Enforcement | B7: Add pre-execution and runtime policy checks; externalize policy decisions where practical. | C7: Policy-as-code tests and runtime decision logs
A8: Observability | B8: Capture prompt, plan, tool-call, policy, approval, action, and outcome traces. | C8: End-to-end trace samples
A9: Governance and Lifecycle | B9: Register agent, model, tools, memory, and policies in catalog; define owner and lifecycle. | C9: Catalog record and approval workflow
A10: Recovery and Resilience | B10: Add kill switch, rollback, circuit breaker, blast-radius isolation, and recovery drills. | C10: Rollback/kill-switch test evidence
A11: Assurance and Evaluation | B11: Add scenario tests, red-team tests, runtime evaluation, drift monitoring, and outcome validation. | C11: Evaluation reports and runtime monitor evidence

Sheet Standards Map
A1: Standards Alignment
A2: ASF complements existing risk, security, management-system, and policy frameworks
A4: Framework | B4: Primary Purpose | C4: ASF Relationship | D4: Source URL
A5: NIST AI RMF | B5: AI risk management through Govern, Map, Measure, Manage | C5: Agent-level stability scoring inside broader AI risk management | D5: https://airc.nist.gov/airmf-resources/airmf/5-sec-core/
A6: ISO/IEC 42001 | B6: AI management-system requirements and guidance | C6: Architecture assessment method for agentic systems under AIMS | D6: https://www.iso.org/standard/42001
A7: OWASP Agentic AI | B7: Threats and mitigations for agentic AI | C7: Input to Assurance, Policy, and threat-model gates | D7: https://genai.owasp.org/resource/agentic-ai-threats-and-mitigations/
A8: OWASP Multi-Agent Threat Modeling | B8: Threat modeling for multi-agent systems | C8: Threat model gate for multi-agent and high-force agents | D8: https://genai.owasp.org/resource/multi-agentic-system-threat-modeling-guide-v1-0/
A9: OPA/Rego | B9: Policy-as-code and externalized policy decisions | C9: Enterprise Gravity component for policy enforcement | D9: https://openpolicyagent.org/docs/policy-language
A10: Zero Trust | B10: Continuous verification of access | C10: Extended to agent identity, context, memory, tools, and actions | D10: https://www.nist.gov/publications/zero-trust-architecture
A118: License | B118: © 2026 Sumir Arora. Licensed under Creative Commons Attribution 4.0 International (CC BY 4.0).

Sheet Change Log
A1: ASF Workbook Change Log - v1.0 Initial Public Release
A2: Version history through v1.0 Initial Public Release
A4: Version | B4: Change | C4: Rationale
A5: 0.2 | B5: Added Basic and Advanced scoring modes | C5: Equal-weight scoring alone is not sufficient for production contexts
A6: 0.2 | B6: Added Evidence Tiers | C6: EGI scores must be supported by control evidence
A7: 0.2 | B7: Added ABOM template | C7: Agents need component and dependency inventory
A8: 0.2 | B8: Added Threat Model gate | C8: High-force agents require security analysis
A9: 0.2 | B9: Added Domain Overlays | C9: Different agent domains require different scoring emphasis
A10: 0.2 | B10: Added Risk Acceptance workflow | C10: Negative SMI requires formal governance path
A11: 0.2 | B11: Added Architecture Review Packet | C11: Makes ASF usable in ARB / governance review
A12: 0.2 | B12: Added Deployment Gates | C12: Connects orbit to decision action
A13: 0.2 | B13: Added dashboard warnings | C13: Surfaces governance debt, missing ABOM, threat model needs
A14: 0.1 | B14: Initial ASF workbook | C14: AFI, EGI, SMI, orbit, rubrics, standards map
A15: 46208 | B15: v0.3 | C15: Added editorial hardening references and real worked example sheet.
A16: 0.4 | B16: Replaced real example with anonymized financial-services client-request automation agent and proofread publication package. | C16: Aligns whitepaper/workbook example with stronger executive-facing use case and removes API-change naming inconsistency.
A17: v0.4 Public RFC | B17: 2026-07-06 | C17: Aligned workbook sample rows with whitepaper summary values; added publication license/status metadata.
A18: v1.0 | B18: Clarified ASF assessment unit as agentic system instance and expanded ABOM/tool-MCP boundary fields. | C18: Prevents misinterpretation that ASF scores a naked model or agent without tools, memory, identity, permissions, and context.
A19: v1.0 | B19: Corrected the Threat Model gate to reference valid orbits (Edge, Unstable, Critical) | C19: Aligned the gate with the five-orbit taxonomy used across the Dashboard and Deployment Gates tabs

Sheet Real Example
A1: ASF Real Worked Example - Agentic System Instance Assessment
A2: Representative financial-services client-servicing pattern; client, vendor, and architecture identifiers generalized.
A4: Metric | B4: Value | C4: Interpretation
A5: AFI | B5: 60 | C5: Moderate-high force because the agent can touch regulated client and financial-servicing workflows.
A6: EGI | B6: 66 | C6: Meaningful gravity: strong identity, authorization, and runtime policy; weaker runtime assurance and recovery evidence.
A7: SMI | B7: 6 | C7: Edge Orbit: positive but thin stability margin.
A8: Deployment Decision | B8: Pilot / limited production only | C8: Do not expand autonomy until runtime assurance, audit-grade decision provenance, and recovery evidence improve.
A10: ABOM Category | B10: Anonymized Contents
A11: Agent purpose | B11: Interpret client-servicing requests, retrieve client context, prepare or execute servicing actions, and route high-impact requests for advisor approval.
A12: Runtime | B12: Enterprise agent runtime integrated with bounded servicing-action catalog, tool broker, API gateway, and client-servicing workflow.
A13: Tools | B13: Servicing APIs with write access, CRM read access, document service, policy/risk classifier, advisor approval workflow, and notification channel.
A14: Data sources | B14: Client CRM and account systems containing regulated PII and financial data; approved servicing policy and procedure sources.
A15: Memory | B15: Session and task memory only; no long-term, cross-client, or self-maintained enterprise memory.
A16: Identity and authorization | B16: Distinct agent identity with on-behalf-of delegation; tool and environment scopes enforced through gateway and broker controls.
A17: Explicit restrictions | B17: No autonomous high-impact financial action, no cross-client memory, no self-approved exceptions, and no bypass of advisor approval or policy gates.
A20: AFI Dimension | B20: Score | C20: Rationale
A21: Decision Autonomy | B21: 3 | C21: Executes low-impact actions under policy; high-impact financial or client-impacting actions require explicit advisor approval.
A22: Decision Velocity | B22: 3 | C22: Event-driven decisions triggered by client-servicing requests.
A23: Operational Reach | B23: 3 | C23: Touches servicing, CRM, document, and account-related APIs within one business domain.
A24: Operational Criticality | B24: 5 | C24: Incorrect action can affect regulated client financial records, account servicing, compliance exposure, and client trust.
A25: Adaptability | B25: 3 | C25: Generates plans dynamically over retrieved client context, bounded by a defined servicing-action catalog.
A26: Collaboration Complexity | B26: 2 | C26: Collaborates with advisors and workflow systems; no dynamic multi-agent coordination.
A27: Persistence and Memory | B27: 2 | C27: Uses short-term task memory only; no long-term or cross-client memory.
A28: Total | B28: 21 | C28: AFI = 21 / 35 x 100 = 60.0
A31: EGI Dimension | B31: Score | C31: Evidence Tier | D31: Evidence Example
A32: Identity | B32: 4 | C32: 3 | D32: Distinct agent identity with strong authentication and on-behalf-of delegation; tested evidence required to sustain a 4.
A33: Authorization | B33: 4 | C33: 3 | D33: Least privilege by tool and environment, gateway-enforced, with delegated context carried through the request path.
A34: Policy Enforcement | B34: 4 | C34: 4 | D34: Runtime enforcement at the gateway with external inspection at defined control points; runtime-verified.
A35: Observability | B35: 3 | C35: 3 | D35: Gateway and tool-call logs plus partial prompt, plan, and action traces; not yet full audit-grade end-to-end provenance.
A36: Governance and Lifecycle | B36: 3 | C36: 3 | D36: Catalogued with lifecycle approval and reviewed by AI risk, architecture, and change governance.
A37: Recovery and Resilience | B37: 3 | C37: 3 | D37: Gateway kill switch and advisor approval gates exist; rollback or compensating control for executed financial actions is only partly tested.
A38: Assurance and Evaluation | B38: 2 | C38: 2 | D38: Pre-release scenario testing exists; no continuous runtime evaluation, drift detection, or outcome validation yet.
A39: Total | B39: 23 | C39: - | D39: EGI = 23 / 35 x 100 = 66.0
A42: Control Uplift | B42: Reason
A43: Add runtime evaluation for client-servicing decisions | B43: High-impact or ambiguous client requests should be evaluated at runtime before execution or approval routing.
A44: Increase observability to audit-grade decision provenance | B44: Reviewers should reconstruct initiating user, delegated authority, prompt, retrieved client context, plan, policy result, tool call, approval decision, action, and outcome end to end.
A45: Test rollback and compensating controls | B45: Some financial or client-record actions cannot be simply undone; compensating processes must be tested and evidenced.
A46: Keep advisor approval for high-impact workflows | B46: Human accountability remains necessary for transfers, sensitive data changes, exceptions, and elevated-risk servicing actions until SMI improves.
A47: Require threat modeling before autonomy expansion | B47: The agent touches regulated PII and financial workflows; model prompt injection, tool misuse, delegated-authority abuse, approval bypass, and data-exfiltration paths.
A78: © 2026 Sumir Arora. Licensed under Creative Commons Attribution 4.0 International (CC BY 4.0).
