Workbook

Sheet Dashboard
A1: Agentic Stability Framework v1.0 - Initial Public Release Dashboard
A2: Portfolio summary for Agentic Force, Enterprise Gravity, Stability Margin, and governance readiness
A4: Metric | B4: Value | D4: Orbit | E4: Count | F4: Default Action
A5: Total Agents | B5: =COUNTA(Assessment!A5:A104) -> 5 | D5: Stable Orbit | E5: =COUNTIF(Assessment!AH5:AH104,"Stable Orbit") -> 1 | F5: Scale with monitoring
A6: Average AFI | B6: =IFERROR(AVERAGE(Assessment!U5:U104),"") -> 61.714286 | D6: Controlled Orbit | E6: =COUNTIF(Assessment!AH5:AH104,"Controlled Orbit") -> 0 | F6: Proceed with controls
A7: Average EGI | B7: =IFERROR(AVERAGE(Assessment!V5:V104),"") -> 66.857143 | D7: Edge Orbit | E7: =COUNTIF(Assessment!AH5:AH104,"Edge Orbit") -> 3 | F7: Pilot / limited production
A8: Average SMI | B8: =IFERROR(AVERAGE(Assessment!W5:W104),"") -> 5.1428571 | D8: Unstable Orbit | E8: =COUNTIF(Assessment!AH5:AH104,"Unstable Orbit") -> 1 | F8: Control uplift required
A9: Negative SMI Agents | B9: =COUNTIF(Assessment!W5:W104,"<0") -> 2 | D9: Critical Orbit | E9: =COUNTIF(Assessment!AH5:AH104,"Critical Orbit") -> 0 | F9: Do not deploy
A10: ABOM Missing | B10: =COUNTIF(Assessment!Z5:Z104,"No") -> 2
A11: Threat Model Required | B11: =COUNTIF(Assessment!AA5:AA104,"Yes") -> 4
A12: Risk Acceptance Required | B12: =COUNTIF(Assessment!AB5:AB104,"Yes") -> 2
A13: Capped by Rule | B13: =COUNTIF(Assessment!AF5:AF104,"<>None")-COUNTBLANK(Assessment!AF5:AF104) -> 4
A15: Agent Snapshot
A16: Agent | B16: Domain | C16: AFI | D16: EGI | E16: SMI | F16: Final Orbit | G16: Rule Fired | H16: Next Uplift
A17: =IF(Assessment!$A5="","",Assessment!A5) -> Documentation Assistant | B17: =IF(Assessment!$A5="","",Assessment!B5) -> Knowledge / Documentation | C17: =IF(Assessment!$A5="","",Assessment!U5) -> 20 | D17: =IF(Assessment!$A5="","",Assessment!V5) -> 71.428571 | E17: =IF(Assessment!$A5="","",Assessment!W5) -> 51.428571 | F17: =IF(Assessment!$A5="","",Assessment!AH5) -> Stable Orbit | G17: =IF(Assessment!$A5="","",Assessment!AG5) -> - | H17: =IF(Assessment!$A5="","",Assessment!AE5) -> Add pre-execution and runtime policy checks; externalize policy decisions where practical.
A18: =IF(Assessment!$A6="","",Assessment!A6) -> Client-Request Automation Agent | B18: =IF(Assessment!$A6="","",Assessment!B6) -> Financial Operations | C18: =IF(Assessment!$A6="","",Assessment!U6) -> 60 | D18: =IF(Assessment!$A6="","",Assessment!V6) -> 65.714286 | E18: =IF(Assessment!$A6="","",Assessment!W6) -> 5.7142857 | F18: =IF(Assessment!$A6="","",Assessment!AH6) -> Edge Orbit | G18: =IF(Assessment!$A6="","",Assessment!AG6) -> R3 evidence tier 3<4; | H18: =IF(Assessment!$A6="","",Assessment!AE6) -> Add scenario tests, red-team tests, runtime evaluation, drift monitoring, and outcome validation.
A19: =IF(Assessment!$A7="","",Assessment!A7) -> Kubernetes Deployment Agent | B19: =IF(Assessment!$A7="","",Assessment!B7) -> Software Delivery | C19: =IF(Assessment!$A7="","",Assessment!U7) -> 65.714286 | D19: =IF(Assessment!$A7="","",Assessment!V7) -> 65.714286 | E19: =IF(Assessment!$A7="","",Assessment!W7) -> 0 | F19: =IF(Assessment!$A7="","",Assessment!AH7) -> Edge Orbit | G19: =IF(Assessment!$A7="","",Assessment!AG7) -> R1 concentrated force; R3 evidence tier 3<4; | H19: =IF(Assessment!$A7="","",Assessment!AE7) -> Add scenario tests, red-team tests, runtime evaluation, drift monitoring, and outcome validation.
A20: =IF(Assessment!$A8="","",Assessment!A8) -> Multi-Agent SDLC Workflow | B20: =IF(Assessment!$A8="","",Assessment!B8) -> Multi-Agent SDLC | C20: =IF(Assessment!$A8="","",Assessment!U8) -> 74.285714 | D20: =IF(Assessment!$A8="","",Assessment!V8) -> 62.857143 | E20: =IF(Assessment!$A8="","",Assessment!W8) -> -11.428571 | F20: =IF(Assessment!$A8="","",Assessment!AH8) -> Edge Orbit | G20: =IF(Assessment!$A8="","",Assessment!AG8) -> R1 concentrated force; | H20: =IF(Assessment!$A8="","",Assessment!AE8) -> Assign dedicated workload identity; remove shared credentials; add ownership metadata.
A21: =IF(Assessment!$A9="","",Assessment!A9) -> Autonomous Production Remediation Agent | B21: =IF(Assessment!$A9="","",Assessment!B9) -> Cloud / Infrastructure | C21: =IF(Assessment!$A9="","",Assessment!U9) -> 88.571429 | D21: =IF(Assessment!$A9="","",Assessment!V9) -> 68.571429 | E21: =IF(Assessment!$A9="","",Assessment!W9) -> -20 | F21: =IF(Assessment!$A9="","",Assessment!AH9) -> Unstable Orbit | G21: =IF(Assessment!$A9="","",Assessment!AG9) -> R1 concentrated force; R3 evidence tier 3<4; | H21: =IF(Assessment!$A9="","",Assessment!AE9) -> Add scenario tests, red-team tests, runtime evaluation, drift monitoring, and outcome validation.
A22: =IF(Assessment!$A10="","",Assessment!A10) | B22: =IF(Assessment!$A10="","",Assessment!B10) | C22: =IF(Assessment!$A10="","",Assessment!U10) | D22: =IF(Assessment!$A10="","",Assessment!V10) | E22: =IF(Assessment!$A10="","",Assessment!W10) | F22: =IF(Assessment!$A10="","",Assessment!AH10) | G22: =IF(Assessment!$A10="","",Assessment!AG10) | H22: =IF(Assessment!$A10="","",Assessment!AE10)
A23: =IF(Assessment!$A11="","",Assessment!A11) | B23: =IF(Assessment!$A11="","",Assessment!B11) | C23: =IF(Assessment!$A11="","",Assessment!U11) | D23: =IF(Assessment!$A11="","",Assessment!V11) | E23: =IF(Assessment!$A11="","",Assessment!W11) | F23: =IF(Assessment!$A11="","",Assessment!AH11) | G23: =IF(Assessment!$A11="","",Assessment!AG11) | H23: =IF(Assessment!$A11="","",Assessment!AE11)
A24: =IF(Assessment!$A12="","",Assessment!A12) | B24: =IF(Assessment!$A12="","",Assessment!B12) | C24: =IF(Assessment!$A12="","",Assessment!U12) | D24: =IF(Assessment!$A12="","",Assessment!V12) | E24: =IF(Assessment!$A12="","",Assessment!W12) | F24: =IF(Assessment!$A12="","",Assessment!AH12) | G24: =IF(Assessment!$A12="","",Assessment!AG12) | H24: =IF(Assessment!$A12="","",Assessment!AE12)
A25: =IF(Assessment!$A13="","",Assessment!A13) | B25: =IF(Assessment!$A13="","",Assessment!B13) | C25: =IF(Assessment!$A13="","",Assessment!U13) | D25: =IF(Assessment!$A13="","",Assessment!V13) | E25: =IF(Assessment!$A13="","",Assessment!W13) | F25: =IF(Assessment!$A13="","",Assessment!AH13) | G25: =IF(Assessment!$A13="","",Assessment!AG13) | H25: =IF(Assessment!$A13="","",Assessment!AE13)
A26: =IF(Assessment!$A14="","",Assessment!A14) | B26: =IF(Assessment!$A14="","",Assessment!B14) | C26: =IF(Assessment!$A14="","",Assessment!U14) | D26: =IF(Assessment!$A14="","",Assessment!V14) | E26: =IF(Assessment!$A14="","",Assessment!W14) | F26: =IF(Assessment!$A14="","",Assessment!AH14) | G26: =IF(Assessment!$A14="","",Assessment!AG14) | H26: =IF(Assessment!$A14="","",Assessment!AE14)
A27: =IF(Assessment!$A15="","",Assessment!A15) | B27: =IF(Assessment!$A15="","",Assessment!B15) | C27: =IF(Assessment!$A15="","",Assessment!U15) | D27: =IF(Assessment!$A15="","",Assessment!V15) | E27: =IF(Assessment!$A15="","",Assessment!W15) | F27: =IF(Assessment!$A15="","",Assessment!AH15) | G27: =IF(Assessment!$A15="","",Assessment!AG15) | H27: =IF(Assessment!$A15="","",Assessment!AE15)
A28: =IF(Assessment!$A16="","",Assessment!A16) | B28: =IF(Assessment!$A16="","",Assessment!B16) | C28: =IF(Assessment!$A16="","",Assessment!U16) | D28: =IF(Assessment!$A16="","",Assessment!V16) | E28: =IF(Assessment!$A16="","",Assessment!W16) | F28: =IF(Assessment!$A16="","",Assessment!AH16) | G28: =IF(Assessment!$A16="","",Assessment!AG16) | H28: =IF(Assessment!$A16="","",Assessment!AE16)
... A36: =IF(Assessment!$A24="","",Assessment!A24) | B36: =IF(Assessment!$A24="","",Assessment!B24) | C36: =IF(Assessment!$A24="","",Assessment!U24) | D36: =IF(Assessment!$A24="","",Assessment!V24) | E36: =IF(Assessment!$A24="","",Assessment!W24) | F36: =IF(Assessment!$A24="","",Assessment!AH24) | G36: =IF(Assessment!$A24="","",Assessment!AG24) | H36: =IF(Assessment!$A24="","",Assessment!AE24)

Sheet Assessment
A1: ASF Agentic System Instance Assessment v1.0 - Initial Public Release
A2: Enter force/gravity scores for the deployed agentic system instance. Formulas compute AFI, EGI, SMI, orbit, and action.
A4: Agent Name | B4: Domain Overlay | C4: Deployment Zone | D4: Scoring Mode | E4: Decision Autonomy | F4: Decision Velocity | G4: Operational Reach | H4: Operational Criticality | I4: Adaptability | J4: Collaboration Complexity | K4: Persistence and Memory | L4: Identity | M4: Authorization | N4: Policy Enforcement | O4: Observability | P4: Governance and Lifecycle | Q4: Recovery and Resilience | R4: Assurance and Evaluation | S4: Min Evidence Tier | T4: Evidence Warning | U4: AFI | V4: EGI | W4: SMI | X4: SMI Orbit | Y4: Deployment Decision | Z4: ABOM Complete | AA4: Threat Model Required | AB4: Risk Acceptance Required | AC4: Weakest Gravity | AD4: Highest Force | AE4: Next Control Uplift | AF4: Non-Compensatory Ceiling | AG4: Rule Fired | AH4: Final Orbit | AI4: Threat Model Completed | AJ4: Review Date
A5: Documentation Assistant | B5: Knowledge / Documentation | C5: Assisted Zone | D5: Basic | E5: 1 | F5: 1 | G5: 1 | H5: 1 | I5: 1 | J5: 1 | K5: 1 | L5: 4 | M5: 4 | N5: 3 | O5: 4 | P5: 4 | Q5: 3 | R5: 3 | S5: 3 | T5: =IF($A5="","",IF(AND(MAX(L5:R5)>3,S5<3),"Warning: EGI >3 needs Tier 3+ evidence",IF(AND(C5="Autonomous Operations Zone",S5<4),"Warning: Autonomous zone needs Tier 4 evidence","OK"))) -> OK | U5: =IF($A5="","",IF($D5="Basic",SUM(E5:K5)/35*100,SUMPRODUCT(E5:K5,INDEX('Weighted Scoring'!$B$5:$H$13,MATCH($B5,'Weighted Scoring'!$A$5:$A$13,0),0))/SUMPRODUCT(5,INDEX('Weighted Scoring'!$B$5:$H$13,MATCH($B5,'Weighted Scoring'!$A$5:$A$13,0),0))*100)) -> 20 | V5: =IF($A5="","",IF($D5="Basic",SUM(L5:R5)/35*100,SUMPRODUCT(L5:R5,INDEX('Weighted Scoring'!$I$5:$O$13,MATCH($B5,'Weighted Scoring'!$A$5:$A$13,0),0))/SUMPRODUCT(5,INDEX('Weighted Scoring'!$I$5:$O$13,MATCH($B5,'Weighted Scoring'!$A$5:$A$13,0),0))*100)) -> 71.428571 | W5: =IF($A5="","",V5-U5) -> 51.428571 | X5: =IF($A5="","",IF(W5>=40,"Stable Orbit",IF(W5>=15,"Controlled Orbit",IF(W5>=-14,"Edge Orbit",IF(W5>=-39,"Unstable Orbit","Critical Orbit"))))) -> Stable Orbit | Y5: =IF($A5="","",INDEX('Deployment Gates'!$C$5:$C$9,MATCH(AH5,'Deployment Gates'!$A$5:$A$9,0))) -> Approved for scale with monitoring | Z5: Yes | AA5: =IF($A5="","",IF(OR(AH5="Edge Orbit",AH5="Unstable Orbit",AH5="Critical Orbit",H5>=4,G5>=4,E5>=4,J5>=4),"Yes","No")) -> No | AB5: =IF($A5="","",IF(W5<0,"Yes","No")) -> No | AC5: =IF($A5="","",INDEX($L$4:$R$4,1,MATCH(MIN(L5:R5),L5:R5,0))&IF(COUNTIF(L5:R5,MIN(L5:R5))>1," (+"&(COUNTIF(L5:R5,MIN(L5:R5))-1)&" tied)","")) -> Policy Enforcement (+2 tied) | AD5: =IF($A5="","",INDEX($E$4:$K$4,1,MATCH(MAX(E5:K5),E5:K5,0))&IF(COUNTIF(E5:K5,MAX(E5:K5))>1," (+"&(COUNTIF(E5:K5,MAX(E5:K5))-1)&" tied)","")) -> Decision Autonomy (+6 tied) | AE5: =IF($A5="","",INDEX('Control Uplift Planner'!$B$5:$B$11,MATCH(INDEX($L$4:$R$4,1,MATCH(MIN(L5:R5),L5:R5,0)),'Control Uplift Planner'!$A$5:$A$11,0))) -> Add pre-execution and runtime policy checks; externalize policy decisions where practical. | AF5: =IF($A5="","",IF(MIN(IF(AND(E5>=4,H5>=4),3,9),IF(AND(OR(C5="Governed Operations Zone",C5="Autonomous Operations Zone"),E5>=3),IF(MIN(L5:N5)=0,2,IF(MIN(L5:N5)=1,3,9)),9),IF(AND(OR(C5="Governed Operations Zone",C5="Autonomous Operations Zone"),S5<4),3,9))=9,"None",IF(MIN(IF(AND(E5>=4,H5>=4),3,9),IF(AND(OR(C5="Governed Operations Zone",C5="Autonomous Operations Zone"),E5>=3),IF(MIN(L5:N5)=0,2,IF(MIN(L5:N5)=1,3,9)),9),IF(AND(OR(C5="Governed Operations Zone",C5="Autonomous Operations Zone"),S5<4),3,9))=1,"Critical Orbit",IF(MIN(IF(AND(E5>=4,H5>=4),3,9),IF(AND(OR(C5="Governed Operations Zone",C5="Autonomous Operations Zone"),E5>=3),IF(MIN(L5:N5)=0,2,IF(MIN(L5:N5)=1,3,9)),9),IF(AND(OR(C5="Governed Operations Zone",C5="Autonomous Operations Zone"),S5<4),3,9))=2,"Unstable Orbit","Edge Orbit")))) -> None | AG5: =IF($A5="","",IF(IF(AND(E5>=4,H5>=4),"R1 concentrated force; ","")&IF(AND(OR(C5="Governed Operations Zone",C5="Autonomous Operations Zone"),E5>=3,MIN(L5:N5)<=1),"R2 mandatory control "&INDEX($L$4:$N$4,1,MATCH(MIN(L5:N5),L5:N5,0))&"="&MIN(L5:N5)&"; ","")&IF(AND(OR(C5="Governed Operations Zone",C5="Autonomous Operations Zone"),S5<4),"R3 evidence tier "&S5&"<4; ","")="","-",IF(AND(E5>=4,H5>=4),"R1 concentrated force; ","")&IF(AND(OR(C5="Governed Operations Zone",C5="Autonomous Operations Zone"),E5>=3,MIN(L5:N5)<=1),"R2 mandatory control "&INDEX($L$4:$N$4,1,MATCH(MIN(L5:N5),L5:N5,0))&"="&MIN(L5:N5)&"; ","")&IF(AND(OR(C5="Governed Operations Zone",C5="Autonomous Operations Zone"),S5<4),"R3 evidence tier "&S5&"<4; ",""))) -> - | AH5: =IF($A5="","",IF(MIN(IF(X5="Critical Orbit",1,IF(X5="Unstable Orbit",2,IF(X5="Edge Orbit",3,IF(X5="Controlled Orbit",4,5)))),IF(AF5="None",9,IF(AF5="Critical Orbit",1,IF(AF5="Unstable Orbit",2,IF(AF5="Edge Orbit",3,IF(AF5="Controlled Orbit",4,5))))))=1,"Critical Orbit",IF(MIN(IF(X5="Critical Orbit",1,IF(X5="Unstable Orbit",2,IF(X5="Edge Orbit",3,IF(X5="Controlled Orbit",4,5)))),IF(AF5="None",9,IF(AF5="Critical Orbit",1,IF(AF5="Unstable Orbit",2,IF(AF5="Edge Orbit",3,IF(AF5="Controlled Orbit",4,5))))))=2,"Unstable Orbit",IF(MIN(IF(X5="Critical Orbit",1,IF(X5="Unstable Orbit",2,IF(X5="Edge Orbit",3,IF(X5="Controlled Orbit",4,5)))),IF(AF5="None",9,IF(AF5="Critical Orbit",1,IF(AF5="Unstable Orbit",2,IF(AF5="Edge Orbit",3,IF(AF5="Controlled Orbit",4,5))))))=3,"Edge Orbit",IF(MIN(IF(X5="Critical Orbit",1,IF(X5="Unstable Orbit",2,IF(X5="Edge Orbit",3,IF(X5="Controlled Orbit",4,5)))),IF(AF5="None",9,IF(AF5="Critical Orbit",1,IF(AF5="Unstable Orbit",2,IF(AF5="Edge Orbit",3,IF(AF5="Controlled Orbit",4,5))))))=4,"Controlled Orbit","Stable Orbit"))))) -> Stable Orbit | AJ5: 2026-09-30
A6: Client-Request Automation Agent | B6: Financial Operations | C6: Governed Operations Zone | D6: Basic | E6: 3 | F6: 3 | G6: 3 | H6: 5 | I6: 3 | J6: 2 | K6: 2 | L6: 4 | M6: 4 | N6: 4 | O6: 3 | P6: 3 | Q6: 3 | R6: 2 | S6: 3 | T6: =IF($A6="","",IF(AND(MAX(L6:R6)>3,S6<3),"Warning: EGI >3 needs Tier 3+ evidence",IF(AND(C6="Autonomous Operations Zone",S6<4),"Warning: Autonomous zone needs Tier 4 evidence","OK"))) -> OK | U6: =IF($A6="","",IF($D6="Basic",SUM(E6:K6)/35*100,SUMPRODUCT(E6:K6,INDEX('Weighted Scoring'!$B$5:$H$13,MATCH($B6,'Weighted Scoring'!$A$5:$A$13,0),0))/SUMPRODUCT(5,INDEX('Weighted Scoring'!$B$5:$H$13,MATCH($B6,'Weighted Scoring'!$A$5:$A$13,0),0))*100)) -> 60 | V6: =IF($A6="","",IF($D6="Basic",SUM(L6:R6)/35*100,SUMPRODUCT(L6:R6,INDEX('Weighted Scoring'!$I$5:$O$13,MATCH($B6,'Weighted Scoring'!$A$5:$A$13,0),0))/SUMPRODUCT(5,INDEX('Weighted Scoring'!$I$5:$O$13,MATCH($B6,'Weighted Scoring'!$A$5:$A$13,0),0))*100)) -> 65.714286 | W6: =IF($A6="","",V6-U6) -> 5.7142857 | X6: =IF($A6="","",IF(W6>=40,"Stable Orbit",IF(W6>=15,"Controlled Orbit",IF(W6>=-14,"Edge Orbit",IF(W6>=-39,"Unstable Orbit","Critical Orbit"))))) -> Edge Orbit | Y6: =IF($A6="","",INDEX('Deployment Gates'!$C$5:$C$9,MATCH(AH6,'Deployment Gates'!$A$5:$A$9,0))) -> Pilot, sandbox, or limited production only | Z6: Yes | AA6: =IF($A6="","",IF(OR(AH6="Edge Orbit",AH6="Unstable Orbit",AH6="Critical Orbit",H6>=4,G6>=4,E6>=4,J6>=4),"Yes","No")) -> Yes | AB6: =IF($A6="","",IF(W6<0,"Yes","No")) -> No | AC6: =IF($A6="","",INDEX($L$4:$R$4,1,MATCH(MIN(L6:R6),L6:R6,0))&IF(COUNTIF(L6:R6,MIN(L6:R6))>1," (+"&(COUNTIF(L6:R6,MIN(L6:R6))-1)&" tied)","")) -> Assurance and Evaluation | AD6: =IF($A6="","",INDEX($E$4:$K$4,1,MATCH(MAX(E6:K6),E6:K6,0))&IF(COUNTIF(E6:K6,MAX(E6:K6))>1," (+"&(COUNTIF(E6:K6,MAX(E6:K6))-1)&" tied)","")) -> Operational Criticality | AE6: =IF($A6="","",INDEX('Control Uplift Planner'!$B$5:$B$11,MATCH(INDEX($L$4:$R$4,1,MATCH(MIN(L6:R6),L6:R6,0)),'Control Uplift Planner'!$A$5:$A$11,0))) -> Add scenario tests, red-team tests, runtime evaluation, drift monitoring, and outcome validation. | AF6: =IF($A6="","",IF(MIN(IF(AND(E6>=4,H6>=4),3,9),IF(AND(OR(C6="Governed Operations Zone",C6="Autonomous Operations Zone"),E6>=3),IF(MIN(L6:N6)=0,2,IF(MIN(L6:N6)=1,3,9)),9),IF(AND(OR(C6="Governed Operations Zone",C6="Autonomous Operations Zone"),S6<4),3,9))=9,"None",IF(MIN(IF(AND(E6>=4,H6>=4),3,9),IF(AND(OR(C6="Governed Operations Zone",C6="Autonomous Operations Zone"),E6>=3),IF(MIN(L6:N6)=0,2,IF(MIN(L6:N6)=1,3,9)),9),IF(AND(OR(C6="Governed Operations Zone",C6="Autonomous Operations Zone"),S6<4),3,9))=1,"Critical Orbit",IF(MIN(IF(AND(E6>=4,H6>=4),3,9),IF(AND(OR(C6="Governed Operations Zone",C6="Autonomous Operations Zone"),E6>=3),IF(MIN(L6:N6)=0,2,IF(MIN(L6:N6)=1,3,9)),9),IF(AND(OR(C6="Governed Operations Zone",C6="Autonomous Operations Zone"),S6<4),3,9))=2,"Unstable Orbit","Edge Orbit")))) -> Edge Orbit | AG6: =IF($A6="","",IF(IF(AND(E6>=4,H6>=4),"R1 concentrated force; ","")&IF(AND(OR(C6="Governed Operations Zone",C6="Autonomous Operations Zone"),E6>=3,MIN(L6:N6)<=1),"R2 mandatory control "&INDEX($L$4:$N$4,1,MATCH(MIN(L6:N6),L6:N6,0))&"="&MIN(L6:N6)&"; ","")&IF(AND(OR(C6="Governed Operations Zone",C6="Autonomous Operations Zone"),S6<4),"R3 evidence tier "&S6&"<4; ","")="","-",IF(AND(E6>=4,H6>=4),"R1 concentrated force; ","")&IF(AND(OR(C6="Governed Operations Zone",C6="Autonomous Operations Zone"),E6>=3,MIN(L6:N6)<=1),"R2 mandatory control "&INDEX($L$4:$N$4,1,MATCH(MIN(L6:N6),L6:N6,0))&"="&MIN(L6:N6)&"; ","")&IF(AND(OR(C6="Governed Operations Zone",C6="Autonomous Operations Zone"),S6<4),"R3 evidence tier "&S6&"<4; ",""))) -> R3 evidence tier 3<4; | AH6: =IF($A6="","",IF(MIN(IF(X6="Critical Orbit",1,IF(X6="Unstable Orbit",2,IF(X6="Edge Orbit",3,IF(X6="Controlled Orbit",4,5)))),IF(AF6="None",9,IF(AF6="Critical Orbit",1,IF(AF6="Unstable Orbit",2,IF(AF6="Edge Orbit",3,IF(AF6="Controlled Orbit",4,5))))))=1,"Critical Orbit",IF(MIN(IF(X6="Critical Orbit",1,IF(X6="Unstable Orbit",2,IF(X6="Edge Orbit",3,IF(X6="Controlled Orbit",4,5)))),IF(AF6="None",9,IF(AF6="Critical Orbit",1,IF(AF6="Unstable Orbit",2,IF(AF6="Edge Orbit",3,IF(AF6="Controlled Orbit",4,5))))))=2,"Unstable Orbit",IF(MIN(IF(X6="Critical Orbit",1,IF(X6="Unstable Orbit",2,IF(X6="Edge Orbit",3,IF(X6="Controlled Orbit",4,5)))),IF(AF6="None",9,IF(AF6="Critical Orbit",1,IF(AF6="Unstable Orbit",2,IF(AF6="Edge Orbit",3,IF(AF6="Controlled Orbit",4,5))))))=3,"Edge Orbit",IF(MIN(IF(X6="Critical Orbit",1,IF(X6="Unstable Orbit",2,IF(X6="Edge Orbit",3,IF(X6="Controlled Orbit",4,5)))),IF(AF6="None",9,IF(AF6="Critical Orbit",1,IF(AF6="Unstable Orbit",2,IF(AF6="Edge Orbit",3,IF(AF6="Controlled Orbit",4,5))))))=4,"Controlled Orbit","Stable Orbit"))))) -> Edge Orbit | AJ6: 2026-09-30
A7: Kubernetes Deployment Agent | B7: Software Delivery | C7: Governed Operations Zone | D7: Basic | E7: 4 | F7: 3 | G7: 4 | H7: 4 | I7: 3 | J7: 2 | K7: 3 | L7: 4 | M7: 3 | N7: 4 | O7: 3 | P7: 3 | Q7: 4 | R7: 2 | S7: 3 | T7: =IF($A7="","",IF(AND(MAX(L7:R7)>3,S7<3),"Warning: EGI >3 needs Tier 3+ evidence",IF(AND(C7="Autonomous Operations Zone",S7<4),"Warning: Autonomous zone needs Tier 4 evidence","OK"))) -> OK | U7: =IF($A7="","",IF($D7="Basic",SUM(E7:K7)/35*100,SUMPRODUCT(E7:K7,INDEX('Weighted Scoring'!$B$5:$H$13,MATCH($B7,'Weighted Scoring'!$A$5:$A$13,0),0))/SUMPRODUCT(5,INDEX('Weighted Scoring'!$B$5:$H$13,MATCH($B7,'Weighted Scoring'!$A$5:$A$13,0),0))*100)) -> 65.714286 | V7: =IF($A7="","",IF($D7="Basic",SUM(L7:R7)/35*100,SUMPRODUCT(L7:R7,INDEX('Weighted Scoring'!$I$5:$O$13,MATCH($B7,'Weighted Scoring'!$A$5:$A$13,0),0))/SUMPRODUCT(5,INDEX('Weighted Scoring'!$I$5:$O$13,MATCH($B7,'Weighted Scoring'!$A$5:$A$13,0),0))*100)) -> 65.714286 | W7: =IF($A7="","",V7-U7) -> 0 | X7: =IF($A7="","",IF(W7>=40,"Stable Orbit",IF(W7>=15,"Controlled Orbit",IF(W7>=-14,"Edge Orbit",IF(W7>=-39,"Unstable Orbit","Critical Orbit"))))) -> Edge Orbit | Y7: =IF($A7="","",INDEX('Deployment Gates'!$C$5:$C$9,MATCH(AH7,'Deployment Gates'!$A$5:$A$9,0))) -> Pilot, sandbox, or limited production only | Z7: Yes | AA7: =IF($A7="","",IF(OR(AH7="Edge Orbit",AH7="Unstable Orbit",AH7="Critical Orbit",H7>=4,G7>=4,E7>=4,J7>=4),"Yes","No")) -> Yes | AB7: =IF($A7="","",IF(W7<0,"Yes","No")) -> No | AC7: =IF($A7="","",INDEX($L$4:$R$4,1,MATCH(MIN(L7:R7),L7:R7,0))&IF(COUNTIF(L7:R7,MIN(L7:R7))>1," (+"&(COUNTIF(L7:R7,MIN(L7:R7))-1)&" tied)","")) -> Assurance and Evaluation | AD7: =IF($A7="","",INDEX($E$4:$K$4,1,MATCH(MAX(E7:K7),E7:K7,0))&IF(COUNTIF(E7:K7,MAX(E7:K7))>1," (+"&(COUNTIF(E7:K7,MAX(E7:K7))-1)&" tied)","")) -> Decision Autonomy (+2 tied) | AE7: =IF($A7="","",INDEX('Control Uplift Planner'!$B$5:$B$11,MATCH(INDEX($L$4:$R$4,1,MATCH(MIN(L7:R7),L7:R7,0)),'Control Uplift Planner'!$A$5:$A$11,0))) -> Add scenario tests, red-team tests, runtime evaluation, drift monitoring, and outcome validation. | AF7: =IF($A7="","",IF(MIN(IF(AND(E7>=4,H7>=4),3,9),IF(AND(OR(C7="Governed Operations Zone",C7="Autonomous Operations Zone"),E7>=3),IF(MIN(L7:N7)=0,2,IF(MIN(L7:N7)=1,3,9)),9),IF(AND(OR(C7="Governed Operations Zone",C7="Autonomous Operations Zone"),S7<4),3,9))=9,"None",IF(MIN(IF(AND(E7>=4,H7>=4),3,9),IF(AND(OR(C7="Governed Operations Zone",C7="Autonomous Operations Zone"),E7>=3),IF(MIN(L7:N7)=0,2,IF(MIN(L7:N7)=1,3,9)),9),IF(AND(OR(C7="Governed Operations Zone",C7="Autonomous Operations Zone"),S7<4),3,9))=1,"Critical Orbit",IF(MIN(IF(AND(E7>=4,H7>=4),3,9),IF(AND(OR(C7="Governed Operations Zone",C7="Autonomous Operations Zone"),E7>=3),IF(MIN(L7:N7)=0,2,IF(MIN(L7:N7)=1,3,9)),9),IF(AND(OR(C7="Governed Operations Zone",C7="Autonomous Operations Zone"),S7<4),3,9))=2,"Unstable Orbit","Edge Orbit")))) -> Edge Orbit | AG7: =IF($A7="","",IF(IF(AND(E7>=4,H7>=4),"R1 concentrated force; ","")&IF(AND(OR(C7="Governed Operations Zone",C7="Autonomous Operations Zone"),E7>=3,MIN(L7:N7)<=1),"R2 mandatory control "&INDEX($L$4:$N$4,1,MATCH(MIN(L7:N7),L7:N7,0))&"="&MIN(L7:N7)&"; ","")&IF(AND(OR(C7="Governed Operations Zone",C7="Autonomous Operations Zone"),S7<4),"R3 evidence tier "&S7&"<4; ","")="","-",IF(AND(E7>=4,H7>=4),"R1 concentrated force; ","")&IF(AND(OR(C7="Governed Operations Zone",C7="Autonomous Operations Zone"),E7>=3,MIN(L7:N7)<=1),"R2 mandatory control "&INDEX($L$4:$N$4,1,MATCH(MIN(L7:N7),L7:N7,0))&"="&MIN(L7:N7)&"; ","")&IF(AND(OR(C7="Governed Operations Zone",C7="Autonomous Operations Zone"),S7<4),"R3 evidence tier "&S7&"<4; ",""))) -> R1 concentrated force; R3 evidence tier 3<4; | AH7: =IF($A7="","",IF(MIN(IF(X7="Critical Orbit",1,IF(X7="Unstable Orbit",2,IF(X7="Edge Orbit",3,IF(X7="Controlled Orbit",4,5)))),IF(AF7="None",9,IF(AF7="Critical Orbit",1,IF(AF7="Unstable Orbit",2,IF(AF7="Edge Orbit",3,IF(AF7="Controlled Orbit",4,5))))))=1,"Critical Orbit",IF(MIN(IF(X7="Critical Orbit",1,IF(X7="Unstable Orbit",2,IF(X7="Edge Orbit",3,IF(X7="Controlled Orbit",4,5)))),IF(AF7="None",9,IF(AF7="Critical Orbit",1,IF(AF7="Unstable Orbit",2,IF(AF7="Edge Orbit",3,IF(AF7="Controlled Orbit",4,5))))))=2,"Unstable Orbit",IF(MIN(IF(X7="Critical Orbit",1,IF(X7="Unstable Orbit",2,IF(X7="Edge Orbit",3,IF(X7="Controlled Orbit",4,5)))),IF(AF7="None",9,IF(AF7="Critical Orbit",1,IF(AF7="Unstable Orbit",2,IF(AF7="Edge Orbit",3,IF(AF7="Controlled Orbit",4,5))))))=3,"Edge Orbit",IF(MIN(IF(X7="Critical Orbit",1,IF(X7="Unstable Orbit",2,IF(X7="Edge Orbit",3,IF(X7="Controlled Orbit",4,5)))),IF(AF7="None",9,IF(AF7="Critical Orbit",1,IF(AF7="Unstable Orbit",2,IF(AF7="Edge Orbit",3,IF(AF7="Controlled Orbit",4,5))))))=4,"Controlled Orbit","Stable Orbit"))))) -> Edge Orbit | AJ7: 2026-08-31
A8: Multi-Agent SDLC Workflow | B8: Multi-Agent SDLC | C8: Assisted Zone | D8: Basic | E8: 4 | F8: 3 | G8: 4 | H8: 4 | I8: 4 | J8: 4 | K8: 3 | L8: 3 | M8: 3 | N8: 3 | O8: 4 | P8: 3 | Q8: 3 | R8: 3 | S8: 3 | T8: =IF($A8="","",IF(AND(MAX(L8:R8)>3,S8<3),"Warning: EGI >3 needs Tier 3+ evidence",IF(AND(C8="Autonomous Operations Zone",S8<4),"Warning: Autonomous zone needs Tier 4 evidence","OK"))) -> OK | U8: =IF($A8="","",IF($D8="Basic",SUM(E8:K8)/35*100,SUMPRODUCT(E8:K8,INDEX('Weighted Scoring'!$B$5:$H$13,MATCH($B8,'Weighted Scoring'!$A$5:$A$13,0),0))/SUMPRODUCT(5,INDEX('Weighted Scoring'!$B$5:$H$13,MATCH($B8,'Weighted Scoring'!$A$5:$A$13,0),0))*100)) -> 74.285714 | V8: =IF($A8="","",IF($D8="Basic",SUM(L8:R8)/35*100,SUMPRODUCT(L8:R8,INDEX('Weighted Scoring'!$I$5:$O$13,MATCH($B8,'Weighted Scoring'!$A$5:$A$13,0),0))/SUMPRODUCT(5,INDEX('Weighted Scoring'!$I$5:$O$13,MATCH($B8,'Weighted Scoring'!$A$5:$A$13,0),0))*100)) -> 62.857143 | W8: =IF($A8="","",V8-U8) -> -11.428571 | X8: =IF($A8="","",IF(W8>=40,"Stable Orbit",IF(W8>=15,"Controlled Orbit",IF(W8>=-14,"Edge Orbit",IF(W8>=-39,"Unstable Orbit","Critical Orbit"))))) -> Edge Orbit | Y8: =IF($A8="","",INDEX('Deployment Gates'!$C$5:$C$9,MATCH(AH8,'Deployment Gates'!$A$5:$A$9,0))) -> Pilot, sandbox, or limited production only | Z8: No | AA8: =IF($A8="","",IF(OR(AH8="Edge Orbit",AH8="Unstable Orbit",AH8="Critical Orbit",H8>=4,G8>=4,E8>=4,J8>=4),"Yes","No")) -> Yes | AB8: =IF($A8="","",IF(W8<0,"Yes","No")) -> Yes | AC8: =IF($A8="","",INDEX($L$4:$R$4,1,MATCH(MIN(L8:R8),L8:R8,0))&IF(COUNTIF(L8:R8,MIN(L8:R8))>1," (+"&(COUNTIF(L8:R8,MIN(L8:R8))-1)&" tied)","")) -> Identity (+5 tied) | AD8: =IF($A8="","",INDEX($E$4:$K$4,1,MATCH(MAX(E8:K8),E8:K8,0))&IF(COUNTIF(E8:K8,MAX(E8:K8))>1," (+"&(COUNTIF(E8:K8,MAX(E8:K8))-1)&" tied)","")) -> Decision Autonomy (+4 tied) | AE8: =IF($A8="","",INDEX('Control Uplift Planner'!$B$5:$B$11,MATCH(INDEX($L$4:$R$4,1,MATCH(MIN(L8:R8),L8:R8,0)),'Control Uplift Planner'!$A$5:$A$11,0))) -> Assign dedicated workload identity; remove shared credentials; add ownership metadata. | AF8: =IF($A8="","",IF(MIN(IF(AND(E8>=4,H8>=4),3,9),IF(AND(OR(C8="Governed Operations Zone",C8="Autonomous Operations Zone"),E8>=3),IF(MIN(L8:N8)=0,2,IF(MIN(L8:N8)=1,3,9)),9),IF(AND(OR(C8="Governed Operations Zone",C8="Autonomous Operations Zone"),S8<4),3,9))=9,"None",IF(MIN(IF(AND(E8>=4,H8>=4),3,9),IF(AND(OR(C8="Governed Operations Zone",C8="Autonomous Operations Zone"),E8>=3),IF(MIN(L8:N8)=0,2,IF(MIN(L8:N8)=1,3,9)),9),IF(AND(OR(C8="Governed Operations Zone",C8="Autonomous Operations Zone"),S8<4),3,9))=1,"Critical Orbit",IF(MIN(IF(AND(E8>=4,H8>=4),3,9),IF(AND(OR(C8="Governed Operations Zone",C8="Autonomous Operations Zone"),E8>=3),IF(MIN(L8:N8)=0,2,IF(MIN(L8:N8)=1,3,9)),9),IF(AND(OR(C8="Governed Operations Zone",C8="Autonomous Operations Zone"),S8<4),3,9))=2,"Unstable Orbit","Edge Orbit")))) -> Edge Orbit | AG8: =IF($A8="","",IF(IF(AND(E8>=4,H8>=4),"R1 concentrated force; ","")&IF(AND(OR(C8="Governed Operations Zone",C8="Autonomous Operations Zone"),E8>=3,MIN(L8:N8)<=1),"R2 mandatory control "&INDEX($L$4:$N$4,1,MATCH(MIN(L8:N8),L8:N8,0))&"="&MIN(L8:N8)&"; ","")&IF(AND(OR(C8="Governed Operations Zone",C8="Autonomous Operations Zone"),S8<4),"R3 evidence tier "&S8&"<4; ","")="","-",IF(AND(E8>=4,H8>=4),"R1 concentrated force; ","")&IF(AND(OR(C8="Governed Operations Zone",C8="Autonomous Operations Zone"),E8>=3,MIN(L8:N8)<=1),"R2 mandatory control "&INDEX($L$4:$N$4,1,MATCH(MIN(L8:N8),L8:N8,0))&"="&MIN(L8:N8)&"; ","")&IF(AND(OR(C8="Governed Operations Zone",C8="Autonomous Operations Zone"),S8<4),"R3 evidence tier "&S8&"<4; ",""))) -> R1 concentrated force; | AH8: =IF($A8="","",IF(MIN(IF(X8="Critical Orbit",1,IF(X8="Unstable Orbit",2,IF(X8="Edge Orbit",3,IF(X8="Controlled Orbit",4,5)))),IF(AF8="None",9,IF(AF8="Critical Orbit",1,IF(AF8="Unstable Orbit",2,IF(AF8="Edge Orbit",3,IF(AF8="Controlled Orbit",4,5))))))=1,"Critical Orbit",IF(MIN(IF(X8="Critical Orbit",1,IF(X8="Unstable Orbit",2,IF(X8="Edge Orbit",3,IF(X8="Controlled Orbit",4,5)))),IF(AF8="None",9,IF(AF8="Critical Orbit",1,IF(AF8="Unstable Orbit",2,IF(AF8="Edge Orbit",3,IF(AF8="Controlled Orbit",4,5))))))=2,"Unstable Orbit",IF(MIN(IF(X8="Critical Orbit",1,IF(X8="Unstable Orbit",2,IF(X8="Edge Orbit",3,IF(X8="Controlled Orbit",4,5)))),IF(AF8="None",9,IF(AF8="Critical Orbit",1,IF(AF8="Unstable Orbit",2,IF(AF8="Edge Orbit",3,IF(AF8="Controlled Orbit",4,5))))))=3,"Edge Orbit",IF(MIN(IF(X8="Critical Orbit",1,IF(X8="Unstable Orbit",2,IF(X8="Edge Orbit",3,IF(X8="Controlled Orbit",4,5)))),IF(AF8="None",9,IF(AF8="Critical Orbit",1,IF(AF8="Unstable Orbit",2,IF(AF8="Edge Orbit",3,IF(AF8="Controlled Orbit",4,5))))))=4,"Controlled Orbit","Stable Orbit"))))) -> Edge Orbit | AJ8: 2026-08-31
A9: Autonomous Production Remediation Agent | B9: Cloud / Infrastructure | C9: Autonomous Operations Zone | D9: Basic | E9: 5 | F9: 4 | G9: 5 | H9: 5 | I9: 4 | J9: 3 | K9: 5 | L9: 4 | M9: 4 | N9: 4 | O9: 3 | P9: 3 | Q9: 4 | R9: 2 | S9: 3 | T9: =IF($A9="","",IF(AND(MAX(L9:R9)>3,S9<3),"Warning: EGI >3 needs Tier 3+ evidence",IF(AND(C9="Autonomous Operations Zone",S9<4),"Warning: Autonomous zone needs Tier 4 evidence","OK"))) -> Warning: Autonomous zone needs Tier 4 evidence | U9: =IF($A9="","",IF($D9="Basic",SUM(E9:K9)/35*100,SUMPRODUCT(E9:K9,INDEX('Weighted Scoring'!$B$5:$H$13,MATCH($B9,'Weighted Scoring'!$A$5:$A$13,0),0))/SUMPRODUCT(5,INDEX('Weighted Scoring'!$B$5:$H$13,MATCH($B9,'Weighted Scoring'!$A$5:$A$13,0),0))*100)) -> 88.571429 | V9: =IF($A9="","",IF($D9="Basic",SUM(L9:R9)/35*100,SUMPRODUCT(L9:R9,INDEX('Weighted Scoring'!$I$5:$O$13,MATCH($B9,'Weighted Scoring'!$A$5:$A$13,0),0))/SUMPRODUCT(5,INDEX('Weighted Scoring'!$I$5:$O$13,MATCH($B9,'Weighted Scoring'!$A$5:$A$13,0),0))*100)) -> 68.571429 | W9: =IF($A9="","",V9-U9) -> -20 | X9: =IF($A9="","",IF(W9>=40,"Stable Orbit",IF(W9>=15,"Controlled Orbit",IF(W9>=-14,"Edge Orbit",IF(W9>=-39,"Unstable Orbit","Critical Orbit"))))) -> Unstable Orbit | Y9: =IF($A9="","",INDEX('Deployment Gates'!$C$5:$C$9,MATCH(AH9,'Deployment Gates'!$A$5:$A$9,0))) -> Do not expand; control uplift required | Z9: No | AA9: =IF($A9="","",IF(OR(AH9="Edge Orbit",AH9="Unstable Orbit",AH9="Critical Orbit",H9>=4,G9>=4,E9>=4,J9>=4),"Yes","No")) -> Yes | AB9: =IF($A9="","",IF(W9<0,"Yes","No")) -> Yes | AC9: =IF($A9="","",INDEX($L$4:$R$4,1,MATCH(MIN(L9:R9),L9:R9,0))&IF(COUNTIF(L9:R9,MIN(L9:R9))>1," (+"&(COUNTIF(L9:R9,MIN(L9:R9))-1)&" tied)","")) -> Assurance and Evaluation | AD9: =IF($A9="","",INDEX($E$4:$K$4,1,MATCH(MAX(E9:K9),E9:K9,0))&IF(COUNTIF(E9:K9,MAX(E9:K9))>1," (+"&(COUNTIF(E9:K9,MAX(E9:K9))-1)&" tied)","")) -> Decision Autonomy (+3 tied) | AE9: =IF($A9="","",INDEX('Control Uplift Planner'!$B$5:$B$11,MATCH(INDEX($L$4:$R$4,1,MATCH(MIN(L9:R9),L9:R9,0)),'Control Uplift Planner'!$A$5:$A$11,0))) -> Add scenario tests, red-team tests, runtime evaluation, drift monitoring, and outcome validation. | AF9: =IF($A9="","",IF(MIN(IF(AND(E9>=4,H9>=4),3,9),IF(AND(OR(C9="Governed Operations Zone",C9="Autonomous Operations Zone"),E9>=3),IF(MIN(L9:N9)=0,2,IF(MIN(L9:N9)=1,3,9)),9),IF(AND(OR(C9="Governed Operations Zone",C9="Autonomous Operations Zone"),S9<4),3,9))=9,"None",IF(MIN(IF(AND(E9>=4,H9>=4),3,9),IF(AND(OR(C9="Governed Operations Zone",C9="Autonomous Operations Zone"),E9>=3),IF(MIN(L9:N9)=0,2,IF(MIN(L9:N9)=1,3,9)),9),IF(AND(OR(C9="Governed Operations Zone",C9="Autonomous Operations Zone"),S9<4),3,9))=1,"Critical Orbit",IF(MIN(IF(AND(E9>=4,H9>=4),3,9),IF(AND(OR(C9="Governed Operations Zone",C9="Autonomous Operations Zone"),E9>=3),IF(MIN(L9:N9)=0,2,IF(MIN(L9:N9)=1,3,9)),9),IF(AND(OR(C9="Governed Operations Zone",C9="Autonomous Operations Zone"),S9<4),3,9))=2,"Unstable Orbit","Edge Orbit")))) -> Edge Orbit | AG9: =IF($A9="","",IF(IF(AND(E9>=4,H9>=4),"R1 concentrated force; ","")&IF(AND(OR(C9="Governed Operations Zone",C9="Autonomous Operations Zone"),E9>=3,MIN(L9:N9)<=1),"R2 mandatory control "&INDEX($L$4:$N$4,1,MATCH(MIN(L9:N9),L9:N9,0))&"="&MIN(L9:N9)&"; ","")&IF(AND(OR(C9="Governed Operations Zone",C9="Autonomous Operations Zone"),S9<4),"R3 evidence tier "&S9&"<4; ","")="","-",IF(AND(E9>=4,H9>=4),"R1 concentrated force; ","")&IF(AND(OR(C9="Governed Operations Zone",C9="Autonomous Operations Zone"),E9>=3,MIN(L9:N9)<=1),"R2 mandatory control "&INDEX($L$4:$N$4,1,MATCH(MIN(L9:N9),L9:N9,0))&"="&MIN(L9:N9)&"; ","")&IF(AND(OR(C9="Governed Operations Zone",C9="Autonomous Operations Zone"),S9<4),"R3 evidence tier "&S9&"<4; ",""))) -> R1 concentrated force; R3 evidence tier 3<4; | AH9: =IF($A9="","",IF(MIN(IF(X9="Critical Orbit",1,IF(X9="Unstable Orbit",2,IF(X9="Edge Orbit",3,IF(X9="Controlled Orbit",4,5)))),IF(AF9="None",9,IF(AF9="Critical Orbit",1,IF(AF9="Unstable Orbit",2,IF(AF9="Edge Orbit",3,IF(AF9="Controlled Orbit",4,5))))))=1,"Critical Orbit",IF(MIN(IF(X9="Critical Orbit",1,IF(X9="Unstable Orbit",2,IF(X9="Edge Orbit",3,IF(X9="Controlled Orbit",4,5)))),IF(AF9="None",9,IF(AF9="Critical Orbit",1,IF(AF9="Unstable Orbit",2,IF(AF9="Edge Orbit",3,IF(AF9="Controlled Orbit",4,5))))))=2,"Unstable Orbit",IF(MIN(IF(X9="Critical Orbit",1,IF(X9="Unstable Orbit",2,IF(X9="Edge Orbit",3,IF(X9="Controlled Orbit",4,5)))),IF(AF9="None",9,IF(AF9="Critical Orbit",1,IF(AF9="Unstable Orbit",2,IF(AF9="Edge Orbit",3,IF(AF9="Controlled Orbit",4,5))))))=3,"Edge Orbit",IF(MIN(IF(X9="Critical Orbit",1,IF(X9="Unstable Orbit",2,IF(X9="Edge Orbit",3,IF(X9="Controlled Orbit",4,5)))),IF(AF9="None",9,IF(AF9="Critical Orbit",1,IF(AF9="Unstable Orbit",2,IF(AF9="Edge Orbit",3,IF(AF9="Controlled Orbit",4,5))))))=4,"Controlled Orbit","Stable Orbit"))))) -> Unstable Orbit | AJ9: 2026-07-31
T10: =IF($A10="","",IF(AND(MAX(L10:R10)>3,S10<3),"Warning: EGI >3 needs Tier 3+ evidence",IF(AND(C10="Autonomous Operations Zone",S10<4),"Warning: Autonomous zone needs Tier 4 evidence","OK"))) | U10: =IF($A10="","",IF($D10="Basic",SUM(E10:K10)/35*100,SUMPRODUCT(E10:K10,INDEX('Weighted Scoring'!$B$5:$H$13,MATCH($B10,'Weighted Scoring'!$A$5:$A$13,0),0))/SUMPRODUCT(5,INDEX('Weighted Scoring'!$B$5:$H$13,MATCH($B10,'Weighted Scoring'!$A$5:$A$13,0),0))*100)) | V10: =IF($A10="","",IF($D10="Basic",SUM(L10:R10)/35*100,SUMPRODUCT(L10:R10,INDEX('Weighted Scoring'!$I$5:$O$13,MATCH($B10,'Weighted Scoring'!$A$5:$A$13,0),0))/SUMPRODUCT(5,INDEX('Weighted Scoring'!$I$5:$O$13,MATCH($B10,'Weighted Scoring'!$A$5:$A$13,0),0))*100)) | W10: =IF($A10="","",V10-U10) | X10: =IF($A10="","",IF(W10>=40,"Stable Orbit",IF(W10>=15,"Controlled Orbit",IF(W10>=-14,"Edge Orbit",IF(W10>=-39,"Unstable Orbit","Critical Orbit"))))) | Y10: =IF($A10="","",INDEX('Deployment Gates'!$C$5:$C$9,MATCH(AH10,'Deployment Gates'!$A$5:$A$9,0))) | AA10: =IF($A10="","",IF(OR(AH10="Edge Orbit",AH10="Unstable Orbit",AH10="Critical Orbit",H10>=4,G10>=4,E10>=4,J10>=4),"Yes","No")) | AB10: =IF($A10="","",IF(W10<0,"Yes","No")) | AC10: =IF($A10="","",INDEX($L$4:$R$4,1,MATCH(MIN(L10:R10),L10:R10,0))&IF(COUNTIF(L10:R10,MIN(L10:R10))>1," (+"&(COUNTIF(L10:R10,MIN(L10:R10))-1)&" tied)","")) | AD10: =IF($A10="","",INDEX($E$4:$K$4,1,MATCH(MAX(E10:K10),E10:K10,0))&IF(COUNTIF(E10:K10,MAX(E10:K10))>1," (+"&(COUNTIF(E10:K10,MAX(E10:K10))-1)&" tied)","")) | AE10: =IF($A10="","",INDEX('Control Uplift Planner'!$B$5:$B$11,MATCH(INDEX($L$4:$R$4,1,MATCH(MIN(L10:R10),L10:R10,0)),'Control Uplift Planner'!$A$5:$A$11,0))) | AF10: =IF($A10="","",IF(MIN(IF(AND(E10>=4,H10>=4),3,9),IF(AND(OR(C10="Governed Operations Zone",C10="Autonomous Operations Zone"),E10>=3),IF(MIN(L10:N10)=0,2,IF(MIN(L10:N10)=1,3,9)),9),IF(AND(OR(C10="Governed Operations Zone",C10="Autonomous Operations Zone"),S10<4),3,9))=9,"None",IF(MIN(IF(AND(E10>=4,H10>=4),3,9),IF(AND(OR(C10="Governed Operations Zone",C10="Autonomous Operations Zone"),E10>=3),IF(MIN(L10:N10)=0,2,IF(MIN(L10:N10)=1,3,9)),9),IF(AND(OR(C10="Governed Operations Zone",C10="Autonomous Operations Zone"),S10<4),3,9))=1,"Critical Orbit",IF(MIN(IF(AND(E10>=4,H10>=4),3,9),IF(AND(OR(C10="Governed Operations Zone",C10="Autonomous Operations Zone"),E10>=3),IF(MIN(L10:N10)=0,2,IF(MIN(L10:N10)=1,3,9)),9),IF(AND(OR(C10="Governed Operations Zone",C10="Autonomous Operations Zone"),S10<4),3,9))=2,"Unstable Orbit","Edge Orbit")))) | AG10: =IF($A10="","",IF(IF(AND(E10>=4,H10>=4),"R1 concentrated force; ","")&IF(AND(OR(C10="Governed Operations Zone",C10="Autonomous Operations Zone"),E10>=3,MIN(L10:N10)<=1),"R2 mandatory control "&INDEX($L$4:$N$4,1,MATCH(MIN(L10:N10),L10:N10,0))&"="&MIN(L10:N10)&"; ","")&IF(AND(OR(C10="Governed Operations Zone",C10="Autonomous Operations Zone"),S10<4),"R3 evidence tier "&S10&"<4; ","")="","-",IF(AND(E10>=4,H10>=4),"R1 concentrated force; ","")&IF(AND(OR(C10="Governed Operations Zone",C10="Autonomous Operations Zone"),E10>=3,MIN(L10:N10)<=1),"R2 mandatory control "&INDEX($L$4:$N$4,1,MATCH(MIN(L10:N10),L10:N10,0))&"="&MIN(L10:N10)&"; ","")&IF(AND(OR(C10="Governed Operations Zone",C10="Autonomous Operations Zone"),S10<4),"R3 evidence tier "&S10&"<4; ",""))) | AH10: =IF($A10="","",IF(MIN(IF(X10="Critical Orbit",1,IF(X10="Unstable Orbit",2,IF(X10="Edge Orbit",3,IF(X10="Controlled Orbit",4,5)))),IF(AF10="None",9,IF(AF10="Critical Orbit",1,IF(AF10="Unstable Orbit",2,IF(AF10="Edge Orbit",3,IF(AF10="Controlled Orbit",4,5))))))=1,"Critical Orbit",IF(MIN(IF(X10="Critical Orbit",1,IF(X10="Unstable Orbit",2,IF(X10="Edge Orbit",3,IF(X10="Controlled Orbit",4,5)))),IF(AF10="None",9,IF(AF10="Critical Orbit",1,IF(AF10="Unstable Orbit",2,IF(AF10="Edge Orbit",3,IF(AF10="Controlled Orbit",4,5))))))=2,"Unstable Orbit",IF(MIN(IF(X10="Critical Orbit",1,IF(X10="Unstable Orbit",2,IF(X10="Edge Orbit",3,IF(X10="Controlled Orbit",4,5)))),IF(AF10="None",9,IF(AF10="Critical Orbit",1,IF(AF10="Unstable Orbit",2,IF(AF10="Edge Orbit",3,IF(AF10="Controlled Orbit",4,5))))))=3,"Edge Orbit",IF(MIN(IF(X10="Critical Orbit",1,IF(X10="Unstable Orbit",2,IF(X10="Edge Orbit",3,IF(X10="Controlled Orbit",4,5)))),IF(AF10="None",9,IF(AF10="Critical Orbit",1,IF(AF10="Unstable Orbit",2,IF(AF10="Edge Orbit",3,IF(AF10="Controlled Orbit",4,5))))))=4,"Controlled Orbit","Stable Orbit")))))
T11: =IF($A11="","",IF(AND(MAX(L11:R11)>3,S11<3),"Warning: EGI >3 needs Tier 3+ evidence",IF(AND(C11="Autonomous Operations Zone",S11<4),"Warning: Autonomous zone needs Tier 4 evidence","OK"))) | U11: =IF($A11="","",IF($D11="Basic",SUM(E11:K11)/35*100,SUMPRODUCT(E11:K11,INDEX('Weighted Scoring'!$B$5:$H$13,MATCH($B11,'Weighted Scoring'!$A$5:$A$13,0),0))/SUMPRODUCT(5,INDEX('Weighted Scoring'!$B$5:$H$13,MATCH($B11,'Weighted Scoring'!$A$5:$A$13,0),0))*100)) | V11: =IF($A11="","",IF($D11="Basic",SUM(L11:R11)/35*100,SUMPRODUCT(L11:R11,INDEX('Weighted Scoring'!$I$5:$O$13,MATCH($B11,'Weighted Scoring'!$A$5:$A$13,0),0))/SUMPRODUCT(5,INDEX('Weighted Scoring'!$I$5:$O$13,MATCH($B11,'Weighted Scoring'!$A$5:$A$13,0),0))*100)) | W11: =IF($A11="","",V11-U11) | X11: =IF($A11="","",IF(W11>=40,"Stable Orbit",IF(W11>=15,"Controlled Orbit",IF(W11>=-14,"Edge Orbit",IF(W11>=-39,"Unstable Orbit","Critical Orbit"))))) | Y11: =IF($A11="","",INDEX('Deployment Gates'!$C$5:$C$9,MATCH(AH11,'Deployment Gates'!$A$5:$A$9,0))) | AA11: =IF($A11="","",IF(OR(AH11="Edge Orbit",AH11="Unstable Orbit",AH11="Critical Orbit",H11>=4,G11>=4,E11>=4,J11>=4),"Yes","No")) | AB11: =IF($A11="","",IF(W11<0,"Yes","No")) | AC11: =IF($A11="","",INDEX($L$4:$R$4,1,MATCH(MIN(L11:R11),L11:R11,0))&IF(COUNTIF(L11:R11,MIN(L11:R11))>1," (+"&(COUNTIF(L11:R11,MIN(L11:R11))-1)&" tied)","")) | AD11: =IF($A11="","",INDEX($E$4:$K$4,1,MATCH(MAX(E11:K11),E11:K11,0))&IF(COUNTIF(E11:K11,MAX(E11:K11))>1," (+"&(COUNTIF(E11:K11,MAX(E11:K11))-1)&" tied)","")) | AE11: =IF($A11="","",INDEX('Control Uplift Planner'!$B$5:$B$11,MATCH(INDEX($L$4:$R$4,1,MATCH(MIN(L11:R11),L11:R11,0)),'Control Uplift Planner'!$A$5:$A$11,0))) | AF11: =IF($A11="","",IF(MIN(IF(AND(E11>=4,H11>=4),3,9),IF(AND(OR(C11="Governed Operations Zone",C11="Autonomous Operations Zone"),E11>=3),IF(MIN(L11:N11)=0,2,IF(MIN(L11:N11)=1,3,9)),9),IF(AND(OR(C11="Governed Operations Zone",C11="Autonomous Operations Zone"),S11<4),3,9))=9,"None",IF(MIN(IF(AND(E11>=4,H11>=4),3,9),IF(AND(OR(C11="Governed Operations Zone",C11="Autonomous Operations Zone"),E11>=3),IF(MIN(L11:N11)=0,2,IF(MIN(L11:N11)=1,3,9)),9),IF(AND(OR(C11="Governed Operations Zone",C11="Autonomous Operations Zone"),S11<4),3,9))=1,"Critical Orbit",IF(MIN(IF(AND(E11>=4,H11>=4),3,9),IF(AND(OR(C11="Governed Operations Zone",C11="Autonomous Operations Zone"),E11>=3),IF(MIN(L11:N11)=0,2,IF(MIN(L11:N11)=1,3,9)),9),IF(AND(OR(C11="Governed Operations Zone",C11="Autonomous Operations Zone"),S11<4),3,9))=2,"Unstable Orbit","Edge Orbit")))) | AG11: =IF($A11="","",IF(IF(AND(E11>=4,H11>=4),"R1 concentrated force; ","")&IF(AND(OR(C11="Governed Operations Zone",C11="Autonomous Operations Zone"),E11>=3,MIN(L11:N11)<=1),"R2 mandatory control "&INDEX($L$4:$N$4,1,MATCH(MIN(L11:N11),L11:N11,0))&"="&MIN(L11:N11)&"; ","")&IF(AND(OR(C11="Governed Operations Zone",C11="Autonomous Operations Zone"),S11<4),"R3 evidence tier "&S11&"<4; ","")="","-",IF(AND(E11>=4,H11>=4),"R1 concentrated force; ","")&IF(AND(OR(C11="Governed Operations Zone",C11="Autonomous Operations Zone"),E11>=3,MIN(L11:N11)<=1),"R2 mandatory control "&INDEX($L$4:$N$4,1,MATCH(MIN(L11:N11),L11:N11,0))&"="&MIN(L11:N11)&"; ","")&IF(AND(OR(C11="Governed Operations Zone",C11="Autonomous Operations Zone"),S11<4),"R3 evidence tier "&S11&"<4; ",""))) | AH11: =IF($A11="","",IF(MIN(IF(X11="Critical Orbit",1,IF(X11="Unstable Orbit",2,IF(X11="Edge Orbit",3,IF(X11="Controlled Orbit",4,5)))),IF(AF11="None",9,IF(AF11="Critical Orbit",1,IF(AF11="Unstable Orbit",2,IF(AF11="Edge Orbit",3,IF(AF11="Controlled Orbit",4,5))))))=1,"Critical Orbit",IF(MIN(IF(X11="Critical Orbit",1,IF(X11="Unstable Orbit",2,IF(X11="Edge Orbit",3,IF(X11="Controlled Orbit",4,5)))),IF(AF11="None",9,IF(AF11="Critical Orbit",1,IF(AF11="Unstable Orbit",2,IF(AF11="Edge Orbit",3,IF(AF11="Controlled Orbit",4,5))))))=2,"Unstable Orbit",IF(MIN(IF(X11="Critical Orbit",1,IF(X11="Unstable Orbit",2,IF(X11="Edge Orbit",3,IF(X11="Controlled Orbit",4,5)))),IF(AF11="None",9,IF(AF11="Critical Orbit",1,IF(AF11="Unstable Orbit",2,IF(AF11="Edge Orbit",3,IF(AF11="Controlled Orbit",4,5))))))=3,"Edge Orbit",IF(MIN(IF(X11="Critical Orbit",1,IF(X11="Unstable Orbit",2,IF(X11="Edge Orbit",3,IF(X11="Controlled Orbit",4,5)))),IF(AF11="None",9,IF(AF11="Critical Orbit",1,IF(AF11="Unstable Orbit",2,IF(AF11="Edge Orbit",3,IF(AF11="Controlled Orbit",4,5))))))=4,"Controlled Orbit","Stable Orbit")))))
T12: =IF($A12="","",IF(AND(MAX(L12:R12)>3,S12<3),"Warning: EGI >3 needs Tier 3+ evidence",IF(AND(C12="Autonomous Operations Zone",S12<4),"Warning: Autonomous zone needs Tier 4 evidence","OK"))) | U12: =IF($A12="","",IF($D12="Basic",SUM(E12:K12)/35*100,SUMPRODUCT(E12:K12,INDEX('Weighted Scoring'!$B$5:$H$13,MATCH($B12,'Weighted Scoring'!$A$5:$A$13,0),0))/SUMPRODUCT(5,INDEX('Weighted Scoring'!$B$5:$H$13,MATCH($B12,'Weighted Scoring'!$A$5:$A$13,0),0))*100)) | V12: =IF($A12="","",IF($D12="Basic",SUM(L12:R12)/35*100,SUMPRODUCT(L12:R12,INDEX('Weighted Scoring'!$I$5:$O$13,MATCH($B12,'Weighted Scoring'!$A$5:$A$13,0),0))/SUMPRODUCT(5,INDEX('Weighted Scoring'!$I$5:$O$13,MATCH($B12,'Weighted Scoring'!$A$5:$A$13,0),0))*100)) | W12: =IF($A12="","",V12-U12) | X12: =IF($A12="","",IF(W12>=40,"Stable Orbit",IF(W12>=15,"Controlled Orbit",IF(W12>=-14,"Edge Orbit",IF(W12>=-39,"Unstable Orbit","Critical Orbit"))))) | Y12: =IF($A12="","",INDEX('Deployment Gates'!$C$5:$C$9,MATCH(AH12,'Deployment Gates'!$A$5:$A$9,0))) | AA12: =IF($A12="","",IF(OR(AH12="Edge Orbit",AH12="Unstable Orbit",AH12="Critical Orbit",H12>=4,G12>=4,E12>=4,J12>=4),"Yes","No")) | AB12: =IF($A12="","",IF(W12<0,"Yes","No")) | AC12: =IF($A12="","",INDEX($L$4:$R$4,1,MATCH(MIN(L12:R12),L12:R12,0))&IF(COUNTIF(L12:R12,MIN(L12:R12))>1," (+"&(COUNTIF(L12:R12,MIN(L12:R12))-1)&" tied)","")) | AD12: =IF($A12="","",INDEX($E$4:$K$4,1,MATCH(MAX(E12:K12),E12:K12,0))&IF(COUNTIF(E12:K12,MAX(E12:K12))>1," (+"&(COUNTIF(E12:K12,MAX(E12:K12))-1)&" tied)","")) | AE12: =IF($A12="","",INDEX('Control Uplift Planner'!$B$5:$B$11,MATCH(INDEX($L$4:$R$4,1,MATCH(MIN(L12:R12),L12:R12,0)),'Control Uplift Planner'!$A$5:$A$11,0))) | AF12: =IF($A12="","",IF(MIN(IF(AND(E12>=4,H12>=4),3,9),IF(AND(OR(C12="Governed Operations Zone",C12="Autonomous Operations Zone"),E12>=3),IF(MIN(L12:N12)=0,2,IF(MIN(L12:N12)=1,3,9)),9),IF(AND(OR(C12="Governed Operations Zone",C12="Autonomous Operations Zone"),S12<4),3,9))=9,"None",IF(MIN(IF(AND(E12>=4,H12>=4),3,9),IF(AND(OR(C12="Governed Operations Zone",C12="Autonomous Operations Zone"),E12>=3),IF(MIN(L12:N12)=0,2,IF(MIN(L12:N12)=1,3,9)),9),IF(AND(OR(C12="Governed Operations Zone",C12="Autonomous Operations Zone"),S12<4),3,9))=1,"Critical Orbit",IF(MIN(IF(AND(E12>=4,H12>=4),3,9),IF(AND(OR(C12="Governed Operations Zone",C12="Autonomous Operations Zone"),E12>=3),IF(MIN(L12:N12)=0,2,IF(MIN(L12:N12)=1,3,9)),9),IF(AND(OR(C12="Governed Operations Zone",C12="Autonomous Operations Zone"),S12<4),3,9))=2,"Unstable Orbit","Edge Orbit")))) | AG12: =IF($A12="","",IF(IF(AND(E12>=4,H12>=4),"R1 concentrated force; ","")&IF(AND(OR(C12="Governed Operations Zone",C12="Autonomous Operations Zone"),E12>=3,MIN(L12:N12)<=1),"R2 mandatory control "&INDEX($L$4:$N$4,1,MATCH(MIN(L12:N12),L12:N12,0))&"="&MIN(L12:N12)&"; ","")&IF(AND(OR(C12="Governed Operations Zone",C12="Autonomous Operations Zone"),S12<4),"R3 evidence tier "&S12&"<4; ","")="","-",IF(AND(E12>=4,H12>=4),"R1 concentrated force; ","")&IF(AND(OR(C12="Governed Operations Zone",C12="Autonomous Operations Zone"),E12>=3,MIN(L12:N12)<=1),"R2 mandatory control "&INDEX($L$4:$N$4,1,MATCH(MIN(L12:N12),L12:N12,0))&"="&MIN(L12:N12)&"; ","")&IF(AND(OR(C12="Governed Operations Zone",C12="Autonomous Operations Zone"),S12<4),"R3 evidence tier "&S12&"<4; ",""))) | AH12: =IF($A12="","",IF(MIN(IF(X12="Critical Orbit",1,IF(X12="Unstable Orbit",2,IF(X12="Edge Orbit",3,IF(X12="Controlled Orbit",4,5)))),IF(AF12="None",9,IF(AF12="Critical Orbit",1,IF(AF12="Unstable Orbit",2,IF(AF12="Edge Orbit",3,IF(AF12="Controlled Orbit",4,5))))))=1,"Critical Orbit",IF(MIN(IF(X12="Critical Orbit",1,IF(X12="Unstable Orbit",2,IF(X12="Edge Orbit",3,IF(X12="Controlled Orbit",4,5)))),IF(AF12="None",9,IF(AF12="Critical Orbit",1,IF(AF12="Unstable Orbit",2,IF(AF12="Edge Orbit",3,IF(AF12="Controlled Orbit",4,5))))))=2,"Unstable Orbit",IF(MIN(IF(X12="Critical Orbit",1,IF(X12="Unstable Orbit",2,IF(X12="Edge Orbit",3,IF(X12="Controlled Orbit",4,5)))),IF(AF12="None",9,IF(AF12="Critical Orbit",1,IF(AF12="Unstable Orbit",2,IF(AF12="Edge Orbit",3,IF(AF12="Controlled Orbit",4,5))))))=3,"Edge Orbit",IF(MIN(IF(X12="Critical Orbit",1,IF(X12="Unstable Orbit",2,IF(X12="Edge Orbit",3,IF(X12="Controlled Orbit",4,5)))),IF(AF12="None",9,IF(AF12="Critical Orbit",1,IF(AF12="Unstable Orbit",2,IF(AF12="Edge Orbit",3,IF(AF12="Controlled Orbit",4,5))))))=4,"Controlled Orbit","Stable Orbit")))))
T13: =IF($A13="","",IF(AND(MAX(L13:R13)>3,S13<3),"Warning: EGI >3 needs Tier 3+ evidence",IF(AND(C13="Autonomous Operations Zone",S13<4),"Warning: Autonomous zone needs Tier 4 evidence","OK"))) | U13: =IF($A13="","",IF($D13="Basic",SUM(E13:K13)/35*100,SUMPRODUCT(E13:K13,INDEX('Weighted Scoring'!$B$5:$H$13,MATCH($B13,'Weighted Scoring'!$A$5:$A$13,0),0))/SUMPRODUCT(5,INDEX('Weighted Scoring'!$B$5:$H$13,MATCH($B13,'Weighted Scoring'!$A$5:$A$13,0),0))*100)) | V13: =IF($A13="","",IF($D13="Basic",SUM(L13:R13)/35*100,SUMPRODUCT(L13:R13,INDEX('Weighted Scoring'!$I$5:$O$13,MATCH($B13,'Weighted Scoring'!$A$5:$A$13,0),0))/SUMPRODUCT(5,INDEX('Weighted Scoring'!$I$5:$O$13,MATCH($B13,'Weighted Scoring'!$A$5:$A$13,0),0))*100)) | W13: =IF($A13="","",V13-U13) | X13: =IF($A13="","",IF(W13>=40,"Stable Orbit",IF(W13>=15,"Controlled Orbit",IF(W13>=-14,"Edge Orbit",IF(W13>=-39,"Unstable Orbit","Critical Orbit"))))) | Y13: =IF($A13="","",INDEX('Deployment Gates'!$C$5:$C$9,MATCH(AH13,'Deployment Gates'!$A$5:$A$9,0))) | AA13: =IF($A13="","",IF(OR(AH13="Edge Orbit",AH13="Unstable Orbit",AH13="Critical Orbit",H13>=4,G13>=4,E13>=4,J13>=4),"Yes","No")) | AB13: =IF($A13="","",IF(W13<0,"Yes","No")) | AC13: =IF($A13="","",INDEX($L$4:$R$4,1,MATCH(MIN(L13:R13),L13:R13,0))&IF(COUNTIF(L13:R13,MIN(L13:R13))>1," (+"&(COUNTIF(L13:R13,MIN(L13:R13))-1)&" tied)","")) | AD13: =IF($A13="","",INDEX($E$4:$K$4,1,MATCH(MAX(E13:K13),E13:K13,0))&IF(COUNTIF(E13:K13,MAX(E13:K13))>1," (+"&(COUNTIF(E13:K13,MAX(E13:K13))-1)&" tied)","")) | AE13: =IF($A13="","",INDEX('Control Uplift Planner'!$B$5:$B$11,MATCH(INDEX($L$4:$R$4,1,MATCH(MIN(L13:R13),L13:R13,0)),'Control Uplift Planner'!$A$5:$A$11,0))) | AF13: =IF($A13="","",IF(MIN(IF(AND(E13>=4,H13>=4),3,9),IF(AND(OR(C13="Governed Operations Zone",C13="Autonomous Operations Zone"),E13>=3),IF(MIN(L13:N13)=0,2,IF(MIN(L13:N13)=1,3,9)),9),IF(AND(OR(C13="Governed Operations Zone",C13="Autonomous Operations Zone"),S13<4),3,9))=9,"None",IF(MIN(IF(AND(E13>=4,H13>=4),3,9),IF(AND(OR(C13="Governed Operations Zone",C13="Autonomous Operations Zone"),E13>=3),IF(MIN(L13:N13)=0,2,IF(MIN(L13:N13)=1,3,9)),9),IF(AND(OR(C13="Governed Operations Zone",C13="Autonomous Operations Zone"),S13<4),3,9))=1,"Critical Orbit",IF(MIN(IF(AND(E13>=4,H13>=4),3,9),IF(AND(OR(C13="Governed Operations Zone",C13="Autonomous Operations Zone"),E13>=3),IF(MIN(L13:N13)=0,2,IF(MIN(L13:N13)=1,3,9)),9),IF(AND(OR(C13="Governed Operations Zone",C13="Autonomous Operations Zone"),S13<4),3,9))=2,"Unstable Orbit","Edge Orbit")))) | AG13: =IF($A13="","",IF(IF(AND(E13>=4,H13>=4),"R1 concentrated force; ","")&IF(AND(OR(C13="Governed Operations Zone",C13="Autonomous Operations Zone"),E13>=3,MIN(L13:N13)<=1),"R2 mandatory control "&INDEX($L$4:$N$4,1,MATCH(MIN(L13:N13),L13:N13,0))&"="&MIN(L13:N13)&"; ","")&IF(AND(OR(C13="Governed Operations Zone",C13="Autonomous Operations Zone"),S13<4),"R3 evidence tier "&S13&"<4; ","")="","-",IF(AND(E13>=4,H13>=4),"R1 concentrated force; ","")&IF(AND(OR(C13="Governed Operations Zone",C13="Autonomous Operations Zone"),E13>=3,MIN(L13:N13)<=1),"R2 mandatory control "&INDEX($L$4:$N$4,1,MATCH(MIN(L13:N13),L13:N13,0))&"="&MIN(L13:N13)&"; ","")&IF(AND(OR(C13="Governed Operations Zone",C13="Autonomous Operations Zone"),S13<4),"R3 evidence tier "&S13&"<4; ",""))) | AH13: =IF($A13="","",IF(MIN(IF(X13="Critical Orbit",1,IF(X13="Unstable Orbit",2,IF(X13="Edge Orbit",3,IF(X13="Controlled Orbit",4,5)))),IF(AF13="None",9,IF(AF13="Critical Orbit",1,IF(AF13="Unstable Orbit",2,IF(AF13="Edge Orbit",3,IF(AF13="Controlled Orbit",4,5))))))=1,"Critical Orbit",IF(MIN(IF(X13="Critical Orbit",1,IF(X13="Unstable Orbit",2,IF(X13="Edge Orbit",3,IF(X13="Controlled Orbit",4,5)))),IF(AF13="None",9,IF(AF13="Critical Orbit",1,IF(AF13="Unstable Orbit",2,IF(AF13="Edge Orbit",3,IF(AF13="Controlled Orbit",4,5))))))=2,"Unstable Orbit",IF(MIN(IF(X13="Critical Orbit",1,IF(X13="Unstable Orbit",2,IF(X13="Edge Orbit",3,IF(X13="Controlled Orbit",4,5)))),IF(AF13="None",9,IF(AF13="Critical Orbit",1,IF(AF13="Unstable Orbit",2,IF(AF13="Edge Orbit",3,IF(AF13="Controlled Orbit",4,5))))))=3,"Edge Orbit",IF(MIN(IF(X13="Critical Orbit",1,IF(X13="Unstable Orbit",2,IF(X13="Edge Orbit",3,IF(X13="Controlled Orbit",4,5)))),IF(AF13="None",9,IF(AF13="Critical Orbit",1,IF(AF13="Unstable Orbit",2,IF(AF13="Edge Orbit",3,IF(AF13="Controlled Orbit",4,5))))))=4,"Controlled Orbit","Stable Orbit")))))
T14: =IF($A14="","",IF(AND(MAX(L14:R14)>3,S14<3),"Warning: EGI >3 needs Tier 3+ evidence",IF(AND(C14="Autonomous Operations Zone",S14<4),"Warning: Autonomous zone needs Tier 4 evidence","OK"))) | U14: =IF($A14="","",IF($D14="Basic",SUM(E14:K14)/35*100,SUMPRODUCT(E14:K14,INDEX('Weighted Scoring'!$B$5:$H$13,MATCH($B14,'Weighted Scoring'!$A$5:$A$13,0),0))/SUMPRODUCT(5,INDEX('Weighted Scoring'!$B$5:$H$13,MATCH($B14,'Weighted Scoring'!$A$5:$A$13,0),0))*100)) | V14: =IF($A14="","",IF($D14="Basic",SUM(L14:R14)/35*100,SUMPRODUCT(L14:R14,INDEX('Weighted Scoring'!$I$5:$O$13,MATCH($B14,'Weighted Scoring'!$A$5:$A$13,0),0))/SUMPRODUCT(5,INDEX('Weighted Scoring'!$I$5:$O$13,MATCH($B14,'Weighted Scoring'!$A$5:$A$13,0),0))*100)) | W14: =IF($A14="","",V14-U14) | X14: =IF($A14="","",IF(W14>=40,"Stable Orbit",IF(W14>=15,"Controlled Orbit",IF(W14>=-14,"Edge Orbit",IF(W14>=-39,"Unstable Orbit","Critical Orbit"))))) | Y14: =IF($A14="","",INDEX('Deployment Gates'!$C$5:$C$9,MATCH(AH14,'Deployment Gates'!$A$5:$A$9,0))) | AA14: =IF($A14="","",IF(OR(AH14="Edge Orbit",AH14="Unstable Orbit",AH14="Critical Orbit",H14>=4,G14>=4,E14>=4,J14>=4),"Yes","No")) | AB14: =IF($A14="","",IF(W14<0,"Yes","No")) | AC14: =IF($A14="","",INDEX($L$4:$R$4,1,MATCH(MIN(L14:R14),L14:R14,0))&IF(COUNTIF(L14:R14,MIN(L14:R14))>1," (+"&(COUNTIF(L14:R14,MIN(L14:R14))-1)&" tied)","")) | AD14: =IF($A14="","",INDEX($E$4:$K$4,1,MATCH(MAX(E14:K14),E14:K14,0))&IF(COUNTIF(E14:K14,MAX(E14:K14))>1," (+"&(COUNTIF(E14:K14,MAX(E14:K14))-1)&" tied)","")) | AE14: =IF($A14="","",INDEX('Control Uplift Planner'!$B$5:$B$11,MATCH(INDEX($L$4:$R$4,1,MATCH(MIN(L14:R14),L14:R14,0)),'Control Uplift Planner'!$A$5:$A$11,0))) | AF14: =IF($A14="","",IF(MIN(IF(AND(E14>=4,H14>=4),3,9),IF(AND(OR(C14="Governed Operations Zone",C14="Autonomous Operations Zone"),E14>=3),IF(MIN(L14:N14)=0,2,IF(MIN(L14:N14)=1,3,9)),9),IF(AND(OR(C14="Governed Operations Zone",C14="Autonomous Operations Zone"),S14<4),3,9))=9,"None",IF(MIN(IF(AND(E14>=4,H14>=4),3,9),IF(AND(OR(C14="Governed Operations Zone",C14="Autonomous Operations Zone"),E14>=3),IF(MIN(L14:N14)=0,2,IF(MIN(L14:N14)=1,3,9)),9),IF(AND(OR(C14="Governed Operations Zone",C14="Autonomous Operations Zone"),S14<4),3,9))=1,"Critical Orbit",IF(MIN(IF(AND(E14>=4,H14>=4),3,9),IF(AND(OR(C14="Governed Operations Zone",C14="Autonomous Operations Zone"),E14>=3),IF(MIN(L14:N14)=0,2,IF(MIN(L14:N14)=1,3,9)),9),IF(AND(OR(C14="Governed Operations Zone",C14="Autonomous Operations Zone"),S14<4),3,9))=2,"Unstable Orbit","Edge Orbit")))) | AG14: =IF($A14="","",IF(IF(AND(E14>=4,H14>=4),"R1 concentrated force; ","")&IF(AND(OR(C14="Governed Operations Zone",C14="Autonomous Operations Zone"),E14>=3,MIN(L14:N14)<=1),"R2 mandatory control "&INDEX($L$4:$N$4,1,MATCH(MIN(L14:N14),L14:N14,0))&"="&MIN(L14:N14)&"; ","")&IF(AND(OR(C14="Governed Operations Zone",C14="Autonomous Operations Zone"),S14<4),"R3 evidence tier "&S14&"<4; ","")="","-",IF(AND(E14>=4,H14>=4),"R1 concentrated force; ","")&IF(AND(OR(C14="Governed Operations Zone",C14="Autonomous Operations Zone"),E14>=3,MIN(L14:N14)<=1),"R2 mandatory control "&INDEX($L$4:$N$4,1,MATCH(MIN(L14:N14),L14:N14,0))&"="&MIN(L14:N14)&"; ","")&IF(AND(OR(C14="Governed Operations Zone",C14="Autonomous Operations Zone"),S14<4),"R3 evidence tier "&S14&"<4; ",""))) | AH14: =IF($A14="","",IF(MIN(IF(X14="Critical Orbit",1,IF(X14="Unstable Orbit",2,IF(X14="Edge Orbit",3,IF(X14="Controlled Orbit",4,5)))),IF(AF14="None",9,IF(AF14="Critical Orbit",1,IF(AF14="Unstable Orbit",2,IF(AF14="Edge Orbit",3,IF(AF14="Controlled Orbit",4,5))))))=1,"Critical Orbit",IF(MIN(IF(X14="Critical Orbit",1,IF(X14="Unstable Orbit",2,IF(X14="Edge Orbit",3,IF(X14="Controlled Orbit",4,5)))),IF(AF14="None",9,IF(AF14="Critical Orbit",1,IF(AF14="Unstable Orbit",2,IF(AF14="Edge Orbit",3,IF(AF14="Controlled Orbit",4,5))))))=2,"Unstable Orbit",IF(MIN(IF(X14="Critical Orbit",1,IF(X14="Unstable Orbit",2,IF(X14="Edge Orbit",3,IF(X14="Controlled Orbit",4,5)))),IF(AF14="None",9,IF(AF14="Critical Orbit",1,IF(AF14="Unstable Orbit",2,IF(AF14="Edge Orbit",3,IF(AF14="Controlled Orbit",4,5))))))=3,"Edge Orbit",IF(MIN(IF(X14="Critical Orbit",1,IF(X14="Unstable Orbit",2,IF(X14="Edge Orbit",3,IF(X14="Controlled Orbit",4,5)))),IF(AF14="None",9,IF(AF14="Critical Orbit",1,IF(AF14="Unstable Orbit",2,IF(AF14="Edge Orbit",3,IF(AF14="Controlled Orbit",4,5))))))=4,"Controlled Orbit","Stable Orbit")))))
T15: =IF($A15="","",IF(AND(MAX(L15:R15)>3,S15<3),"Warning: EGI >3 needs Tier 3+ evidence",IF(AND(C15="Autonomous Operations Zone",S15<4),"Warning: Autonomous zone needs Tier 4 evidence","OK"))) | U15: =IF($A15="","",IF($D15="Basic",SUM(E15:K15)/35*100,SUMPRODUCT(E15:K15,INDEX('Weighted Scoring'!$B$5:$H$13,MATCH($B15,'Weighted Scoring'!$A$5:$A$13,0),0))/SUMPRODUCT(5,INDEX('Weighted Scoring'!$B$5:$H$13,MATCH($B15,'Weighted Scoring'!$A$5:$A$13,0),0))*100)) | V15: =IF($A15="","",IF($D15="Basic",SUM(L15:R15)/35*100,SUMPRODUCT(L15:R15,INDEX('Weighted Scoring'!$I$5:$O$13,MATCH($B15,'Weighted Scoring'!$A$5:$A$13,0),0))/SUMPRODUCT(5,INDEX('Weighted Scoring'!$I$5:$O$13,MATCH($B15,'Weighted Scoring'!$A$5:$A$13,0),0))*100)) | W15: =IF($A15="","",V15-U15) | X15: =IF($A15="","",IF(W15>=40,"Stable Orbit",IF(W15>=15,"Controlled Orbit",IF(W15>=-14,"Edge Orbit",IF(W15>=-39,"Unstable Orbit","Critical Orbit"))))) | Y15: =IF($A15="","",INDEX('Deployment Gates'!$C$5:$C$9,MATCH(AH15,'Deployment Gates'!$A$5:$A$9,0))) | AA15: =IF($A15="","",IF(OR(AH15="Edge Orbit",AH15="Unstable Orbit",AH15="Critical Orbit",H15>=4,G15>=4,E15>=4,J15>=4),"Yes","No")) | AB15: =IF($A15="","",IF(W15<0,"Yes","No")) | AC15: =IF($A15="","",INDEX($L$4:$R$4,1,MATCH(MIN(L15:R15),L15:R15,0))&IF(COUNTIF(L15:R15,MIN(L15:R15))>1," (+"&(COUNTIF(L15:R15,MIN(L15:R15))-1)&" tied)","")) | AD15: =IF($A15="","",INDEX($E$4:$K$4,1,MATCH(MAX(E15:K15),E15:K15,0))&IF(COUNTIF(E15:K15,MAX(E15:K15))>1," (+"&(COUNTIF(E15:K15,MAX(E15:K15))-1)&" tied)","")) | AE15: =IF($A15="","",INDEX('Control Uplift Planner'!$B$5:$B$11,MATCH(INDEX($L$4:$R$4,1,MATCH(MIN(L15:R15),L15:R15,0)),'Control Uplift Planner'!$A$5:$A$11,0))) | AF15: =IF($A15="","",IF(MIN(IF(AND(E15>=4,H15>=4),3,9),IF(AND(OR(C15="Governed Operations Zone",C15="Autonomous Operations Zone"),E15>=3),IF(MIN(L15:N15)=0,2,IF(MIN(L15:N15)=1,3,9)),9),IF(AND(OR(C15="Governed Operations Zone",C15="Autonomous Operations Zone"),S15<4),3,9))=9,"None",IF(MIN(IF(AND(E15>=4,H15>=4),3,9),IF(AND(OR(C15="Governed Operations Zone",C15="Autonomous Operations Zone"),E15>=3),IF(MIN(L15:N15)=0,2,IF(MIN(L15:N15)=1,3,9)),9),IF(AND(OR(C15="Governed Operations Zone",C15="Autonomous Operations Zone"),S15<4),3,9))=1,"Critical Orbit",IF(MIN(IF(AND(E15>=4,H15>=4),3,9),IF(AND(OR(C15="Governed Operations Zone",C15="Autonomous Operations Zone"),E15>=3),IF(MIN(L15:N15)=0,2,IF(MIN(L15:N15)=1,3,9)),9),IF(AND(OR(C15="Governed Operations Zone",C15="Autonomous Operations Zone"),S15<4),3,9))=2,"Unstable Orbit","Edge Orbit")))) | AG15: =IF($A15="","",IF(IF(AND(E15>=4,H15>=4),"R1 concentrated force; ","")&IF(AND(OR(C15="Governed Operations Zone",C15="Autonomous Operations Zone"),E15>=3,MIN(L15:N15)<=1),"R2 mandatory control "&INDEX($L$4:$N$4,1,MATCH(MIN(L15:N15),L15:N15,0))&"="&MIN(L15:N15)&"; ","")&IF(AND(OR(C15="Governed Operations Zone",C15="Autonomous Operations Zone"),S15<4),"R3 evidence tier "&S15&"<4; ","")="","-",IF(AND(E15>=4,H15>=4),"R1 concentrated force; ","")&IF(AND(OR(C15="Governed Operations Zone",C15="Autonomous Operations Zone"),E15>=3,MIN(L15:N15)<=1),"R2 mandatory control "&INDEX($L$4:$N$4,1,MATCH(MIN(L15:N15),L15:N15,0))&"="&MIN(L15:N15)&"; ","")&IF(AND(OR(C15="Governed Operations Zone",C15="Autonomous Operations Zone"),S15<4),"R3 evidence tier "&S15&"<4; ",""))) | AH15: =IF($A15="","",IF(MIN(IF(X15="Critical Orbit",1,IF(X15="Unstable Orbit",2,IF(X15="Edge Orbit",3,IF(X15="Controlled Orbit",4,5)))),IF(AF15="None",9,IF(AF15="Critical Orbit",1,IF(AF15="Unstable Orbit",2,IF(AF15="Edge Orbit",3,IF(AF15="Controlled Orbit",4,5))))))=1,"Critical Orbit",IF(MIN(IF(X15="Critical Orbit",1,IF(X15="Unstable Orbit",2,IF(X15="Edge Orbit",3,IF(X15="Controlled Orbit",4,5)))),IF(AF15="None",9,IF(AF15="Critical Orbit",1,IF(AF15="Unstable Orbit",2,IF(AF15="Edge Orbit",3,IF(AF15="Controlled Orbit",4,5))))))=2,"Unstable Orbit",IF(MIN(IF(X15="Critical Orbit",1,IF(X15="Unstable Orbit",2,IF(X15="Edge Orbit",3,IF(X15="Controlled Orbit",4,5)))),IF(AF15="None",9,IF(AF15="Critical Orbit",1,IF(AF15="Unstable Orbit",2,IF(AF15="Edge Orbit",3,IF(AF15="Controlled Orbit",4,5))))))=3,"Edge Orbit",IF(MIN(IF(X15="Critical Orbit",1,IF(X15="Unstable Orbit",2,IF(X15="Edge Orbit",3,IF(X15="Controlled Orbit",4,5)))),IF(AF15="None",9,IF(AF15="Critical Orbit",1,IF(AF15="Unstable Orbit",2,IF(AF15="Edge Orbit",3,IF(AF15="Controlled Orbit",4,5))))))=4,"Controlled Orbit","Stable Orbit")))))
T16: =IF($A16="","",IF(AND(MAX(L16:R16)>3,S16<3),"Warning: EGI >3 needs Tier 3+ evidence",IF(AND(C16="Autonomous Operations Zone",S16<4),"Warning: Autonomous zone needs Tier 4 evidence","OK"))) | U16: =IF($A16="","",IF($D16="Basic",SUM(E16:K16)/35*100,SUMPRODUCT(E16:K16,INDEX('Weighted Scoring'!$B$5:$H$13,MATCH($B16,'Weighted Scoring'!$A$5:$A$13,0),0))/SUMPRODUCT(5,INDEX('Weighted Scoring'!$B$5:$H$13,MATCH($B16,'Weighted Scoring'!$A$5:$A$13,0),0))*100)) | V16: =IF($A16="","",IF($D16="Basic",SUM(L16:R16)/35*100,SUMPRODUCT(L16:R16,INDEX('Weighted Scoring'!$I$5:$O$13,MATCH($B16,'Weighted Scoring'!$A$5:$A$13,0),0))/SUMPRODUCT(5,INDEX('Weighted Scoring'!$I$5:$O$13,MATCH($B16,'Weighted Scoring'!$A$5:$A$13,0),0))*100)) | W16: =IF($A16="","",V16-U16) | X16: =IF($A16="","",IF(W16>=40,"Stable Orbit",IF(W16>=15,"Controlled Orbit",IF(W16>=-14,"Edge Orbit",IF(W16>=-39,"Unstable Orbit","Critical Orbit"))))) | Y16: =IF($A16="","",INDEX('Deployment Gates'!$C$5:$C$9,MATCH(AH16,'Deployment Gates'!$A$5:$A$9,0))) | AA16: =IF($A16="","",IF(OR(AH16="Edge Orbit",AH16="Unstable Orbit",AH16="Critical Orbit",H16>=4,G16>=4,E16>=4,J16>=4),"Yes","No")) | AB16: =IF($A16="","",IF(W16<0,"Yes","No")) | AC16: =IF($A16="","",INDEX($L$4:$R$4,1,MATCH(MIN(L16:R16),L16:R16,0))&IF(COUNTIF(L16:R16,MIN(L16:R16))>1," (+"&(COUNTIF(L16:R16,MIN(L16:R16))-1)&" tied)","")) | AD16: =IF($A16="","",INDEX($E$4:$K$4,1,MATCH(MAX(E16:K16),E16:K16,0))&IF(COUNTIF(E16:K16,MAX(E16:K16))>1," (+"&(COUNTIF(E16:K16,MAX(E16:K16))-1)&" tied)","")) | AE16: =IF($A16="","",INDEX('Control Uplift Planner'!$B$5:$B$11,MATCH(INDEX($L$4:$R$4,1,MATCH(MIN(L16:R16),L16:R16,0)),'Control Uplift Planner'!$A$5:$A$11,0))) | AF16: =IF($A16="","",IF(MIN(IF(AND(E16>=4,H16>=4),3,9),IF(AND(OR(C16="Governed Operations Zone",C16="Autonomous Operations Zone"),E16>=3),IF(MIN(L16:N16)=0,2,IF(MIN(L16:N16)=1,3,9)),9),IF(AND(OR(C16="Governed Operations Zone",C16="Autonomous Operations Zone"),S16<4),3,9))=9,"None",IF(MIN(IF(AND(E16>=4,H16>=4),3,9),IF(AND(OR(C16="Governed Operations Zone",C16="Autonomous Operations Zone"),E16>=3),IF(MIN(L16:N16)=0,2,IF(MIN(L16:N16)=1,3,9)),9),IF(AND(OR(C16="Governed Operations Zone",C16="Autonomous Operations Zone"),S16<4),3,9))=1,"Critical Orbit",IF(MIN(IF(AND(E16>=4,H16>=4),3,9),IF(AND(OR(C16="Governed Operations Zone",C16="Autonomous Operations Zone"),E16>=3),IF(MIN(L16:N16)=0,2,IF(MIN(L16:N16)=1,3,9)),9),IF(AND(OR(C16="Governed Operations Zone",C16="Autonomous Operations Zone"),S16<4),3,9))=2,"Unstable Orbit","Edge Orbit")))) | AG16: =IF($A16="","",IF(IF(AND(E16>=4,H16>=4),"R1 concentrated force; ","")&IF(AND(OR(C16="Governed Operations Zone",C16="Autonomous Operations Zone"),E16>=3,MIN(L16:N16)<=1),"R2 mandatory control "&INDEX($L$4:$N$4,1,MATCH(MIN(L16:N16),L16:N16,0))&"="&MIN(L16:N16)&"; ","")&IF(AND(OR(C16="Governed Operations Zone",C16="Autonomous Operations Zone"),S16<4),"R3 evidence tier "&S16&"<4; ","")="","-",IF(AND(E16>=4,H16>=4),"R1 concentrated force; ","")&IF(AND(OR(C16="Governed Operations Zone",C16="Autonomous Operations Zone"),E16>=3,MIN(L16:N16)<=1),"R2 mandatory control "&INDEX($L$4:$N$4,1,MATCH(MIN(L16:N16),L16:N16,0))&"="&MIN(L16:N16)&"; ","")&IF(AND(OR(C16="Governed Operations Zone",C16="Autonomous Operations Zone"),S16<4),"R3 evidence tier "&S16&"<4; ",""))) | AH16: =IF($A16="","",IF(MIN(IF(X16="Critical Orbit",1,IF(X16="Unstable Orbit",2,IF(X16="Edge Orbit",3,IF(X16="Controlled Orbit",4,5)))),IF(AF16="None",9,IF(AF16="Critical Orbit",1,IF(AF16="Unstable Orbit",2,IF(AF16="Edge Orbit",3,IF(AF16="Controlled Orbit",4,5))))))=1,"Critical Orbit",IF(MIN(IF(X16="Critical Orbit",1,IF(X16="Unstable Orbit",2,IF(X16="Edge Orbit",3,IF(X16="Controlled Orbit",4,5)))),IF(AF16="None",9,IF(AF16="Critical Orbit",1,IF(AF16="Unstable Orbit",2,IF(AF16="Edge Orbit",3,IF(AF16="Controlled Orbit",4,5))))))=2,"Unstable Orbit",IF(MIN(IF(X16="Critical Orbit",1,IF(X16="Unstable Orbit",2,IF(X16="Edge Orbit",3,IF(X16="Controlled Orbit",4,5)))),IF(AF16="None",9,IF(AF16="Critical Orbit",1,IF(AF16="Unstable Orbit",2,IF(AF16="Edge Orbit",3,IF(AF16="Controlled Orbit",4,5))))))=3,"Edge Orbit",IF(MIN(IF(X16="Critical Orbit",1,IF(X16="Unstable Orbit",2,IF(X16="Edge Orbit",3,IF(X16="Controlled Orbit",4,5)))),IF(AF16="None",9,IF(AF16="Critical Orbit",1,IF(AF16="Unstable Orbit",2,IF(AF16="Edge Orbit",3,IF(AF16="Controlled Orbit",4,5))))))=4,"Controlled Orbit","Stable Orbit")))))
T17: =IF($A17="","",IF(AND(MAX(L17:R17)>3,S17<3),"Warning: EGI >3 needs Tier 3+ evidence",IF(AND(C17="Autonomous Operations Zone",S17<4),"Warning: Autonomous zone needs Tier 4 evidence","OK"))) | U17: =IF($A17="","",IF($D17="Basic",SUM(E17:K17)/35*100,SUMPRODUCT(E17:K17,INDEX('Weighted Scoring'!$B$5:$H$13,MATCH($B17,'Weighted Scoring'!$A$5:$A$13,0),0))/SUMPRODUCT(5,INDEX('Weighted Scoring'!$B$5:$H$13,MATCH($B17,'Weighted Scoring'!$A$5:$A$13,0),0))*100)) | V17: =IF($A17="","",IF($D17="Basic",SUM(L17:R17)/35*100,SUMPRODUCT(L17:R17,INDEX('Weighted Scoring'!$I$5:$O$13,MATCH($B17,'Weighted Scoring'!$A$5:$A$13,0),0))/SUMPRODUCT(5,INDEX('Weighted Scoring'!$I$5:$O$13,MATCH($B17,'Weighted Scoring'!$A$5:$A$13,0),0))*100)) | W17: =IF($A17="","",V17-U17) | X17: =IF($A17="","",IF(W17>=40,"Stable Orbit",IF(W17>=15,"Controlled Orbit",IF(W17>=-14,"Edge Orbit",IF(W17>=-39,"Unstable Orbit","Critical Orbit"))))) | Y17: =IF($A17="","",INDEX('Deployment Gates'!$C$5:$C$9,MATCH(AH17,'Deployment Gates'!$A$5:$A$9,0))) | AA17: =IF($A17="","",IF(OR(AH17="Edge Orbit",AH17="Unstable Orbit",AH17="Critical Orbit",H17>=4,G17>=4,E17>=4,J17>=4),"Yes","No")) | AB17: =IF($A17="","",IF(W17<0,"Yes","No")) | AC17: =IF($A17="","",INDEX($L$4:$R$4,1,MATCH(MIN(L17:R17),L17:R17,0))&IF(COUNTIF(L17:R17,MIN(L17:R17))>1," (+"&(COUNTIF(L17:R17,MIN(L17:R17))-1)&" tied)","")) | AD17: =IF($A17="","",INDEX($E$4:$K$4,1,MATCH(MAX(E17:K17),E17:K17,0))&IF(COUNTIF(E17:K17,MAX(E17:K17))>1," (+"&(COUNTIF(E17:K17,MAX(E17:K17))-1)&" tied)","")) | AE17: =IF($A17="","",INDEX('Control Uplift Planner'!$B$5:$B$11,MATCH(INDEX($L$4:$R$4,1,MATCH(MIN(L17:R17),L17:R17,0)),'Control Uplift Planner'!$A$5:$A$11,0))) | AF17: =IF($A17="","",IF(MIN(IF(AND(E17>=4,H17>=4),3,9),IF(AND(OR(C17="Governed Operations Zone",C17="Autonomous Operations Zone"),E17>=3),IF(MIN(L17:N17)=0,2,IF(MIN(L17:N17)=1,3,9)),9),IF(AND(OR(C17="Governed Operations Zone",C17="Autonomous Operations Zone"),S17<4),3,9))=9,"None",IF(MIN(IF(AND(E17>=4,H17>=4),3,9),IF(AND(OR(C17="Governed Operations Zone",C17="Autonomous Operations Zone"),E17>=3),IF(MIN(L17:N17)=0,2,IF(MIN(L17:N17)=1,3,9)),9),IF(AND(OR(C17="Governed Operations Zone",C17="Autonomous Operations Zone"),S17<4),3,9))=1,"Critical Orbit",IF(MIN(IF(AND(E17>=4,H17>=4),3,9),IF(AND(OR(C17="Governed Operations Zone",C17="Autonomous Operations Zone"),E17>=3),IF(MIN(L17:N17)=0,2,IF(MIN(L17:N17)=1,3,9)),9),IF(AND(OR(C17="Governed Operations Zone",C17="Autonomous Operations Zone"),S17<4),3,9))=2,"Unstable Orbit","Edge Orbit")))) | AG17: =IF($A17="","",IF(IF(AND(E17>=4,H17>=4),"R1 concentrated force; ","")&IF(AND(OR(C17="Governed Operations Zone",C17="Autonomous Operations Zone"),E17>=3,MIN(L17:N17)<=1),"R2 mandatory control "&INDEX($L$4:$N$4,1,MATCH(MIN(L17:N17),L17:N17,0))&"="&MIN(L17:N17)&"; ","")&IF(AND(OR(C17="Governed Operations Zone",C17="Autonomous Operations Zone"),S17<4),"R3 evidence tier "&S17&"<4; ","")="","-",IF(AND(E17>=4,H17>=4),"R1 concentrated force; ","")&IF(AND(OR(C17="Governed Operations Zone",C17="Autonomous Operations Zone"),E17>=3,MIN(L17:N17)<=1),"R2 mandatory control "&INDEX($L$4:$N$4,1,MATCH(MIN(L17:N17),L17:N17,0))&"="&MIN(L17:N17)&"; ","")&IF(AND(OR(C17="Governed Operations Zone",C17="Autonomous Operations Zone"),S17<4),"R3 evidence tier "&S17&"<4; ",""))) | AH17: =IF($A17="","",IF(MIN(IF(X17="Critical Orbit",1,IF(X17="Unstable Orbit",2,IF(X17="Edge Orbit",3,IF(X17="Controlled Orbit",4,5)))),IF(AF17="None",9,IF(AF17="Critical Orbit",1,IF(AF17="Unstable Orbit",2,IF(AF17="Edge Orbit",3,IF(AF17="Controlled Orbit",4,5))))))=1,"Critical Orbit",IF(MIN(IF(X17="Critical Orbit",1,IF(X17="Unstable Orbit",2,IF(X17="Edge Orbit",3,IF(X17="Controlled Orbit",4,5)))),IF(AF17="None",9,IF(AF17="Critical Orbit",1,IF(AF17="Unstable Orbit",2,IF(AF17="Edge Orbit",3,IF(AF17="Controlled Orbit",4,5))))))=2,"Unstable Orbit",IF(MIN(IF(X17="Critical Orbit",1,IF(X17="Unstable Orbit",2,IF(X17="Edge Orbit",3,IF(X17="Controlled Orbit",4,5)))),IF(AF17="None",9,IF(AF17="Critical Orbit",1,IF(AF17="Unstable Orbit",2,IF(AF17="Edge Orbit",3,IF(AF17="Controlled Orbit",4,5))))))=3,"Edge Orbit",IF(MIN(IF(X17="Critical Orbit",1,IF(X17="Unstable Orbit",2,IF(X17="Edge Orbit",3,IF(X17="Controlled Orbit",4,5)))),IF(AF17="None",9,IF(AF17="Critical Orbit",1,IF(AF17="Unstable Orbit",2,IF(AF17="Edge Orbit",3,IF(AF17="Controlled Orbit",4,5))))))=4,"Controlled Orbit","Stable Orbit")))))
T18: =IF($A18="","",IF(AND(MAX(L18:R18)>3,S18<3),"Warning: EGI >3 needs Tier 3+ evidence",IF(AND(C18="Autonomous Operations Zone",S18<4),"Warning: Autonomous zone needs Tier 4 evidence","OK"))) | U18: =IF($A18="","",IF($D18="Basic",SUM(E18:K18)/35*100,SUMPRODUCT(E18:K18,INDEX('Weighted Scoring'!$B$5:$H$13,MATCH($B18,'Weighted Scoring'!$A$5:$A$13,0),0))/SUMPRODUCT(5,INDEX('Weighted Scoring'!$B$5:$H$13,MATCH($B18,'Weighted Scoring'!$A$5:$A$13,0),0))*100)) | V18: =IF($A18="","",IF($D18="Basic",SUM(L18:R18)/35*100,SUMPRODUCT(L18:R18,INDEX('Weighted Scoring'!$I$5:$O$13,MATCH($B18,'Weighted Scoring'!$A$5:$A$13,0),0))/SUMPRODUCT(5,INDEX('Weighted Scoring'!$I$5:$O$13,MATCH($B18,'Weighted Scoring'!$A$5:$A$13,0),0))*100)) | W18: =IF($A18="","",V18-U18) | X18: =IF($A18="","",IF(W18>=40,"Stable Orbit",IF(W18>=15,"Controlled Orbit",IF(W18>=-14,"Edge Orbit",IF(W18>=-39,"Unstable Orbit","Critical Orbit"))))) | Y18: =IF($A18="","",INDEX('Deployment Gates'!$C$5:$C$9,MATCH(AH18,'Deployment Gates'!$A$5:$A$9,0))) | AA18: =IF($A18="","",IF(OR(AH18="Edge Orbit",AH18="Unstable Orbit",AH18="Critical Orbit",H18>=4,G18>=4,E18>=4,J18>=4),"Yes","No")) | AB18: =IF($A18="","",IF(W18<0,"Yes","No")) | AC18: =IF($A18="","",INDEX($L$4:$R$4,1,MATCH(MIN(L18:R18),L18:R18,0))&IF(COUNTIF(L18:R18,MIN(L18:R18))>1," (+"&(COUNTIF(L18:R18,MIN(L18:R18))-1)&" tied)","")) | AD18: =IF($A18="","",INDEX($E$4:$K$4,1,MATCH(MAX(E18:K18),E18:K18,0))&IF(COUNTIF(E18:K18,MAX(E18:K18))>1," (+"&(COUNTIF(E18:K18,MAX(E18:K18))-1)&" tied)","")) | AE18: =IF($A18="","",INDEX('Control Uplift Planner'!$B$5:$B$11,MATCH(INDEX($L$4:$R$4,1,MATCH(MIN(L18:R18),L18:R18,0)),'Control Uplift Planner'!$A$5:$A$11,0))) | AF18: =IF($A18="","",IF(MIN(IF(AND(E18>=4,H18>=4),3,9),IF(AND(OR(C18="Governed Operations Zone",C18="Autonomous Operations Zone"),E18>=3),IF(MIN(L18:N18)=0,2,IF(MIN(L18:N18)=1,3,9)),9),IF(AND(OR(C18="Governed Operations Zone",C18="Autonomous Operations Zone"),S18<4),3,9))=9,"None",IF(MIN(IF(AND(E18>=4,H18>=4),3,9),IF(AND(OR(C18="Governed Operations Zone",C18="Autonomous Operations Zone"),E18>=3),IF(MIN(L18:N18)=0,2,IF(MIN(L18:N18)=1,3,9)),9),IF(AND(OR(C18="Governed Operations Zone",C18="Autonomous Operations Zone"),S18<4),3,9))=1,"Critical Orbit",IF(MIN(IF(AND(E18>=4,H18>=4),3,9),IF(AND(OR(C18="Governed Operations Zone",C18="Autonomous Operations Zone"),E18>=3),IF(MIN(L18:N18)=0,2,IF(MIN(L18:N18)=1,3,9)),9),IF(AND(OR(C18="Governed Operations Zone",C18="Autonomous Operations Zone"),S18<4),3,9))=2,"Unstable Orbit","Edge Orbit")))) | AG18: =IF($A18="","",IF(IF(AND(E18>=4,H18>=4),"R1 concentrated force; ","")&IF(AND(OR(C18="Governed Operations Zone",C18="Autonomous Operations Zone"),E18>=3,MIN(L18:N18)<=1),"R2 mandatory control "&INDEX($L$4:$N$4,1,MATCH(MIN(L18:N18),L18:N18,0))&"="&MIN(L18:N18)&"; ","")&IF(AND(OR(C18="Governed Operations Zone",C18="Autonomous Operations Zone"),S18<4),"R3 evidence tier "&S18&"<4; ","")="","-",IF(AND(E18>=4,H18>=4),"R1 concentrated force; ","")&IF(AND(OR(C18="Governed Operations Zone",C18="Autonomous Operations Zone"),E18>=3,MIN(L18:N18)<=1),"R2 mandatory control "&INDEX($L$4:$N$4,1,MATCH(MIN(L18:N18),L18:N18,0))&"="&MIN(L18:N18)&"; ","")&IF(AND(OR(C18="Governed Operations Zone",C18="Autonomous Operations Zone"),S18<4),"R3 evidence tier "&S18&"<4; ",""))) | AH18: =IF($A18="","",IF(MIN(IF(X18="Critical Orbit",1,IF(X18="Unstable Orbit",2,IF(X18="Edge Orbit",3,IF(X18="Controlled Orbit",4,5)))),IF(AF18="None",9,IF(AF18="Critical Orbit",1,IF(AF18="Unstable Orbit",2,IF(AF18="Edge Orbit",3,IF(AF18="Controlled Orbit",4,5))))))=1,"Critical Orbit",IF(MIN(IF(X18="Critical Orbit",1,IF(X18="Unstable Orbit",2,IF(X18="Edge Orbit",3,IF(X18="Controlled Orbit",4,5)))),IF(AF18="None",9,IF(AF18="Critical Orbit",1,IF(AF18="Unstable Orbit",2,IF(AF18="Edge Orbit",3,IF(AF18="Controlled Orbit",4,5))))))=2,"Unstable Orbit",IF(MIN(IF(X18="Critical Orbit",1,IF(X18="Unstable Orbit",2,IF(X18="Edge Orbit",3,IF(X18="Controlled Orbit",4,5)))),IF(AF18="None",9,IF(AF18="Critical Orbit",1,IF(AF18="Unstable Orbit",2,IF(AF18="Edge Orbit",3,IF(AF18="Controlled Orbit",4,5))))))=3,"Edge Orbit",IF(MIN(IF(X18="Critical Orbit",1,IF(X18="Unstable Orbit",2,IF(X18="Edge Orbit",3,IF(X18="Controlled Orbit",4,5)))),IF(AF18="None",9,IF(AF18="Critical Orbit",1,IF(AF18="Unstable Orbit",2,IF(AF18="Edge Orbit",3,IF(AF18="Controlled Orbit",4,5))))))=4,"Controlled Orbit","Stable Orbit")))))
T19: =IF($A19="","",IF(AND(MAX(L19:R19)>3,S19<3),"Warning: EGI >3 needs Tier 3+ evidence",IF(AND(C19="Autonomous Operations Zone",S19<4),"Warning: Autonomous zone needs Tier 4 evidence","OK"))) | U19: =IF($A19="","",IF($D19="Basic",SUM(E19:K19)/35*100,SUMPRODUCT(E19:K19,INDEX('Weighted Scoring'!$B$5:$H$13,MATCH($B19,'Weighted Scoring'!$A$5:$A$13,0),0))/SUMPRODUCT(5,INDEX('Weighted Scoring'!$B$5:$H$13,MATCH($B19,'Weighted Scoring'!$A$5:$A$13,0),0))*100)) | V19: =IF($A19="","",IF($D19="Basic",SUM(L19:R19)/35*100,SUMPRODUCT(L19:R19,INDEX('Weighted Scoring'!$I$5:$O$13,MATCH($B19,'Weighted Scoring'!$A$5:$A$13,0),0))/SUMPRODUCT(5,INDEX('Weighted Scoring'!$I$5:$O$13,MATCH($B19,'Weighted Scoring'!$A$5:$A$13,0),0))*100)) | W19: =IF($A19="","",V19-U19) | X19: =IF($A19="","",IF(W19>=40,"Stable Orbit",IF(W19>=15,"Controlled Orbit",IF(W19>=-14,"Edge Orbit",IF(W19>=-39,"Unstable Orbit","Critical Orbit"))))) | Y19: =IF($A19="","",INDEX('Deployment Gates'!$C$5:$C$9,MATCH(AH19,'Deployment Gates'!$A$5:$A$9,0))) | AA19: =IF($A19="","",IF(OR(AH19="Edge Orbit",AH19="Unstable Orbit",AH19="Critical Orbit",H19>=4,G19>=4,E19>=4,J19>=4),"Yes","No")) | AB19: =IF($A19="","",IF(W19<0,"Yes","No")) | AC19: =IF($A19="","",INDEX($L$4:$R$4,1,MATCH(MIN(L19:R19),L19:R19,0))&IF(COUNTIF(L19:R19,MIN(L19:R19))>1," (+"&(COUNTIF(L19:R19,MIN(L19:R19))-1)&" tied)","")) | AD19: =IF($A19="","",INDEX($E$4:$K$4,1,MATCH(MAX(E19:K19),E19:K19,0))&IF(COUNTIF(E19:K19,MAX(E19:K19))>1," (+"&(COUNTIF(E19:K19,MAX(E19:K19))-1)&" tied)","")) | AE19: =IF($A19="","",INDEX('Control Uplift Planner'!$B$5:$B$11,MATCH(INDEX($L$4:$R$4,1,MATCH(MIN(L19:R19),L19:R19,0)),'Control Uplift Planner'!$A$5:$A$11,0))) | AF19: =IF($A19="","",IF(MIN(IF(AND(E19>=4,H19>=4),3,9),IF(AND(OR(C19="Governed Operations Zone",C19="Autonomous Operations Zone"),E19>=3),IF(MIN(L19:N19)=0,2,IF(MIN(L19:N19)=1,3,9)),9),IF(AND(OR(C19="Governed Operations Zone",C19="Autonomous Operations Zone"),S19<4),3,9))=9,"None",IF(MIN(IF(AND(E19>=4,H19>=4),3,9),IF(AND(OR(C19="Governed Operations Zone",C19="Autonomous Operations Zone"),E19>=3),IF(MIN(L19:N19)=0,2,IF(MIN(L19:N19)=1,3,9)),9),IF(AND(OR(C19="Governed Operations Zone",C19="Autonomous Operations Zone"),S19<4),3,9))=1,"Critical Orbit",IF(MIN(IF(AND(E19>=4,H19>=4),3,9),IF(AND(OR(C19="Governed Operations Zone",C19="Autonomous Operations Zone"),E19>=3),IF(MIN(L19:N19)=0,2,IF(MIN(L19:N19)=1,3,9)),9),IF(AND(OR(C19="Governed Operations Zone",C19="Autonomous Operations Zone"),S19<4),3,9))=2,"Unstable Orbit","Edge Orbit")))) | AG19: =IF($A19="","",IF(IF(AND(E19>=4,H19>=4),"R1 concentrated force; ","")&IF(AND(OR(C19="Governed Operations Zone",C19="Autonomous Operations Zone"),E19>=3,MIN(L19:N19)<=1),"R2 mandatory control "&INDEX($L$4:$N$4,1,MATCH(MIN(L19:N19),L19:N19,0))&"="&MIN(L19:N19)&"; ","")&IF(AND(OR(C19="Governed Operations Zone",C19="Autonomous Operations Zone"),S19<4),"R3 evidence tier "&S19&"<4; ","")="","-",IF(AND(E19>=4,H19>=4),"R1 concentrated force; ","")&IF(AND(OR(C19="Governed Operations Zone",C19="Autonomous Operations Zone"),E19>=3,MIN(L19:N19)<=1),"R2 mandatory control "&INDEX($L$4:$N$4,1,MATCH(MIN(L19:N19),L19:N19,0))&"="&MIN(L19:N19)&"; ","")&IF(AND(OR(C19="Governed Operations Zone",C19="Autonomous Operations Zone"),S19<4),"R3 evidence tier "&S19&"<4; ",""))) | AH19: =IF($A19="","",IF(MIN(IF(X19="Critical Orbit",1,IF(X19="Unstable Orbit",2,IF(X19="Edge Orbit",3,IF(X19="Controlled Orbit",4,5)))),IF(AF19="None",9,IF(AF19="Critical Orbit",1,IF(AF19="Unstable Orbit",2,IF(AF19="Edge Orbit",3,IF(AF19="Controlled Orbit",4,5))))))=1,"Critical Orbit",IF(MIN(IF(X19="Critical Orbit",1,IF(X19="Unstable Orbit",2,IF(X19="Edge Orbit",3,IF(X19="Controlled Orbit",4,5)))),IF(AF19="None",9,IF(AF19="Critical Orbit",1,IF(AF19="Unstable Orbit",2,IF(AF19="Edge Orbit",3,IF(AF19="Controlled Orbit",4,5))))))=2,"Unstable Orbit",IF(MIN(IF(X19="Critical Orbit",1,IF(X19="Unstable Orbit",2,IF(X19="Edge Orbit",3,IF(X19="Controlled Orbit",4,5)))),IF(AF19="None",9,IF(AF19="Critical Orbit",1,IF(AF19="Unstable Orbit",2,IF(AF19="Edge Orbit",3,IF(AF19="Controlled Orbit",4,5))))))=3,"Edge Orbit",IF(MIN(IF(X19="Critical Orbit",1,IF(X19="Unstable Orbit",2,IF(X19="Edge Orbit",3,IF(X19="Controlled Orbit",4,5)))),IF(AF19="None",9,IF(AF19="Critical Orbit",1,IF(AF19="Unstable Orbit",2,IF(AF19="Edge Orbit",3,IF(AF19="Controlled Orbit",4,5))))))=4,"Controlled Orbit","Stable Orbit")))))
T20: =IF($A20="","",IF(AND(MAX(L20:R20)>3,S20<3),"Warning: EGI >3 needs Tier 3+ evidence",IF(AND(C20="Autonomous Operations Zone",S20<4),"Warning: Autonomous zone needs Tier 4 evidence","OK"))) | U20: =IF($A20="","",IF($D20="Basic",SUM(E20:K20)/35*100,SUMPRODUCT(E20:K20,INDEX('Weighted Scoring'!$B$5:$H$13,MATCH($B20,'Weighted Scoring'!$A$5:$A$13,0),0))/SUMPRODUCT(5,INDEX('Weighted Scoring'!$B$5:$H$13,MATCH($B20,'Weighted Scoring'!$A$5:$A$13,0),0))*100)) | V20: =IF($A20="","",IF($D20="Basic",SUM(L20:R20)/35*100,SUMPRODUCT(L20:R20,INDEX('Weighted Scoring'!$I$5:$O$13,MATCH($B20,'Weighted Scoring'!$A$5:$A$13,0),0))/SUMPRODUCT(5,INDEX('Weighted Scoring'!$I$5:$O$13,MATCH($B20,'Weighted Scoring'!$A$5:$A$13,0),0))*100)) | W20: =IF($A20="","",V20-U20) | X20: =IF($A20="","",IF(W20>=40,"Stable Orbit",IF(W20>=15,"Controlled Orbit",IF(W20>=-14,"Edge Orbit",IF(W20>=-39,"Unstable Orbit","Critical Orbit"))))) | Y20: =IF($A20="","",INDEX('Deployment Gates'!$C$5:$C$9,MATCH(AH20,'Deployment Gates'!$A$5:$A$9,0))) | AA20: =IF($A20="","",IF(OR(AH20="Edge Orbit",AH20="Unstable Orbit",AH20="Critical Orbit",H20>=4,G20>=4,E20>=4,J20>=4),"Yes","No")) | AB20: =IF($A20="","",IF(W20<0,"Yes","No")) | AC20: =IF($A20="","",INDEX($L$4:$R$4,1,MATCH(MIN(L20:R20),L20:R20,0))&IF(COUNTIF(L20:R20,MIN(L20:R20))>1," (+"&(COUNTIF(L20:R20,MIN(L20:R20))-1)&" tied)","")) | AD20: =IF($A20="","",INDEX($E$4:$K$4,1,MATCH(MAX(E20:K20),E20:K20,0))&IF(COUNTIF(E20:K20,MAX(E20:K20))>1," (+"&(COUNTIF(E20:K20,MAX(E20:K20))-1)&" tied)","")) | AE20: =IF($A20="","",INDEX('Control Uplift Planner'!$B$5:$B$11,MATCH(INDEX($L$4:$R$4,1,MATCH(MIN(L20:R20),L20:R20,0)),'Control Uplift Planner'!$A$5:$A$11,0))) | AF20: =IF($A20="","",IF(MIN(IF(AND(E20>=4,H20>=4),3,9),IF(AND(OR(C20="Governed Operations Zone",C20="Autonomous Operations Zone"),E20>=3),IF(MIN(L20:N20)=0,2,IF(MIN(L20:N20)=1,3,9)),9),IF(AND(OR(C20="Governed Operations Zone",C20="Autonomous Operations Zone"),S20<4),3,9))=9,"None",IF(MIN(IF(AND(E20>=4,H20>=4),3,9),IF(AND(OR(C20="Governed Operations Zone",C20="Autonomous Operations Zone"),E20>=3),IF(MIN(L20:N20)=0,2,IF(MIN(L20:N20)=1,3,9)),9),IF(AND(OR(C20="Governed Operations Zone",C20="Autonomous Operations Zone"),S20<4),3,9))=1,"Critical Orbit",IF(MIN(IF(AND(E20>=4,H20>=4),3,9),IF(AND(OR(C20="Governed Operations Zone",C20="Autonomous Operations Zone"),E20>=3),IF(MIN(L20:N20)=0,2,IF(MIN(L20:N20)=1,3,9)),9),IF(AND(OR(C20="Governed Operations Zone",C20="Autonomous Operations Zone"),S20<4),3,9))=2,"Unstable Orbit","Edge Orbit")))) | AG20: =IF($A20="","",IF(IF(AND(E20>=4,H20>=4),"R1 concentrated force; ","")&IF(AND(OR(C20="Governed Operations Zone",C20="Autonomous Operations Zone"),E20>=3,MIN(L20:N20)<=1),"R2 mandatory control "&INDEX($L$4:$N$4,1,MATCH(MIN(L20:N20),L20:N20,0))&"="&MIN(L20:N20)&"; ","")&IF(AND(OR(C20="Governed Operations Zone",C20="Autonomous Operations Zone"),S20<4),"R3 evidence tier "&S20&"<4; ","")="","-",IF(AND(E20>=4,H20>=4),"R1 concentrated force; ","")&IF(AND(OR(C20="Governed Operations Zone",C20="Autonomous Operations Zone"),E20>=3,MIN(L20:N20)<=1),"R2 mandatory control "&INDEX($L$4:$N$4,1,MATCH(MIN(L20:N20),L20:N20,0))&"="&MIN(L20:N20)&"; ","")&IF(AND(OR(C20="Governed Operations Zone",C20="Autonomous Operations Zone"),S20<4),"R3 evidence tier "&S20&"<4; ",""))) | AH20: =IF($A20="","",IF(MIN(IF(X20="Critical Orbit",1,IF(X20="Unstable Orbit",2,IF(X20="Edge Orbit",3,IF(X20="Controlled Orbit",4,5)))),IF(AF20="None",9,IF(AF20="Critical Orbit",1,IF(AF20="Unstable Orbit",2,IF(AF20="Edge Orbit",3,IF(AF20="Controlled Orbit",4,5))))))=1,"Critical Orbit",IF(MIN(IF(X20="Critical Orbit",1,IF(X20="Unstable Orbit",2,IF(X20="Edge Orbit",3,IF(X20="Controlled Orbit",4,5)))),IF(AF20="None",9,IF(AF20="Critical Orbit",1,IF(AF20="Unstable Orbit",2,IF(AF20="Edge Orbit",3,IF(AF20="Controlled Orbit",4,5))))))=2,"Unstable Orbit",IF(MIN(IF(X20="Critical Orbit",1,IF(X20="Unstable Orbit",2,IF(X20="Edge Orbit",3,IF(X20="Controlled Orbit",4,5)))),IF(AF20="None",9,IF(AF20="Critical Orbit",1,IF(AF20="Unstable Orbit",2,IF(AF20="Edge Orbit",3,IF(AF20="Controlled Orbit",4,5))))))=3,"Edge Orbit",IF(MIN(IF(X20="Critical Orbit",1,IF(X20="Unstable Orbit",2,IF(X20="Edge Orbit",3,IF(X20="Controlled Orbit",4,5)))),IF(AF20="None",9,IF(AF20="Critical Orbit",1,IF(AF20="Unstable Orbit",2,IF(AF20="Edge Orbit",3,IF(AF20="Controlled Orbit",4,5))))))=4,"Controlled Orbit","Stable Orbit")))))
T21: =IF($A21="","",IF(AND(MAX(L21:R21)>3,S21<3),"Warning: EGI >3 needs Tier 3+ evidence",IF(AND(C21="Autonomous Operations Zone",S21<4),"Warning: Autonomous zone needs Tier 4 evidence","OK"))) | U21: =IF($A21="","",IF($D21="Basic",SUM(E21:K21)/35*100,SUMPRODUCT(E21:K21,INDEX('Weighted Scoring'!$B$5:$H$13,MATCH($B21,'Weighted Scoring'!$A$5:$A$13,0),0))/SUMPRODUCT(5,INDEX('Weighted Scoring'!$B$5:$H$13,MATCH($B21,'Weighted Scoring'!$A$5:$A$13,0),0))*100)) | V21: =IF($A21="","",IF($D21="Basic",SUM(L21:R21)/35*100,SUMPRODUCT(L21:R21,INDEX('Weighted Scoring'!$I$5:$O$13,MATCH($B21,'Weighted Scoring'!$A$5:$A$13,0),0))/SUMPRODUCT(5,INDEX('Weighted Scoring'!$I$5:$O$13,MATCH($B21,'Weighted Scoring'!$A$5:$A$13,0),0))*100)) | W21: =IF($A21="","",V21-U21) | X21: =IF($A21="","",IF(W21>=40,"Stable Orbit",IF(W21>=15,"Controlled Orbit",IF(W21>=-14,"Edge Orbit",IF(W21>=-39,"Unstable Orbit","Critical Orbit"))))) | Y21: =IF($A21="","",INDEX('Deployment Gates'!$C$5:$C$9,MATCH(AH21,'Deployment Gates'!$A$5:$A$9,0))) | AA21: =IF($A21="","",IF(OR(AH21="Edge Orbit",AH21="Unstable Orbit",AH21="Critical Orbit",H21>=4,G21>=4,E21>=4,J21>=4),"Yes","No")) | AB21: =IF($A21="","",IF(W21<0,"Yes","No")) | AC21: =IF($A21="","",INDEX($L$4:$R$4,1,MATCH(MIN(L21:R21),L21:R21,0))&IF(COUNTIF(L21:R21,MIN(L21:R21))>1," (+"&(COUNTIF(L21:R21,MIN(L21:R21))-1)&" tied)","")) | AD21: =IF($A21="","",INDEX($E$4:$K$4,1,MATCH(MAX(E21:K21),E21:K21,0))&IF(COUNTIF(E21:K21,MAX(E21:K21))>1," (+"&(COUNTIF(E21:K21,MAX(E21:K21))-1)&" tied)","")) | AE21: =IF($A21="","",INDEX('Control Uplift Planner'!$B$5:$B$11,MATCH(INDEX($L$4:$R$4,1,MATCH(MIN(L21:R21),L21:R21,0)),'Control Uplift Planner'!$A$5:$A$11,0))) | AF21: =IF($A21="","",IF(MIN(IF(AND(E21>=4,H21>=4),3,9),IF(AND(OR(C21="Governed Operations Zone",C21="Autonomous Operations Zone"),E21>=3),IF(MIN(L21:N21)=0,2,IF(MIN(L21:N21)=1,3,9)),9),IF(AND(OR(C21="Governed Operations Zone",C21="Autonomous Operations Zone"),S21<4),3,9))=9,"None",IF(MIN(IF(AND(E21>=4,H21>=4),3,9),IF(AND(OR(C21="Governed Operations Zone",C21="Autonomous Operations Zone"),E21>=3),IF(MIN(L21:N21)=0,2,IF(MIN(L21:N21)=1,3,9)),9),IF(AND(OR(C21="Governed Operations Zone",C21="Autonomous Operations Zone"),S21<4),3,9))=1,"Critical Orbit",IF(MIN(IF(AND(E21>=4,H21>=4),3,9),IF(AND(OR(C21="Governed Operations Zone",C21="Autonomous Operations Zone"),E21>=3),IF(MIN(L21:N21)=0,2,IF(MIN(L21:N21)=1,3,9)),9),IF(AND(OR(C21="Governed Operations Zone",C21="Autonomous Operations Zone"),S21<4),3,9))=2,"Unstable Orbit","Edge Orbit")))) | AG21: =IF($A21="","",IF(IF(AND(E21>=4,H21>=4),"R1 concentrated force; ","")&IF(AND(OR(C21="Governed Operations Zone",C21="Autonomous Operations Zone"),E21>=3,MIN(L21:N21)<=1),"R2 mandatory control "&INDEX($L$4:$N$4,1,MATCH(MIN(L21:N21),L21:N21,0))&"="&MIN(L21:N21)&"; ","")&IF(AND(OR(C21="Governed Operations Zone",C21="Autonomous Operations Zone"),S21<4),"R3 evidence tier "&S21&"<4; ","")="","-",IF(AND(E21>=4,H21>=4),"R1 concentrated force; ","")&IF(AND(OR(C21="Governed Operations Zone",C21="Autonomous Operations Zone"),E21>=3,MIN(L21:N21)<=1),"R2 mandatory control "&INDEX($L$4:$N$4,1,MATCH(MIN(L21:N21),L21:N21,0))&"="&MIN(L21:N21)&"; ","")&IF(AND(OR(C21="Governed Operations Zone",C21="Autonomous Operations Zone"),S21<4),"R3 evidence tier "&S21&"<4; ",""))) | AH21: =IF($A21="","",IF(MIN(IF(X21="Critical Orbit",1,IF(X21="Unstable Orbit",2,IF(X21="Edge Orbit",3,IF(X21="Controlled Orbit",4,5)))),IF(AF21="None",9,IF(AF21="Critical Orbit",1,IF(AF21="Unstable Orbit",2,IF(AF21="Edge Orbit",3,IF(AF21="Controlled Orbit",4,5))))))=1,"Critical Orbit",IF(MIN(IF(X21="Critical Orbit",1,IF(X21="Unstable Orbit",2,IF(X21="Edge Orbit",3,IF(X21="Controlled Orbit",4,5)))),IF(AF21="None",9,IF(AF21="Critical Orbit",1,IF(AF21="Unstable Orbit",2,IF(AF21="Edge Orbit",3,IF(AF21="Controlled Orbit",4,5))))))=2,"Unstable Orbit",IF(MIN(IF(X21="Critical Orbit",1,IF(X21="Unstable Orbit",2,IF(X21="Edge Orbit",3,IF(X21="Controlled Orbit",4,5)))),IF(AF21="None",9,IF(AF21="Critical Orbit",1,IF(AF21="Unstable Orbit",2,IF(AF21="Edge Orbit",3,IF(AF21="Controlled Orbit",4,5))))))=3,"Edge Orbit",IF(MIN(IF(X21="Critical Orbit",1,IF(X21="Unstable Orbit",2,IF(X21="Edge Orbit",3,IF(X21="Controlled Orbit",4,5)))),IF(AF21="None",9,IF(AF21="Critical Orbit",1,IF(AF21="Unstable Orbit",2,IF(AF21="Edge Orbit",3,IF(AF21="Controlled Orbit",4,5))))))=4,"Controlled Orbit","Stable Orbit")))))
... T104: =IF($A104="","",IF(AND(MAX(L104:R104)>3,S104<3),"Warning: EGI >3 needs Tier 3+ evidence",IF(AND(C104="Autonomous Operations Zone",S104<4),"Warning: Autonomous zone needs Tier 4 evidence","OK"))) | U104: =IF($A104="","",IF($D104="Basic",SUM(E104:K104)/35*100,SUMPRODUCT(E104:K104,INDEX('Weighted Scoring'!$B$5:$H$13,MATCH($B104,'Weighted Scoring'!$A$5:$A$13,0),0))/SUMPRODUCT(5,INDEX('Weighted Scoring'!$B$5:$H$13,MATCH($B104,'Weighted Scoring'!$A$5:$A$13,0),0))*100)) | V104: =IF($A104="","",IF($D104="Basic",SUM(L104:R104)/35*100,SUMPRODUCT(L104:R104,INDEX('Weighted Scoring'!$I$5:$O$13,MATCH($B104,'Weighted Scoring'!$A$5:$A$13,0),0))/SUMPRODUCT(5,INDEX('Weighted Scoring'!$I$5:$O$13,MATCH($B104,'Weighted Scoring'!$A$5:$A$13,0),0))*100)) | W104: =IF($A104="","",V104-U104) | X104: =IF($A104="","",IF(W104>=40,"Stable Orbit",IF(W104>=15,"Controlled Orbit",IF(W104>=-14,"Edge Orbit",IF(W104>=-39,"Unstable Orbit","Critical Orbit"))))) | Y104: =IF($A104="","",INDEX('Deployment Gates'!$C$5:$C$9,MATCH(AH104,'Deployment Gates'!$A$5:$A$9,0))) | AA104: =IF($A104="","",IF(OR(AH104="Edge Orbit",AH104="Unstable Orbit",AH104="Critical Orbit",H104>=4,G104>=4,E104>=4,J104>=4),"Yes","No")) | AB104: =IF($A104="","",IF(W104<0,"Yes","No")) | AC104: =IF($A104="","",INDEX($L$4:$R$4,1,MATCH(MIN(L104:R104),L104:R104,0))&IF(COUNTIF(L104:R104,MIN(L104:R104))>1," (+"&(COUNTIF(L104:R104,MIN(L104:R104))-1)&" tied)","")) | AD104: =IF($A104="","",INDEX($E$4:$K$4,1,MATCH(MAX(E104:K104),E104:K104,0))&IF(COUNTIF(E104:K104,MAX(E104:K104))>1," (+"&(COUNTIF(E104:K104,MAX(E104:K104))-1)&" tied)","")) | AE104: =IF($A104="","",INDEX('Control Uplift Planner'!$B$5:$B$11,MATCH(INDEX($L$4:$R$4,1,MATCH(MIN(L104:R104),L104:R104,0)),'Control Uplift Planner'!$A$5:$A$11,0))) | AF104: =IF($A104="","",IF(MIN(IF(AND(E104>=4,H104>=4),3,9),IF(AND(OR(C104="Governed Operations Zone",C104="Autonomous Operations Zone"),E104>=3),IF(MIN(L104:N104)=0,2,IF(MIN(L104:N104)=1,3,9)),9),IF(AND(OR(C104="Governed Operations Zone",C104="Autonomous Operations Zone"),S104<4),3,9))=9,"None",IF(MIN(IF(AND(E104>=4,H104>=4),3,9),IF(AND(OR(C104="Governed Operations Zone",C104="Autonomous Operations Zone"),E104>=3),IF(MIN(L104:N104)=0,2,IF(MIN(L104:N104)=1,3,9)),9),IF(AND(OR(C104="Governed Operations Zone",C104="Autonomous Operations Zone"),S104<4),3,9))=1,"Critical Orbit",IF(MIN(IF(AND(E104>=4,H104>=4),3,9),IF(AND(OR(C104="Governed Operations Zone",C104="Autonomous Operations Zone"),E104>=3),IF(MIN(L104:N104)=0,2,IF(MIN(L104:N104)=1,3,9)),9),IF(AND(OR(C104="Governed Operations Zone",C104="Autonomous Operations Zone"),S104<4),3,9))=2,"Unstable Orbit","Edge Orbit")))) | AG104: =IF($A104="","",IF(IF(AND(E104>=4,H104>=4),"R1 concentrated force; ","")&IF(AND(OR(C104="Governed Operations Zone",C104="Autonomous Operations Zone"),E104>=3,MIN(L104:N104)<=1),"R2 mandatory control "&INDEX($L$4:$N$4,1,MATCH(MIN(L104:N104),L104:N104,0))&"="&MIN(L104:N104)&"; ","")&IF(AND(OR(C104="Governed Operations Zone",C104="Autonomous Operations Zone"),S104<4),"R3 evidence tier "&S104&"<4; ","")="","-",IF(AND(E104>=4,H104>=4),"R1 concentrated force; ","")&IF(AND(OR(C104="Governed Operations Zone",C104="Autonomous Operations Zone"),E104>=3,MIN(L104:N104)<=1),"R2 mandatory control "&INDEX($L$4:$N$4,1,MATCH(MIN(L104:N104),L104:N104,0))&"="&MIN(L104:N104)&"; ","")&IF(AND(OR(C104="Governed Operations Zone",C104="Autonomous Operations Zone"),S104<4),"R3 evidence tier "&S104&"<4; ",""))) | AH104: =IF($A104="","",IF(MIN(IF(X104="Critical Orbit",1,IF(X104="Unstable Orbit",2,IF(X104="Edge Orbit",3,IF(X104="Controlled Orbit",4,5)))),IF(AF104="None",9,IF(AF104="Critical Orbit",1,IF(AF104="Unstable Orbit",2,IF(AF104="Edge Orbit",3,IF(AF104="Controlled Orbit",4,5))))))=1,"Critical Orbit",IF(MIN(IF(X104="Critical Orbit",1,IF(X104="Unstable Orbit",2,IF(X104="Edge Orbit",3,IF(X104="Controlled Orbit",4,5)))),IF(AF104="None",9,IF(AF104="Critical Orbit",1,IF(AF104="Unstable Orbit",2,IF(AF104="Edge Orbit",3,IF(AF104="Controlled Orbit",4,5))))))=2,"Unstable Orbit",IF(MIN(IF(X104="Critical Orbit",1,IF(X104="Unstable Orbit",2,IF(X104="Edge Orbit",3,IF(X104="Controlled Orbit",4,5)))),IF(AF104="None",9,IF(AF104="Critical Orbit",1,IF(AF104="Unstable Orbit",2,IF(AF104="Edge Orbit",3,IF(AF104="Controlled Orbit",4,5))))))=3,"Edge Orbit",IF(MIN(IF(X104="Critical Orbit",1,IF(X104="Unstable Orbit",2,IF(X104="Edge Orbit",3,IF(X104="Controlled Orbit",4,5)))),IF(AF104="None",9,IF(AF104="Critical Orbit",1,IF(AF104="Unstable Orbit",2,IF(AF104="Edge Orbit",3,IF(AF104="Controlled Orbit",4,5))))))=4,"Controlled Orbit","Stable Orbit")))))

Sheet Weighted Scoring
A1: Advanced Mode Weights
A2: Weights are applied only when Scoring Mode = Advanced
A4: Domain Overlay | B4: Decision Autonomy | C4: Decision Velocity | D4: Operational Reach | E4: Operational Criticality | F4: Adaptability | G4: Collaboration Complexity | H4: Persistence and Memory | I4: Identity | J4: Authorization | K4: Policy Enforcement | L4: Observability | M4: Governance and Lifecycle | N4: Recovery and Resilience | O4: Assurance and Evaluation
A5: Knowledge / Documentation | B5: 1 | C5: 1 | D5: 1 | E5: 1 | F5: 1 | G5: 1 | H5: 1 | I5: 1 | J5: 1 | K5: 1 | L5: 1 | M5: 1 | N5: 1 | O5: 1
A6: API Governance | B6: 1.4 | C6: 1 | D6: 1.5 | E6: 1.4 | F6: 1.2 | G6: 1 | H6: 1 | I6: 1.2 | J6: 1.4 | K6: 1.8 | L6: 1.6 | M6: 1.6 | N6: 1.1 | O6: 1.4
A7: Software Delivery | B7: 1.6 | C7: 1.2 | D7: 1.6 | E7: 1.8 | F7: 1.4 | G7: 1.3 | H7: 1 | I7: 1.3 | J7: 1.5 | K7: 1.9 | L7: 1.8 | M7: 1.2 | N7: 1.8 | O7: 1.7
A8: Cloud / Infrastructure | B8: 1.7 | C8: 1.5 | D8: 1.8 | E8: 1.9 | F8: 1.4 | G8: 1.2 | H8: 1.2 | I8: 1.5 | J8: 1.8 | K8: 1.9 | L8: 1.8 | M8: 1.2 | N8: 2 | O8: 1.6
A9: Security Operations | B9: 1.8 | C9: 1.6 | D9: 1.4 | E9: 1.9 | F9: 1.3 | G9: 1.2 | H9: 1 | I9: 1.8 | J9: 1.6 | K9: 2 | L9: 1.8 | M9: 1.1 | N9: 2 | O9: 1.7
A10: Customer Service | B10: 1.3 | C10: 1.5 | D10: 1.8 | E10: 1.7 | F10: 1.2 | G10: 1.1 | H10: 1.6 | I10: 1.2 | J10: 1.8 | K10: 1.4 | L10: 1.9 | M10: 1.2 | N10: 1.2 | O10: 1.8
A11: Financial Operations | B11: 1.8 | C11: 1.2 | D11: 1.7 | E11: 2 | F11: 1.2 | G11: 1 | H11: 1.3 | I11: 1.5 | J11: 2 | K11: 1.6 | L11: 1.5 | M11: 1.8 | N11: 1.4 | O11: 2
A12: Regulated Data | B12: 1.4 | C12: 1.1 | D12: 1.7 | E12: 2 | F12: 1.2 | G12: 1 | H12: 1.6 | I12: 1.4 | J12: 2 | K12: 1.7 | L12: 1.9 | M12: 1.7 | N12: 1.3 | O12: 2
A13: Multi-Agent SDLC | B13: 1.6 | C13: 1.3 | D13: 1.7 | E13: 1.8 | F13: 1.7 | G13: 2 | H13: 1.3 | I13: 1.4 | J13: 1.5 | K13: 1.8 | L13: 2 | M13: 1.9 | N13: 1.6 | O13: 1.8

Sheet AFI Rubric
A1: Agentic Force Index (AFI) Rubric
A2: Score each dimension from 0 to 5
A4: Dimension | B4: 0 | C4: 1 | D4: 2 | E4: 3 | F4: 4 | G4: 5
A5: Decision Autonomy | B5: No decision capability | C5: Suggests actions only | D5: Recommends for approval | E5: Executes after human approval | F5: Executes under policy approval | G5: Executes independently within delegated authority
A6: Decision Velocity | B6: No decisions | C6: Occasional/manual | D6: Daily/batch | E6: Hourly/event-driven | F6: Near-real-time | G6: Continuous autonomous loop
A7: Operational Reach | B7: No system access POPULATION: No consumers | C7: Single user workspace POPULATION: Single user | D7: Single application or repository POPULATION: Single team | E7: Multiple apps in one domain POPULATION: Single business unit | F7: Multiple domains or business units POPULATION: Multiple business units | G7: Enterprise-wide or external ecosystem POPULATION: Enterprise-wide, customer-facing, or external
A8: Operational Criticality | B8: No impact | C8: Low/cosmetic | D8: Team productivity | E8: Application/workflow | F8: Production/customer/security | G8: Financial/regulatory/safety/enterprise-critical
A9: Adaptability | B9: No adaptation | C9: Static prompt/fixed workflow | D9: Chooses predefined paths | E9: Generates dynamic plans | F9: Learns from feedback/memory | G9: Discovers tools/self-optimizes
A10: Collaboration Complexity | B10: No collaboration | C10: Single-agent | D10: Human-agent | E10: Multi-agent fixed roles | F10: Dynamic handoffs | G10: Swarm-like/emergent
A11: Persistence and Memory | B11: No persistence | C11: Single-session | D11: Short-term task memory | E11: Long-lived scoped memory | F11: Cross-session memory | G11: Enterprise/self-maintained memory
A16: Operational Reach — dual measure
A17: Score the WIDER of system breadth and consumer population. An agent touching one application but serving an entire enterprise has enterprise reach. Where the two measures differ, record which one drove the score. An agent serving external customers scores 5 on population regardless of how few systems it touches.

Sheet EGI Rubric
A1: Enterprise Gravity Index (EGI) Rubric
A2: Score only controls that are present, well-designed, and evidenced
A4: Dimension | B4: 0 | C4: 1 | D4: 2 | E4: 3 | F4: 4 | G4: 5
A5: Identity | B5: No distinct identity | C5: Shared user/service account | D5: Dedicated service identity | E5: Workload identity with ownership | F5: Short-lived credentials + strong auth | G5: Cryptographic identity + continuous verification
A6: Authorization | B6: No boundary | C6: Broad static access | D6: Role-based access | E6: Least privilege by tool/workflow | F6: Context-aware authorization | G6: Dynamic policy-driven JIT access
A7: Policy Enforcement | B7: None | C7: Human guidelines only | D7: Static config checks | E7: CI/CD or pre-execution checks | F7: Runtime policy enforcement | G7: Adaptive risk-based policy
A8: Observability | B8: No logs | C8: Basic application logs | D8: Tool-call logs | E8: Prompt/plan/action traces | F8: End-to-end traceability | G8: Audit-grade decision provenance
A9: Governance and Lifecycle | B9: No inventory | C9: Informal ownership | D9: Agent catalog/registry | E9: Lifecycle approval workflow | F9: Version/certification/deprecation | G9: Control plane for agents/tools/models/memory/policies
A10: Recovery and Resilience | B10: No recovery | C10: Manual intervention | D10: Basic rollback | E10: Kill switch/circuit breaker | F10: Automated rollback + human takeover | G10: Blast-radius isolation + recovery drills
A11: Assurance and Evaluation | B11: No evaluation | C11: Manual pre-release testing | D11: Basic prompt/output eval | E11: Scenario eval + red team | F11: Runtime eval + drift detection | G11: Continuous assurance across policy/behavior/security/outcomes

Sheet Evidence Tiers
A1: Evidence Tiers
A2: EGI scores above 3 require Tier 3+ evidence
A4: Tier | B4: Name | C4: Meaning | D4: Examples
A5: 0 | B5: Claimed | C5: Claimed, no evidence | D5: Verbal statement, slide, unvalidated design claim
A6: 1 | B6: Documented | C6: Documented design | D6: Architecture doc, policy draft, decision record
A7: 2 | B7: Implemented | C7: Implemented control | D7: Configured identity, gateway, policy, logging, workflow
A8: 3 | B8: Tested | C8: Tested control | D8: Validation result, policy test, rollback test, drill
A9: 4 | B9: Runtime Verified | C9: Runtime-verified control | D9: Production trace, policy decision log, audit event
A10: 5 | B10: Continuous Audit | C10: Continuously monitored and audited | D10: Dashboards, recurring evidence, automated checks
A12: Rule | B12: Applies To | C12: Requirement | D12: Notes
A13: EGI > 3 | B13: Any EGI dimension | C13: Tier 3+ evidence required | D13: Design intent is not enough
A14: Production-impacting agent | B14: Policy, Observability, Recovery, Assurance | C14: Tier 4+ evidence required to move beyond Edge Orbit | D14: Runtime proof expected

Sheet ABOM
A1: ABOM - System Boundary
A2: Defines model, runtime, memory, tools/MCP, identity, permissions, policies, approvals, and operating context.
A4: Category | B4: Required Information | C4: Owner | D4: Evidence Link / Location | E4: Status | F4: Control Responsibility
A5: Agentic System Instance | B5: Name, version, owner, purpose, business domain, assessed context
A6: Model | B6: Provider, model, deployment mode, approval status
A7: Runtime | B7: Agent framework, orchestrator, hosting environment
A8: Prompts | B8: System prompts, task prompts, prompt versioning
A9: Tools / MCP Servers | B9: APIs, MCP servers, plugins, scripts, functions, workflows; read/write capability, tool risk level, reversibility
A10: Data Sources | B10: KBs, vector stores, databases, files, SaaS systems
A11: Memory | B11: Session, short-term, long-term, enterprise memory
A12: Identity | B12: Agent identity, user delegation, service identity, on-behalf-of authority
A13: Authorization | B13: Permissions, scopes, roles, environments, JIT access, delegated authority model
A14: Policies | B14: Policy rules, enforcement points, exceptions, tool/action policies
A15: Observability | B15: Logs, traces, audit store, dashboards, prompt-plan-tool-action traces
A16: Recovery | B16: Rollback, kill switch, circuit breakers, compensating actions, reversibility limits
... A23: Operating Context | B23: Environment, users, approval model, delegated authority, business process, regulatory context
A62: Control Responsibility — recorded per EGI dimension where it differs
A63: Self-operated | B63: The assessing organization implements and can change the control.
A64: Platform-operated | B64: An internal platform team operates the control on the assessing team's behalf.
A65: Vendor-operated | B65: A third party operates it. The organization can influence it only contractually.
A67: Does NOT affect AFI, EGI, SMI or Orbit. A weak control presents the same risk whether built or bought; scoring it more favourably would reward the absence of remediation capability. Control Responsibility routes REMEDIATION only.

Sheet Threat Model
A1: ASF Threat Model Gate
A2: Required for Edge, Unstable, or Critical Orbit agents, and for any agent with production action authority, sensitive-data access, multi-agent handoffs, long-term memory, or external exposure.
A4: Threat Category | B4: Scenario / Question | C4: Likelihood | D4: Impact | E4: Mitigation | F4: Status
A5: Prompt injection | B5: Can user or retrieved content override agent instructions or policy boundaries?
A6: Tool misuse | B6: Can the agent invoke tools in unintended order, scope, or context?
A7: Excessive agency | B7: Does the agent have broader permissions than its task requires?
A8: Identity abuse | B8: Can agent identity or delegated user authority be misused?
A9: Memory poisoning | B9: Can malicious content persist and influence future behavior?
A10: Context poisoning | B10: Can retrieved content manipulate plan or tool choice?
A11: Data exfiltration | B11: Can retrieved or generated content leak sensitive data?
A12: Inter-agent manipulation | B12: Can one agent manipulate another through handoff, context, or memory?
A13: Policy evasion | B13: Can the agent bypass gateway, broker, or policy enforcement?
A14: Cascading failure | B14: Can one action trigger uncontrolled downstream impact?
A15: Recovery failure | B15: Can the enterprise stop, reverse, or contain action fast enough?

Sheet Domain Overlays
A1: Domain Overlays
A2: Adjust scoring emphasis, evidence expectations, threat scenarios, and uplift actions
A4: Overlay | B4: Use When | C4: Higher Force Weights | D4: Higher Gravity Weights | E4: Required Evidence
A5: Software Delivery | B5: Reviewing, coding, testing, merging, deploying software | C5: Autonomy, Criticality, Reach, Collaboration | D5: Policy, Recovery, Observability, Assurance | E5: Repo permissions, CI/CD logs, policy-as-code, rollback validation
A6: Cloud / Infrastructure | B6: Provisioning, configuring, remediating cloud/platform systems | C6: Autonomy, Reach, Criticality, Velocity | D6: Identity, Authorization, Policy, Recovery | E6: IaC policy, workload identity, namespace/account scoping, recovery drills
A7: Security Operations | B7: Triaging alerts, changing controls, incident response | C7: Autonomy, Criticality, Velocity | D7: Identity, Policy, Recovery, Observability | E7: SOC playbooks, evidence logs, credential boundaries, containment controls
A8: API Governance | B8: Reviewing specs, attaching policies, publishing APIs | C8: Reach, Criticality, Autonomy | D8: Policy, Observability, Governance, Authorization | E8: Catalog workflow, Spectral/OPA rules, gateway policy binding records
A9: Customer Service | B9: Using CRM, case data, external customer communications | C9: Reach, Criticality, Memory | D9: Authorization, Assurance, Observability | E9: PII controls, response review, escalation logs
A10: Financial Operations | B10: Payments, invoices, reconciliation, approvals | C10: Criticality, Autonomy, Reach | D10: Authorization, Assurance, Governance | E10: Segregation of duties, approval records, fraud controls
A11: Regulated Data | B11: Health, financial, legal, regulated data | C11: Criticality, Reach, Memory | D11: Authorization, Observability, Assurance | E11: Data classification, audit-grade logs, regulatory review
A12: Multi-Agent SDLC | B12: Planner, coder, tester, reviewer, release handoffs | C12: Collaboration, Adaptability, Reach | D12: Observability, Policy, Governance | E12: Handoff traces, shared memory controls, conflict resolution
A13: Knowledge / Documentation | B13: Read-only enterprise knowledge assistants | C13: Reach, Memory | D13: Identity, Authorization, Observability | E13: Approved sources, access logs, output disclaimers where needed

Sheet Non-Compensatory Rules
A1: ASF v1.1 — Non-Compensatory Rules
A2: AFI and EGI are compensatory: a high score in one dimension offsets low scores in others. Some conditions are not matters of degree. These rules apply AFTER the SMI orbit is determined and may only LOWER a classification, never raise it. Final Orbit is the more restrictive of the SMI Orbit and any ceiling below.
A4: Rule | B4: Trigger | C4: Ceiling | D4: Rationale
A5: R1 — Concentrated Force Gate | B5: Decision Autonomy >= 4 AND Operational Criticality >= 4 | C5: Edge Orbit | D5: Conjunctive by design. Autonomy without blast radius is a sandboxed agent. Blast radius without autonomy is a consequential workflow under human approval. Neither alone warrants a ceiling. Their combination is the condition a margin cannot safely offset.
A6: R2 — Mandatory Control Floor | B6: Governed or Autonomous Operations Zone, Decision Autonomy >= 3, and MIN(Identity, Authorization, Policy Enforcement) = 0 | C6: Unstable Orbit | D6: Identity, Authorization and Policy Enforcement are prerequisites, not contributors. Observability, Recovery and Assurance describe how well behaviour can be seen, reversed and validated; they cannot substitute for the absence of an identity boundary or an enforcement point.
B7: ...same trigger, MIN(Identity, Authorization, Policy Enforcement) = 1 | C7: Edge Orbit | D7: A nominal control is not an absent one, but it is not a basis for scale.
A8: R3 — Evidence Gate | B8: Governed or Autonomous Operations Zone and Min Evidence Tier < 4 | C8: Edge Orbit | D8: Formalises the Evidence Rule already stated in ASF v1.0 section 10, which the v1.0 workbook implemented only as an advisory string that did not affect classification. This is a ceiling on classification, not an adjustment to EGI: the computed indices remain as scored so the evidence gap stays visible rather than absorbed.
A10: Known approximation in R3
A11: ASF v1.0 section 10 states the rule per dimension — Tier 4 evidence for Policy Enforcement, Observability, Recovery and Assurance. This workbook holds one scalar Min Evidence Tier per agent, so R3 fires whenever ANY dimension falls below Tier 4, not only the four named. It is therefore conservative: it may cap an agent whose four gated dimensions are all Tier 4 while an ungated dimension is lower. Per-dimension evidence tiers are v2 work. The approximation is recorded here rather than hidden in a formula.
A13: Reading the result
A14: Column | B14: Meaning
A15: X — SMI Orbit | B15: Classification from SMI alone. Unchanged from v1.0.
A16: AF — Non-Compensatory Ceiling | B16: Worst orbit permitted by R1, R2, R3. 'None' where no rule fires.
A17: AG — Rule Fired | B17: Which rule applied and on which dimension. Blank where none fired.
A18: AH — Final Orbit | B18: The decision-bearing value. Deployment Decision, Threat Model Required and every Dashboard orbit count key off this column.

Sheet Risk Acceptance
A1: Risk Acceptance Workflow
A2: Required when SMI is negative and deployment continues by exception
A4: Field | B4: Requirement | C4: Value | D4: Evidence / Notes
A5: Business Owner | B5: Named accountable business owner
A6: Technology Owner | B6: Named accountable technical owner
A7: Reason | B7: Why exception is needed
A8: Compensating Controls | B8: Controls that reduce exposure
A9: Expiration Date | B9: No open-ended exceptions
A10: Reassessment Date | B10: Required follow-up date
A11: Residual Risk | B11: Accepted residual risk statement
A12: Approval Record | B12: Governance approval evidence
A13: Decision | B13: Accept / Reject / Defer

Sheet Architecture Review Packet
A1: ASF Architecture Review Packet
A2: Use this checklist in architecture review board or AI governance review
A4: Review Item | B4: Required? | C4: Status | D4: Evidence / Link
A5: Agent profile and business context | B5: Yes
A6: Agent Bill of Materials complete | B6: Yes
A7: AFI, EGI, SMI, orbit classification | B7: Yes
A8: Deployment zone and default decision | B8: Yes
A9: Architecture diagram | B9: Yes
A10: Tool/MCP inventory | B10: Required | C10: Classify tools/MCP servers by read/write capability, action impact, reversibility, auth model, and auditability. | D10: ABOM / Tool registry
A11: Data-source inventory | B11: Yes
A12: Identity model | B12: Yes
A13: Authorization model | B13: Yes
A14: Policy enforcement model | B14: Yes
A15: Observability model | B15: Yes
A16: Recovery and rollback model | B16: Yes
A17: Threat model and mitigation plan | B17: Yes
A18: Evidence tier summary | B18: Yes
A19: Open control gaps | B19: Yes
A20: Risk acceptance record if applicable | B20: Yes
A21: Reassessment date and triggers | B21: Yes

Sheet Deployment Gates
A1: Deployment Gates
A2: Default deployment decision by orbit
A4: Orbit | B4: SMI Range | C4: Default Deployment Decision | D4: Minimum Required Action
A5: Stable Orbit | B5: +40 to +100 | C5: Approved for scale with monitoring | D5: Maintain evidence and reassessment cadence
A6: Controlled Orbit | B6: +15 to +39 | C6: Approved with standard controls | D6: Proceed with standard governance controls
A7: Edge Orbit | B7: -14 to +14 | C7: Pilot, sandbox, or limited production only | D7: Architecture review and active control uplift
A8: Unstable Orbit | B8: -15 to -39 | C8: Do not expand; control uplift required | D8: Increase gravity, reduce force, or formal exception
A9: Critical Orbit | B9: -40 to -100 | C9: Do not deploy without formal exception | D9: Executive risk acceptance and major control uplift

Sheet Control Uplift Planner
A1: Control Uplift Planner
A2: Recommended actions based on weakest Enterprise Gravity dimension
A4: Weakest Gravity Dimension | B4: Recommended Control Uplift | C4: Evidence Target | D4: If Vendor- or Platform-operated
A5: Identity | B5: Assign dedicated workload identity; remove shared credentials; add ownership metadata. | C5: Tier 3+ identity test or Tier 4 runtime identity logs | D5: Request the capability from the vendor and record the commitment and date; or obtain contractual/attestation evidence sufficient to raise the evidence tier; or compensate outside the platform (e.g. enforce at an egress gateway you control); or reduce force instead of raising gravity by narrowing reach, criticality or autonomy; or accept the risk via the s13.1 workflow with expiry.
A6: Authorization | B6: Apply least privilege by tool, workflow, environment, and risk level; add JIT access where needed. | C6: Permission boundary evidence and access logs | D6: Request the capability from the vendor and record the commitment and date; or obtain contractual/attestation evidence sufficient to raise the evidence tier; or compensate outside the platform (e.g. enforce at an egress gateway you control); or reduce force instead of raising gravity by narrowing reach, criticality or autonomy; or accept the risk via the s13.1 workflow with expiry.
A7: Policy Enforcement | B7: Add pre-execution and runtime policy checks; externalize policy decisions where practical. | C7: Policy-as-code tests and runtime decision logs | D7: Request the capability from the vendor and record the commitment and date; or obtain contractual/attestation evidence sufficient to raise the evidence tier; or compensate outside the platform (e.g. enforce at an egress gateway you control); or reduce force instead of raising gravity by narrowing reach, criticality or autonomy; or accept the risk via the s13.1 workflow with expiry.
A8: Observability | B8: Capture prompt, plan, tool-call, policy, approval, action, and outcome traces. | C8: End-to-end trace samples | D8: Request the capability from the vendor and record the commitment and date; or obtain contractual/attestation evidence sufficient to raise the evidence tier; or compensate outside the platform (e.g. enforce at an egress gateway you control); or reduce force instead of raising gravity by narrowing reach, criticality or autonomy; or accept the risk via the s13.1 workflow with expiry.
A9: Governance and Lifecycle | B9: Register agent, model, tools, memory, and policies in catalog; define owner and lifecycle. | C9: Catalog record and approval workflow | D9: Request the capability from the vendor and record the commitment and date; or obtain contractual/attestation evidence sufficient to raise the evidence tier; or compensate outside the platform (e.g. enforce at an egress gateway you control); or reduce force instead of raising gravity by narrowing reach, criticality or autonomy; or accept the risk via the s13.1 workflow with expiry.
A10: Recovery and Resilience | B10: Add kill switch, rollback, circuit breaker, blast-radius isolation, and recovery drills. | C10: Rollback/kill-switch test evidence | D10: Request the capability from the vendor and record the commitment and date; or obtain contractual/attestation evidence sufficient to raise the evidence tier; or compensate outside the platform (e.g. enforce at an egress gateway you control); or reduce force instead of raising gravity by narrowing reach, criticality or autonomy; or accept the risk via the s13.1 workflow with expiry.
A11: Assurance and Evaluation | B11: Add scenario tests, red-team tests, runtime evaluation, drift monitoring, and outcome validation. | C11: Evaluation reports and runtime monitor evidence | D11: Request the capability from the vendor and record the commitment and date; or obtain contractual/attestation evidence sufficient to raise the evidence tier; or compensate outside the platform (e.g. enforce at an egress gateway you control); or reduce force instead of raising gravity by narrowing reach, criticality or autonomy; or accept the risk via the s13.1 workflow with expiry.
A13: Where every uplift path for a mandatory control is vendor-operated and no compensating control exists, the correct outcome is a reduction in force or a formal risk acceptance — not a more favourable score.

Sheet Standards Map
A1: Standards Alignment
A2: ASF complements existing risk, security, management-system, and policy frameworks
A4: Framework | B4: Primary Purpose | C4: ASF Relationship | D4: Source URL
A5: NIST AI RMF | B5: AI risk management through Govern, Map, Measure, Manage | C5: Agent-level stability scoring inside broader AI risk management | D5: https://airc.nist.gov/airmf-resources/airmf/5-sec-core/
A6: ISO/IEC 42001 | B6: AI management-system requirements and guidance | C6: Architecture assessment method for agentic systems under AIMS | D6: https://www.iso.org/standard/42001
A7: OWASP Agentic AI | B7: Threats and mitigations for agentic AI | C7: Input to Assurance, Policy, and threat-model gates | D7: https://genai.owasp.org/resource/agentic-ai-threats-and-mitigations/
A8: OWASP Multi-Agent Threat Modeling | B8: Threat modeling for multi-agent systems | C8: Threat model gate for multi-agent and high-force agents | D8: https://genai.owasp.org/resource/multi-agentic-system-threat-modeling-guide-v1-0/
A9: OPA/Rego | B9: Policy-as-code and externalized policy decisions | C9: Enterprise Gravity component for policy enforcement | D9: https://openpolicyagent.org/docs/policy-language
A10: Zero Trust | B10: Continuous verification of access | C10: Extended to agent identity, context, memory, tools, and actions | D10: https://www.nist.gov/publications/zero-trust-architecture
A118: License | B118: © 2026 Sumir Arora. Licensed under Creative Commons Attribution 4.0 International (CC BY 4.0).

Sheet Change Log
A1: ASF Workbook Change Log - v1.0 Initial Public Release
A2: Version history through v1.0 Initial Public Release
A4: Version | B4: Change | C4: Rationale
A5: 0.2 | B5: Added Basic and Advanced scoring modes | C5: Equal-weight scoring alone is not sufficient for production contexts
A6: 0.2 | B6: Added Evidence Tiers | C6: EGI scores must be supported by control evidence
A7: 0.2 | B7: Added ABOM template | C7: Agents need component and dependency inventory
A8: 0.2 | B8: Added Threat Model gate | C8: High-force agents require security analysis
A9: 0.2 | B9: Added Domain Overlays | C9: Different agent domains require different scoring emphasis
A10: 0.2 | B10: Added Risk Acceptance workflow | C10: Negative SMI requires formal governance path
A11: 0.2 | B11: Added Architecture Review Packet | C11: Makes ASF usable in ARB / governance review
A12: 0.2 | B12: Added Deployment Gates | C12: Connects orbit to decision action
A13: 0.2 | B13: Added dashboard warnings | C13: Surfaces governance debt, missing ABOM, threat model needs
A14: 0.1 | B14: Initial ASF workbook | C14: AFI, EGI, SMI, orbit, rubrics, standards map
A15: 46208 | B15: v0.3 | C15: Added editorial hardening references and real worked example sheet.
A16: 0.4 | B16: Replaced real example with anonymized financial-services client-request automation agent and proofread publication package. | C16: Aligns whitepaper/workbook example with stronger executive-facing use case and removes API-change naming inconsistency.
A17: v0.4 Public RFC | B17: 2026-07-06 | C17: Aligned workbook sample rows with whitepaper summary values; added publication license/status metadata.
A18: v1.0 | B18: Clarified ASF assessment unit as agentic system instance and expanded ABOM/tool-MCP boundary fields. | C18: Prevents misinterpretation that ASF scores a naked model or agent without tools, memory, identity, permissions, and context.
A19: v1.0 | B19: Corrected the Threat Model gate to reference valid orbits (Edge, Unstable, Critical) | C19: Aligned the gate with the five-orbit taxonomy used across the Dashboard and Deployment Gates tabs
A20: v1.1 | B20: 2026-08 | C20: Errata: Dashboard aggregates corrected from rows 5-9 to 5-104 (a sixth agent was excluded from every average and risk counter); IFS replaced with nested IF and XLOOKUP with INDEX/MATCH, since v1.0 stored both without the _xlfn. prefix and they resolved to a name error in Excel; weakest-gravity and highest-force now report tied dimensions; blank rows no longer display Evidence Warning OK. Scoring hardening: three non-compensatory rules added (concentrated force gate, mandatory control floor, evidence gate) with new columns AF Non-Compensatory Ceiling, AG Rule Fired and AH Final Orbit. Review Date moved from AF to AJ. AFI, EGI and SMI formulas unchanged; all five published worked examples retain their v1.0 orbit.
A21: v1.1 | B21: 2026-08 | C21: Operational Reach rubric extended to score the wider of system breadth and consumer population; ABOM gains Control Responsibility (self/platform/vendor-operated) which routes remediation and does not affect scoring; Control Uplift Planner gains uplift paths for vendor-operated controls.

Sheet Real Example
A1: ASF Real Worked Example - Agentic System Instance Assessment
A2: Representative financial-services client-servicing pattern; client, vendor, and architecture identifiers generalized.
A4: Metric | B4: Value | C4: Interpretation
A5: AFI | B5: 60 | C5: Moderate-high force because the agent can touch regulated client and financial-servicing workflows.
A6: EGI | B6: 66 | C6: Meaningful gravity: strong identity, authorization, and runtime policy; weaker runtime assurance and recovery evidence.
A7: SMI | B7: 6 | C7: Edge Orbit: positive but thin stability margin.
A8: Deployment Decision | B8: Pilot / limited production only | C8: Do not expand autonomy until runtime assurance, audit-grade decision provenance, and recovery evidence improve.
A10: ABOM Category | B10: Anonymized Contents
A11: Agent purpose | B11: Interpret client-servicing requests, retrieve client context, prepare or execute servicing actions, and route high-impact requests for advisor approval.
A12: Runtime | B12: Enterprise agent runtime integrated with bounded servicing-action catalog, tool broker, API gateway, and client-servicing workflow.
A13: Tools | B13: Servicing APIs with write access, CRM read access, document service, policy/risk classifier, advisor approval workflow, and notification channel.
A14: Data sources | B14: Client CRM and account systems containing regulated PII and financial data; approved servicing policy and procedure sources.
A15: Memory | B15: Session and task memory only; no long-term, cross-client, or self-maintained enterprise memory.
A16: Identity and authorization | B16: Distinct agent identity with on-behalf-of delegation; tool and environment scopes enforced through gateway and broker controls.
A17: Explicit restrictions | B17: No autonomous high-impact financial action, no cross-client memory, no self-approved exceptions, and no bypass of advisor approval or policy gates.
A20: AFI Dimension | B20: Score | C20: Rationale
A21: Decision Autonomy | B21: 3 | C21: Executes low-impact actions under policy; high-impact financial or client-impacting actions require explicit advisor approval.
A22: Decision Velocity | B22: 3 | C22: Event-driven decisions triggered by client-servicing requests.
A23: Operational Reach | B23: 3 | C23: Touches servicing, CRM, document, and account-related APIs within one business domain.
A24: Operational Criticality | B24: 5 | C24: Incorrect action can affect regulated client financial records, account servicing, compliance exposure, and client trust.
A25: Adaptability | B25: 3 | C25: Generates plans dynamically over retrieved client context, bounded by a defined servicing-action catalog.
A26: Collaboration Complexity | B26: 2 | C26: Collaborates with advisors and workflow systems; no dynamic multi-agent coordination.
A27: Persistence and Memory | B27: 2 | C27: Uses short-term task memory only; no long-term or cross-client memory.
A28: Total | B28: 21 | C28: AFI = 21 / 35 x 100 = 60.0
A31: EGI Dimension | B31: Score | C31: Evidence Tier | D31: Evidence Example
A32: Identity | B32: 4 | C32: 3 | D32: Distinct agent identity with strong authentication and on-behalf-of delegation; tested evidence required to sustain a 4.
A33: Authorization | B33: 4 | C33: 3 | D33: Least privilege by tool and environment, gateway-enforced, with delegated context carried through the request path.
A34: Policy Enforcement | B34: 4 | C34: 4 | D34: Runtime enforcement at the gateway with external inspection at defined control points; runtime-verified.
A35: Observability | B35: 3 | C35: 3 | D35: Gateway and tool-call logs plus partial prompt, plan, and action traces; not yet full audit-grade end-to-end provenance.
A36: Governance and Lifecycle | B36: 3 | C36: 3 | D36: Catalogued with lifecycle approval and reviewed by AI risk, architecture, and change governance.
A37: Recovery and Resilience | B37: 3 | C37: 3 | D37: Gateway kill switch and advisor approval gates exist; rollback or compensating control for executed financial actions is only partly tested.
A38: Assurance and Evaluation | B38: 2 | C38: 2 | D38: Pre-release scenario testing exists; no continuous runtime evaluation, drift detection, or outcome validation yet.
A39: Total | B39: 23 | C39: - | D39: EGI = 23 / 35 x 100 = 66.0
A42: Control Uplift | B42: Reason
A43: Add runtime evaluation for client-servicing decisions | B43: High-impact or ambiguous client requests should be evaluated at runtime before execution or approval routing.
A44: Increase observability to audit-grade decision provenance | B44: Reviewers should reconstruct initiating user, delegated authority, prompt, retrieved client context, plan, policy result, tool call, approval decision, action, and outcome end to end.
A45: Test rollback and compensating controls | B45: Some financial or client-record actions cannot be simply undone; compensating processes must be tested and evidenced.
A46: Keep advisor approval for high-impact workflows | B46: Human accountability remains necessary for transfers, sensitive data changes, exceptions, and elevated-risk servicing actions until SMI improves.
A47: Require threat modeling before autonomy expansion | B47: The agent touches regulated PII and financial workflows; model prompt injection, tool misuse, delegated-authority abuse, approval bypass, and data-exfiltration paths.
A78: © 2026 Sumir Arora. Licensed under Creative Commons Attribution 4.0 International (CC BY 4.0).
